{"arraySize":10000,"runs":0.0502,"arraytype":"Almost-Sorted-0.4","adaptiveSortExecutionTime":151,"insertionSortExecutionTime":8131,"shellSortExecutionTime":240,"heapSortExecutionTime":831,"mergeSortExecutionTime":268,"quickSortExecutionTime":201,"parallelMergeSortExecutionTime":147,"parallelQuickSortExecutionTime":550}
{"arraySize":10000,"runs":0.0543,"arraytype":"Almost-Sorted-0.4","adaptiveSortExecutionTime":161,"insertionSortExecutionTime":8144,"shellSortExecutionTime":241,"heapSortExecutionTime":836,"mergeSortExecutionTime":268,"quickSortExecutionTime":206,"parallelMergeSortExecutionTime":157,"parallelQuickSortExecutionTime":570}
{"arraySize":10000,"runs":0.0519,"arraytype":"Almost-Sorted-0.4","adaptiveSortExecutionTime":171,"insertionSortExecutionTime":8042,"shellSortExecutionTime":241,"heapSortExecutionTime":958,"mergeSortExecutionTime":315,"quickSortExecutionTime":226,"parallelMergeSortExecutionTime":183,"parallelQuickSortExecutionTime":600}
{"arraySize":10000,"runs":0.0517,"arraytype":"Almost-Sorted-0.4","adaptiveSortExecutionTime":144,"insertionSortExecutionTime":8173,"shellSortExecutionTime":241,"heapSortExecutionTime":834,"mergeSortExecutionTime":269,"quickSortExecutionTime":216,"parallelMergeSortExecutionTime":146,"parallelQuickSortExecutionTime":634}
{"arraySize":10000,"runs":0.0526,"arraytype":"Almost-Sorted-0.4","adaptiveSortExecutionTime":159,"insertionSortExecutionTime":8380,"shellSortExecutionTime":240,"heapSortExecutionTime":841,"mergeSortExecutionTime":269,"quickSortExecutionTime":186,"parallelMergeSortExecutionTime":126,"parallelQuickSortExecutionTime":624}
{"arraySize":10000,"runs":0.0505,"arraytype":"Almost-Sorted-0.4","adaptiveSortExecutionTime":152,"insertionSortExecutionTime":8244,"shellSortExecutionTime":264,"heapSortExecutionTime":807,"mergeSortExecutionTime":308,"quickSortExecutionTime":195,"parallelMergeSortExecutionTime":149,"parallelQuickSortExecutionTime":667}
{"arraySize":10000,"runs":0.0508,"arraytype":"Almost-Sorted-0.4","adaptiveSortExecutionTime":158,"insertionSortExecutionTime":8560,"shellSortExecutionTime":243,"heapSortExecutionTime":833,"mergeSortExecutionTime":272,"quickSortExecutionTime":193,"parallelMergeSortExecutionTime":169,"parallelQuickSortExecutionTime":547}
{"arraySize":10000,"runs":0.0518,"arraytype":"Almost-Sorted-0.4","adaptiveSortExecutionTime":140,"insertionSortExecutionTime":8249,"shellSortExecutionTime":243,"heapSortExecutionTime":838,"mergeSortExecutionTime":268,"quickSortExecutionTime":221,"parallelMergeSortExecutionTime":166,"parallelQuickSortExecutionTime":582}
{"arraySize":10000,"runs":0.0523,"arraytype":"Almost-Sorted-0.4","adaptiveSortExecutionTime":167,"insertionSortExecutionTime":8312,"shellSortExecutionTime":250,"heapSortExecutionTime":842,"mergeSortExecutionTime":283,"quickSortExecutionTime":198,"parallelMergeSortExecutionTime":154,"parallelQuickSortExecutionTime":617}
{"arraySize":10000,"runs":0.0533,"arraytype":"Almost-Sorted-0.4","adaptiveSortExecutionTime":168,"insertionSortExecutionTime":8250,"shellSortExecutionTime":263,"heapSortExecutionTime":858,"mergeSortExecutionTime":272,"quickSortExecutionTime":194,"parallelMergeSortExecutionTime":147,"parallelQuickSortExecutionTime":591}
{"arraySize":10000,"runs":0.0524,"arraytype":"Almost-Sorted-0.4","adaptiveSortExecutionTime":138,"insertionSortExecutionTime":8261,"shellSortExecutionTime":242,"heapSortExecutionTime":878,"mergeSortExecutionTime":267,"quickSortExecutionTime":188,"parallelMergeSortExecutionTime":156,"parallelQuickSortExecutionTime":588}
{"arraySize":10000,"runs":0.055,"arraytype":"Almost-Sorted-0.4","adaptiveSortExecutionTime":164,"insertionSortExecutionTime":7999,"shellSortExecutionTime":241,"heapSortExecutionTime":830,"mergeSortExecutionTime":268,"quickSortExecutionTime":195,"parallelMergeSortExecutionTime":144,"parallelQuickSortExecutionTime":598}
{"arraySize":10000,"runs":0.0492,"arraytype":"Almost-Sorted-0.4","adaptiveSortExecutionTime":152,"insertionSortExecutionTime":8194,"shellSortExecutionTime":253,"heapSortExecutionTime":838,"mergeSortExecutionTime":296,"quickSortExecutionTime":200,"parallelMergeSortExecutionTime":179,"parallelQuickSortExecutionTime":647}
{"arraySize":10000,"runs":0.0539,"arraytype":"Almost-Sorted-0.4","adaptiveSortExecutionTime":150,"insertionSortExecutionTime":8231,"shellSortExecutionTime":242,"heapSortExecutionTime":830,"mergeSortExecutionTime":268,"quickSortExecutionTime":208,"parallelMergeSortExecutionTime":145,"parallelQuickSortExecutionTime":587}
{"arraySize":10000,"runs":0.0502,"arraytype":"Almost-Sorted-0.4","adaptiveSortExecutionTime":157,"insertionSortExecutionTime":8146,"shellSortExecutionTime":242,"heapSortExecutionTime":833,"mergeSortExecutionTime":268,"quickSortExecutionTime":217,"parallelMergeSortExecutionTime":149,"parallelQuickSortExecutionTime":587}
{"arraySize":10000,"runs":0.0559,"arraytype":"Almost-Sorted-0.4","adaptiveSortExecutionTime":112,"insertionSortExecutionTime":8246,"shellSortExecutionTime":244,"heapSortExecutionTime":845,"mergeSortExecutionTime":291,"quickSortExecutionTime":195,"parallelMergeSortExecutionTime":160,"parallelQuickSortExecutionTime":558}
{"arraySize":10000,"runs":0.0507,"arraytype":"Almost-Sorted-0.4","adaptiveSortExecutionTime":141,"insertionSortExecutionTime":8133,"shellSortExecutionTime":243,"heapSortExecutionTime":833,"mergeSortExecutionTime":269,"quickSortExecutionTime":230,"parallelMergeSortExecutionTime":156,"parallelQuickSortExecutionTime":529}
{"arraySize":10000,"runs":0.0527,"arraytype":"Almost-Sorted-0.4","adaptiveSortExecutionTime":116,"insertionSortExecutionTime":8425,"shellSortExecutionTime":251,"heapSortExecutionTime":835,"mergeSortExecutionTime":284,"quickSortExecutionTime":201,"parallelMergeSortExecutionTime":110,"parallelQuickSortExecutionTime":553}
{"arraySize":10000,"runs":0.0503,"arraytype":"Almost-Sorted-0.4","adaptiveSortExecutionTime":575,"insertionSortExecutionTime":8327,"shellSortExecutionTime":261,"heapSortExecutionTime":841,"mergeSortExecutionTime":268,"quickSortExecutionTime":209,"parallelMergeSortExecutionTime":156,"parallelQuickSortExecutionTime":550}
{"arraySize":10000,"runs":0.0523,"arraytype":"Almost-Sorted-0.4","adaptiveSortExecutionTime":149,"insertionSortExecutionTime":8107,"shellSortExecutionTime":242,"heapSortExecutionTime":885,"mergeSortExecutionTime":268,"quickSortExecutionTime":198,"parallelMergeSortExecutionTime":131,"parallelQuickSortExecutionTime":546}
{"arraySize":10000,"runs":0.0555,"arraytype":"Almost-Sorted-0.4","adaptiveSortExecutionTime":138,"insertionSortExecutionTime":8237,"shellSortExecutionTime":252,"heapSortExecutionTime":842,"mergeSortExecutionTime":277,"quickSortExecutionTime":204,"parallelMergeSortExecutionTime":105,"parallelQuickSortExecutionTime":507}
{"arraySize":10000,"runs":0.0515,"arraytype":"Almost-Sorted-0.4","adaptiveSortExecutionTime":137,"insertionSortExecutionTime":8314,"shellSortExecutionTime":250,"heapSortExecutionTime":842,"mergeSortExecutionTime":281,"quickSortExecutionTime":218,"parallelMergeSortExecutionTime":142,"parallelQuickSortExecutionTime":523}
{"arraySize":10000,"runs":0.0551,"arraytype":"Almost-Sorted-0.4","adaptiveSortExecutionTime":117,"insertionSortExecutionTime":8232,"shellSortExecutionTime":243,"heapSortExecutionTime":828,"mergeSortExecutionTime":294,"quickSortExecutionTime":189,"parallelMergeSortExecutionTime":146,"parallelQuickSortExecutionTime":536}
{"arraySize":10000,"runs":0.0515,"arraytype":"Almost-Sorted-0.4","adaptiveSortExecutionTime":150,"insertionSortExecutionTime":8680,"shellSortExecutionTime":240,"heapSortExecutionTime":836,"mergeSortExecutionTime":267,"quickSortExecutionTime":199,"parallelMergeSortExecutionTime":156,"parallelQuickSortExecutionTime":566}
{"arraySize":10000,"runs":0.0533,"arraytype":"Almost-Sorted-0.4","adaptiveSortExecutionTime":153,"insertionSortExecutionTime":8128,"shellSortExecutionTime":243,"heapSortExecutionTime":831,"mergeSortExecutionTime":268,"quickSortExecutionTime":197,"parallelMergeSortExecutionTime":145,"parallelQuickSortExecutionTime":571}
{"arraySize":10000,"runs":0.05,"arraytype":"Almost-Sorted-0.4","adaptiveSortExecutionTime":161,"insertionSortExecutionTime":8227,"shellSortExecutionTime":250,"heapSortExecutionTime":860,"mergeSortExecutionTime":268,"quickSortExecutionTime":198,"parallelMergeSortExecutionTime":144,"parallelQuickSortExecutionTime":599}
{"arraySize":10000,"runs":0.0543,"arraytype":"Almost-Sorted-0.4","adaptiveSortExecutionTime":120,"insertionSortExecutionTime":8027,"shellSortExecutionTime":241,"heapSortExecutionTime":835,"mergeSortExecutionTime":268,"quickSortExecutionTime":220,"parallelMergeSortExecutionTime":153,"parallelQuickSortExecutionTime":521}
{"arraySize":10000,"runs":0.053,"arraytype":"Almost-Sorted-0.4","adaptiveSortExecutionTime":135,"insertionSortExecutionTime":8187,"shellSortExecutionTime":243,"heapSortExecutionTime":828,"mergeSortExecutionTime":271,"quickSortExecutionTime":208,"parallelMergeSortExecutionTime":157,"parallelQuickSortExecutionTime":569}
{"arraySize":10000,"runs":0.0544,"arraytype":"Almost-Sorted-0.4","adaptiveSortExecutionTime":116,"insertionSortExecutionTime":8185,"shellSortExecutionTime":253,"heapSortExecutionTime":840,"mergeSortExecutionTime":282,"quickSortExecutionTime":195,"parallelMergeSortExecutionTime":129,"parallelQuickSortExecutionTime":565}
{"arraySize":10000,"runs":0.054,"arraytype":"Almost-Sorted-0.4","adaptiveSortExecutionTime":133,"insertionSortExecutionTime":8181,"shellSortExecutionTime":241,"heapSortExecutionTime":834,"mergeSortExecutionTime":268,"quickSortExecutionTime":189,"parallelMergeSortExecutionTime":146,"parallelQuickSortExecutionTime":529}
{"arraySize":10000,"runs":0.0497,"arraytype":"Almost-Sorted-0.4","adaptiveSortExecutionTime":117,"insertionSortExecutionTime":8341,"shellSortExecutionTime":250,"heapSortExecutionTime":839,"mergeSortExecutionTime":277,"quickSortExecutionTime":203,"parallelMergeSortExecutionTime":131,"parallelQuickSortExecutionTime":511}
{"arraySize":10000,"runs":0.0551,"arraytype":"Almost-Sorted-0.4","adaptiveSortExecutionTime":143,"insertionSortExecutionTime":8062,"shellSortExecutionTime":242,"heapSortExecutionTime":833,"mergeSortExecutionTime":273,"quickSortExecutionTime":216,"parallelMergeSortExecutionTime":145,"parallelQuickSortExecutionTime":520}
{"arraySize":10000,"runs":0.0523,"arraytype":"Almost-Sorted-0.4","adaptiveSortExecutionTime":112,"insertionSortExecutionTime":8125,"shellSortExecutionTime":250,"heapSortExecutionTime":843,"mergeSortExecutionTime":277,"quickSortExecutionTime":224,"parallelMergeSortExecutionTime":113,"parallelQuickSortExecutionTime":553}
{"arraySize":10000,"runs":0.0547,"arraytype":"Almost-Sorted-0.4","adaptiveSortExecutionTime":144,"insertionSortExecutionTime":8056,"shellSortExecutionTime":240,"heapSortExecutionTime":830,"mergeSortExecutionTime":269,"quickSortExecutionTime":204,"parallelMergeSortExecutionTime":166,"parallelQuickSortExecutionTime":518}
{"arraySize":10000,"runs":0.0539,"arraytype":"Almost-Sorted-0.4","adaptiveSortExecutionTime":120,"insertionSortExecutionTime":8333,"shellSortExecutionTime":249,"heapSortExecutionTime":834,"mergeSortExecutionTime":277,"quickSortExecutionTime":203,"parallelMergeSortExecutionTime":123,"parallelQuickSortExecutionTime":545}
{"arraySize":10000,"runs":0.0506,"arraytype":"Almost-Sorted-0.4","adaptiveSortExecutionTime":118,"insertionSortExecutionTime":8115,"shellSortExecutionTime":241,"heapSortExecutionTime":830,"mergeSortExecutionTime":268,"quickSortExecutionTime":203,"parallelMergeSortExecutionTime":531,"parallelQuickSortExecutionTime":501}
{"arraySize":10000,"runs":0.0545,"arraytype":"Almost-Sorted-0.4","adaptiveSortExecutionTime":149,"insertionSortExecutionTime":8037,"shellSortExecutionTime":240,"heapSortExecutionTime":837,"mergeSortExecutionTime":268,"quickSortExecutionTime":220,"parallelMergeSortExecutionTime":154,"parallelQuickSortExecutionTime":494}
{"arraySize":10000,"runs":0.0553,"arraytype":"Almost-Sorted-0.4","adaptiveSortExecutionTime":142,"insertionSortExecutionTime":8321,"shellSortExecutionTime":248,"heapSortExecutionTime":841,"mergeSortExecutionTime":298,"quickSortExecutionTime":210,"parallelMergeSortExecutionTime":107,"parallelQuickSortExecutionTime":509}
{"arraySize":10000,"runs":0.0537,"arraytype":"Almost-Sorted-0.4","adaptiveSortExecutionTime":117,"insertionSortExecutionTime":8359,"shellSortExecutionTime":255,"heapSortExecutionTime":855,"mergeSortExecutionTime":277,"quickSortExecutionTime":197,"parallelMergeSortExecutionTime":133,"parallelQuickSortExecutionTime":523}
{"arraySize":10000,"runs":0.0576,"arraytype":"Almost-Sorted-0.4","adaptiveSortExecutionTime":116,"insertionSortExecutionTime":8185,"shellSortExecutionTime":243,"heapSortExecutionTime":836,"mergeSortExecutionTime":268,"quickSortExecutionTime":190,"parallelMergeSortExecutionTime":138,"parallelQuickSortExecutionTime":506}
{"arraySize":10000,"runs":0.0521,"arraytype":"Almost-Sorted-0.4","adaptiveSortExecutionTime":143,"insertionSortExecutionTime":8109,"shellSortExecutionTime":242,"heapSortExecutionTime":834,"mergeSortExecutionTime":269,"quickSortExecutionTime":196,"parallelMergeSortExecutionTime":144,"parallelQuickSortExecutionTime":519}
{"arraySize":10000,"runs":0.0519,"arraytype":"Almost-Sorted-0.4","adaptiveSortExecutionTime":146,"insertionSortExecutionTime":8097,"shellSortExecutionTime":249,"heapSortExecutionTime":845,"mergeSortExecutionTime":277,"quickSortExecutionTime":200,"parallelMergeSortExecutionTime":108,"parallelQuickSortExecutionTime":519}
{"arraySize":10000,"runs":0.0522,"arraytype":"Almost-Sorted-0.4","adaptiveSortExecutionTime":119,"insertionSortExecutionTime":8125,"shellSortExecutionTime":259,"heapSortExecutionTime":846,"mergeSortExecutionTime":277,"quickSortExecutionTime":195,"parallelMergeSortExecutionTime":108,"parallelQuickSortExecutionTime":517}
{"arraySize":10000,"runs":0.0511,"arraytype":"Almost-Sorted-0.4","adaptiveSortExecutionTime":117,"insertionSortExecutionTime":8235,"shellSortExecutionTime":266,"heapSortExecutionTime":808,"mergeSortExecutionTime":280,"quickSortExecutionTime":188,"parallelMergeSortExecutionTime":154,"parallelQuickSortExecutionTime":532}
{"arraySize":10000,"runs":0.0508,"arraytype":"Almost-Sorted-0.4","adaptiveSortExecutionTime":143,"insertionSortExecutionTime":8196,"shellSortExecutionTime":251,"heapSortExecutionTime":845,"mergeSortExecutionTime":284,"quickSortExecutionTime":217,"parallelMergeSortExecutionTime":128,"parallelQuickSortExecutionTime":539}
{"arraySize":10000,"runs":0.0553,"arraytype":"Almost-Sorted-0.4","adaptiveSortExecutionTime":150,"insertionSortExecutionTime":8311,"shellSortExecutionTime":253,"heapSortExecutionTime":838,"mergeSortExecutionTime":277,"quickSortExecutionTime":213,"parallelMergeSortExecutionTime":124,"parallelQuickSortExecutionTime":620}
{"arraySize":10000,"runs":0.0543,"arraytype":"Almost-Sorted-0.4","adaptiveSortExecutionTime":136,"insertionSortExecutionTime":8384,"shellSortExecutionTime":270,"heapSortExecutionTime":884,"mergeSortExecutionTime":269,"quickSortExecutionTime":227,"parallelMergeSortExecutionTime":142,"parallelQuickSortExecutionTime":679}
{"arraySize":10000,"runs":0.0518,"arraytype":"Almost-Sorted-0.4","adaptiveSortExecutionTime":126,"insertionSortExecutionTime":8340,"shellSortExecutionTime":252,"heapSortExecutionTime":846,"mergeSortExecutionTime":282,"quickSortExecutionTime":213,"parallelMergeSortExecutionTime":113,"parallelQuickSortExecutionTime":564}
{"arraySize":10000,"runs":0.0525,"arraytype":"Almost-Sorted-0.4","adaptiveSortExecutionTime":145,"insertionSortExecutionTime":8394,"shellSortExecutionTime":252,"heapSortExecutionTime":838,"mergeSortExecutionTime":283,"quickSortExecutionTime":208,"parallelMergeSortExecutionTime":137,"parallelQuickSortExecutionTime":590}
{"arraySize":10000,"runs":0.055,"arraytype":"Almost-Sorted-0.4","adaptiveSortExecutionTime":108,"insertionSortExecutionTime":8155,"shellSortExecutionTime":253,"heapSortExecutionTime":847,"mergeSortExecutionTime":288,"quickSortExecutionTime":208,"parallelMergeSortExecutionTime":143,"parallelQuickSortExecutionTime":584}
{"arraySize":10000,"runs":0.0505,"arraytype":"Almost-Sorted-0.4","adaptiveSortExecutionTime":165,"insertionSortExecutionTime":10305,"shellSortExecutionTime":247,"heapSortExecutionTime":850,"mergeSortExecutionTime":277,"quickSortExecutionTime":204,"parallelMergeSortExecutionTime":134,"parallelQuickSortExecutionTime":563}
{"arraySize":10000,"runs":0.0542,"arraytype":"Almost-Sorted-0.4","adaptiveSortExecutionTime":121,"insertionSortExecutionTime":8373,"shellSortExecutionTime":252,"heapSortExecutionTime":837,"mergeSortExecutionTime":279,"quickSortExecutionTime":222,"parallelMergeSortExecutionTime":114,"parallelQuickSortExecutionTime":514}
{"arraySize":10000,"runs":0.0591,"arraytype":"Almost-Sorted-0.4","adaptiveSortExecutionTime":130,"insertionSortExecutionTime":8156,"shellSortExecutionTime":249,"heapSortExecutionTime":847,"mergeSortExecutionTime":282,"quickSortExecutionTime":195,"parallelMergeSortExecutionTime":101,"parallelQuickSortExecutionTime":478}
{"arraySize":10000,"runs":0.053,"arraytype":"Almost-Sorted-0.4","adaptiveSortExecutionTime":106,"insertionSortExecutionTime":8329,"shellSortExecutionTime":243,"heapSortExecutionTime":963,"mergeSortExecutionTime":277,"quickSortExecutionTime":221,"parallelMergeSortExecutionTime":122,"parallelQuickSortExecutionTime":541}
{"arraySize":10000,"runs":0.0548,"arraytype":"Almost-Sorted-0.4","adaptiveSortExecutionTime":108,"insertionSortExecutionTime":8326,"shellSortExecutionTime":239,"heapSortExecutionTime":832,"mergeSortExecutionTime":268,"quickSortExecutionTime":236,"parallelMergeSortExecutionTime":140,"parallelQuickSortExecutionTime":541}
{"arraySize":10000,"runs":0.0546,"arraytype":"Almost-Sorted-0.4","adaptiveSortExecutionTime":115,"insertionSortExecutionTime":8048,"shellSortExecutionTime":241,"heapSortExecutionTime":831,"mergeSortExecutionTime":268,"quickSortExecutionTime":199,"parallelMergeSortExecutionTime":144,"parallelQuickSortExecutionTime":543}
{"arraySize":10000,"runs":0.052,"arraytype":"Almost-Sorted-0.4","adaptiveSortExecutionTime":103,"insertionSortExecutionTime":8063,"shellSortExecutionTime":242,"heapSortExecutionTime":830,"mergeSortExecutionTime":269,"quickSortExecutionTime":201,"parallelMergeSortExecutionTime":149,"parallelQuickSortExecutionTime":485}
{"arraySize":10000,"runs":0.0531,"arraytype":"Almost-Sorted-0.4","adaptiveSortExecutionTime":134,"insertionSortExecutionTime":8215,"shellSortExecutionTime":250,"heapSortExecutionTime":842,"mergeSortExecutionTime":277,"quickSortExecutionTime":199,"parallelMergeSortExecutionTime":132,"parallelQuickSortExecutionTime":543}
{"arraySize":10000,"runs":0.0533,"arraytype":"Almost-Sorted-0.4","adaptiveSortExecutionTime":119,"insertionSortExecutionTime":8218,"shellSortExecutionTime":254,"heapSortExecutionTime":839,"mergeSortExecutionTime":276,"quickSortExecutionTime":198,"parallelMergeSortExecutionTime":135,"parallelQuickSortExecutionTime":550}
{"arraySize":10000,"runs":0.0517,"arraytype":"Almost-Sorted-0.4","adaptiveSortExecutionTime":136,"insertionSortExecutionTime":8035,"shellSortExecutionTime":261,"heapSortExecutionTime":862,"mergeSortExecutionTime":282,"quickSortExecutionTime":195,"parallelMergeSortExecutionTime":160,"parallelQuickSortExecutionTime":626}
{"arraySize":10000,"runs":0.0548,"arraytype":"Almost-Sorted-0.4","adaptiveSortExecutionTime":117,"insertionSortExecutionTime":8162,"shellSortExecutionTime":248,"heapSortExecutionTime":839,"mergeSortExecutionTime":277,"quickSortExecutionTime":205,"parallelMergeSortExecutionTime":107,"parallelQuickSortExecutionTime":487}
{"arraySize":10000,"runs":0.0566,"arraytype":"Almost-Sorted-0.4","adaptiveSortExecutionTime":149,"insertionSortExecutionTime":8323,"shellSortExecutionTime":247,"heapSortExecutionTime":842,"mergeSortExecutionTime":279,"quickSortExecutionTime":198,"parallelMergeSortExecutionTime":128,"parallelQuickSortExecutionTime":526}
{"arraySize":10000,"runs":0.0536,"arraytype":"Almost-Sorted-0.4","adaptiveSortExecutionTime":126,"insertionSortExecutionTime":8268,"shellSortExecutionTime":250,"heapSortExecutionTime":841,"mergeSortExecutionTime":277,"quickSortExecutionTime":202,"parallelMergeSortExecutionTime":105,"parallelQuickSortExecutionTime":483}
{"arraySize":10000,"runs":0.05,"arraytype":"Almost-Sorted-0.4","adaptiveSortExecutionTime":125,"insertionSortExecutionTime":8303,"shellSortExecutionTime":250,"heapSortExecutionTime":851,"mergeSortExecutionTime":278,"quickSortExecutionTime":214,"parallelMergeSortExecutionTime":104,"parallelQuickSortExecutionTime":525}
{"arraySize":10000,"runs":0.0536,"arraytype":"Almost-Sorted-0.4","adaptiveSortExecutionTime":140,"insertionSortExecutionTime":8503,"shellSortExecutionTime":247,"heapSortExecutionTime":853,"mergeSortExecutionTime":279,"quickSortExecutionTime":206,"parallelMergeSortExecutionTime":112,"parallelQuickSortExecutionTime":553}
{"arraySize":10000,"runs":0.0531,"arraytype":"Almost-Sorted-0.4","adaptiveSortExecutionTime":139,"insertionSortExecutionTime":8271,"shellSortExecutionTime":303,"heapSortExecutionTime":961,"mergeSortExecutionTime":269,"quickSortExecutionTime":219,"parallelMergeSortExecutionTime":147,"parallelQuickSortExecutionTime":587}
{"arraySize":10000,"runs":0.0525,"arraytype":"Almost-Sorted-0.4","adaptiveSortExecutionTime":142,"insertionSortExecutionTime":8187,"shellSortExecutionTime":250,"heapSortExecutionTime":855,"mergeSortExecutionTime":278,"quickSortExecutionTime":209,"parallelMergeSortExecutionTime":135,"parallelQuickSortExecutionTime":526}
{"arraySize":10000,"runs":0.0506,"arraytype":"Almost-Sorted-0.4","adaptiveSortExecutionTime":152,"insertionSortExecutionTime":8147,"shellSortExecutionTime":241,"heapSortExecutionTime":832,"mergeSortExecutionTime":272,"quickSortExecutionTime":218,"parallelMergeSortExecutionTime":145,"parallelQuickSortExecutionTime":595}
{"arraySize":10000,"runs":0.0548,"arraytype":"Almost-Sorted-0.4","adaptiveSortExecutionTime":142,"insertionSortExecutionTime":8202,"shellSortExecutionTime":243,"heapSortExecutionTime":839,"mergeSortExecutionTime":291,"quickSortExecutionTime":194,"parallelMergeSortExecutionTime":154,"parallelQuickSortExecutionTime":543}
{"arraySize":10000,"runs":0.053,"arraytype":"Almost-Sorted-0.4","adaptiveSortExecutionTime":127,"insertionSortExecutionTime":8302,"shellSortExecutionTime":250,"heapSortExecutionTime":843,"mergeSortExecutionTime":281,"quickSortExecutionTime":219,"parallelMergeSortExecutionTime":142,"parallelQuickSortExecutionTime":548}
{"arraySize":10000,"runs":0.0537,"arraytype":"Almost-Sorted-0.4","adaptiveSortExecutionTime":163,"insertionSortExecutionTime":8426,"shellSortExecutionTime":250,"heapSortExecutionTime":845,"mergeSortExecutionTime":281,"quickSortExecutionTime":195,"parallelMergeSortExecutionTime":133,"parallelQuickSortExecutionTime":505}
{"arraySize":10000,"runs":0.0521,"arraytype":"Almost-Sorted-0.4","adaptiveSortExecutionTime":142,"insertionSortExecutionTime":8265,"shellSortExecutionTime":252,"heapSortExecutionTime":830,"mergeSortExecutionTime":280,"quickSortExecutionTime":195,"parallelMergeSortExecutionTime":104,"parallelQuickSortExecutionTime":547}
{"arraySize":10000,"runs":0.0519,"arraytype":"Almost-Sorted-0.4","adaptiveSortExecutionTime":115,"insertionSortExecutionTime":8118,"shellSortExecutionTime":267,"heapSortExecutionTime":892,"mergeSortExecutionTime":279,"quickSortExecutionTime":208,"parallelMergeSortExecutionTime":135,"parallelQuickSortExecutionTime":545}
{"arraySize":10000,"runs":0.0498,"arraytype":"Almost-Sorted-0.4","adaptiveSortExecutionTime":151,"insertionSortExecutionTime":7967,"shellSortExecutionTime":240,"heapSortExecutionTime":829,"mergeSortExecutionTime":290,"quickSortExecutionTime":192,"parallelMergeSortExecutionTime":155,"parallelQuickSortExecutionTime":546}
{"arraySize":10000,"runs":0.0545,"arraytype":"Almost-Sorted-0.4","adaptiveSortExecutionTime":139,"insertionSortExecutionTime":8129,"shellSortExecutionTime":259,"heapSortExecutionTime":816,"mergeSortExecutionTime":291,"quickSortExecutionTime":194,"parallelMergeSortExecutionTime":144,"parallelQuickSortExecutionTime":521}
{"arraySize":10000,"runs":0.0512,"arraytype":"Almost-Sorted-0.4","adaptiveSortExecutionTime":151,"insertionSortExecutionTime":8133,"shellSortExecutionTime":243,"heapSortExecutionTime":828,"mergeSortExecutionTime":293,"quickSortExecutionTime":198,"parallelMergeSortExecutionTime":144,"parallelQuickSortExecutionTime":565}
{"arraySize":10000,"runs":0.0491,"arraytype":"Almost-Sorted-0.4","adaptiveSortExecutionTime":140,"insertionSortExecutionTime":8099,"shellSortExecutionTime":245,"heapSortExecutionTime":841,"mergeSortExecutionTime":305,"quickSortExecutionTime":233,"parallelMergeSortExecutionTime":133,"parallelQuickSortExecutionTime":546}
{"arraySize":10000,"runs":0.0532,"arraytype":"Almost-Sorted-0.4","adaptiveSortExecutionTime":155,"insertionSortExecutionTime":8256,"shellSortExecutionTime":257,"heapSortExecutionTime":846,"mergeSortExecutionTime":277,"quickSortExecutionTime":220,"parallelMergeSortExecutionTime":114,"parallelQuickSortExecutionTime":526}
{"arraySize":10000,"runs":0.051,"arraytype":"Almost-Sorted-0.4","adaptiveSortExecutionTime":105,"insertionSortExecutionTime":8140,"shellSortExecutionTime":249,"heapSortExecutionTime":843,"mergeSortExecutionTime":277,"quickSortExecutionTime":207,"parallelMergeSortExecutionTime":108,"parallelQuickSortExecutionTime":563}
{"arraySize":10000,"runs":0.052,"arraytype":"Almost-Sorted-0.4","adaptiveSortExecutionTime":154,"insertionSortExecutionTime":8546,"shellSortExecutionTime":331,"heapSortExecutionTime":847,"mergeSortExecutionTime":289,"quickSortExecutionTime":218,"parallelMergeSortExecutionTime":144,"parallelQuickSortExecutionTime":640}
{"arraySize":10000,"runs":0.052,"arraytype":"Almost-Sorted-0.4","adaptiveSortExecutionTime":164,"insertionSortExecutionTime":10782,"shellSortExecutionTime":242,"heapSortExecutionTime":828,"mergeSortExecutionTime":292,"quickSortExecutionTime":201,"parallelMergeSortExecutionTime":160,"parallelQuickSortExecutionTime":625}
{"arraySize":10000,"runs":0.0554,"arraytype":"Almost-Sorted-0.4","adaptiveSortExecutionTime":159,"insertionSortExecutionTime":8199,"shellSortExecutionTime":253,"heapSortExecutionTime":816,"mergeSortExecutionTime":290,"quickSortExecutionTime":193,"parallelMergeSortExecutionTime":145,"parallelQuickSortExecutionTime":582}
{"arraySize":10000,"runs":0.0507,"arraytype":"Almost-Sorted-0.4","adaptiveSortExecutionTime":144,"insertionSortExecutionTime":8255,"shellSortExecutionTime":268,"heapSortExecutionTime":825,"mergeSortExecutionTime":278,"quickSortExecutionTime":204,"parallelMergeSortExecutionTime":157,"parallelQuickSortExecutionTime":548}
{"arraySize":10000,"runs":0.0549,"arraytype":"Almost-Sorted-0.4","adaptiveSortExecutionTime":146,"insertionSortExecutionTime":8000,"shellSortExecutionTime":262,"heapSortExecutionTime":805,"mergeSortExecutionTime":310,"quickSortExecutionTime":206,"parallelMergeSortExecutionTime":145,"parallelQuickSortExecutionTime":589}
{"arraySize":10000,"runs":0.057,"arraytype":"Almost-Sorted-0.4","adaptiveSortExecutionTime":146,"insertionSortExecutionTime":8109,"shellSortExecutionTime":262,"heapSortExecutionTime":812,"mergeSortExecutionTime":302,"quickSortExecutionTime":211,"parallelMergeSortExecutionTime":155,"parallelQuickSortExecutionTime":514}
{"arraySize":10000,"runs":0.0525,"arraytype":"Almost-Sorted-0.4","adaptiveSortExecutionTime":110,"insertionSortExecutionTime":8294,"shellSortExecutionTime":251,"heapSortExecutionTime":837,"mergeSortExecutionTime":277,"quickSortExecutionTime":203,"parallelMergeSortExecutionTime":110,"parallelQuickSortExecutionTime":523}
{"arraySize":10000,"runs":0.0479,"arraytype":"Almost-Sorted-0.4","adaptiveSortExecutionTime":144,"insertionSortExecutionTime":8184,"shellSortExecutionTime":243,"heapSortExecutionTime":828,"mergeSortExecutionTime":271,"quickSortExecutionTime":216,"parallelMergeSortExecutionTime":143,"parallelQuickSortExecutionTime":587}
{"arraySize":10000,"runs":0.055,"arraytype":"Almost-Sorted-0.4","adaptiveSortExecutionTime":111,"insertionSortExecutionTime":8613,"shellSortExecutionTime":273,"heapSortExecutionTime":845,"mergeSortExecutionTime":278,"quickSortExecutionTime":216,"parallelMergeSortExecutionTime":152,"parallelQuickSortExecutionTime":562}
{"arraySize":10000,"runs":0.0552,"arraytype":"Almost-Sorted-0.4","adaptiveSortExecutionTime":137,"insertionSortExecutionTime":8162,"shellSortExecutionTime":250,"heapSortExecutionTime":852,"mergeSortExecutionTime":277,"quickSortExecutionTime":201,"parallelMergeSortExecutionTime":121,"parallelQuickSortExecutionTime":554}
{"arraySize":10000,"runs":0.0571,"arraytype":"Almost-Sorted-0.4","adaptiveSortExecutionTime":117,"insertionSortExecutionTime":8275,"shellSortExecutionTime":249,"heapSortExecutionTime":836,"mergeSortExecutionTime":281,"quickSortExecutionTime":201,"parallelMergeSortExecutionTime":132,"parallelQuickSortExecutionTime":637}
{"arraySize":10000,"runs":0.0557,"arraytype":"Almost-Sorted-0.4","adaptiveSortExecutionTime":120,"insertionSortExecutionTime":8898,"shellSortExecutionTime":238,"heapSortExecutionTime":838,"mergeSortExecutionTime":268,"quickSortExecutionTime":192,"parallelMergeSortExecutionTime":153,"parallelQuickSortExecutionTime":468}
{"arraySize":10000,"runs":0.0482,"arraytype":"Almost-Sorted-0.4","adaptiveSortExecutionTime":119,"insertionSortExecutionTime":8415,"shellSortExecutionTime":250,"heapSortExecutionTime":849,"mergeSortExecutionTime":279,"quickSortExecutionTime":199,"parallelMergeSortExecutionTime":105,"parallelQuickSortExecutionTime":478}
{"arraySize":10000,"runs":0.0537,"arraytype":"Almost-Sorted-0.4","adaptiveSortExecutionTime":161,"insertionSortExecutionTime":8113,"shellSortExecutionTime":249,"heapSortExecutionTime":839,"mergeSortExecutionTime":277,"quickSortExecutionTime":207,"parallelMergeSortExecutionTime":116,"parallelQuickSortExecutionTime":499}
{"arraySize":10000,"runs":0.0528,"arraytype":"Almost-Sorted-0.4","adaptiveSortExecutionTime":115,"insertionSortExecutionTime":8191,"shellSortExecutionTime":250,"heapSortExecutionTime":855,"mergeSortExecutionTime":279,"quickSortExecutionTime":209,"parallelMergeSortExecutionTime":106,"parallelQuickSortExecutionTime":478}
{"arraySize":10000,"runs":0.053,"arraytype":"Almost-Sorted-0.4","adaptiveSortExecutionTime":124,"insertionSortExecutionTime":8195,"shellSortExecutionTime":250,"heapSortExecutionTime":857,"mergeSortExecutionTime":280,"quickSortExecutionTime":198,"parallelMergeSortExecutionTime":113,"parallelQuickSortExecutionTime":484}
{"arraySize":10000,"runs":0.0516,"arraytype":"Almost-Sorted-0.4","adaptiveSortExecutionTime":124,"insertionSortExecutionTime":8267,"shellSortExecutionTime":240,"heapSortExecutionTime":837,"mergeSortExecutionTime":270,"quickSortExecutionTime":189,"parallelMergeSortExecutionTime":152,"parallelQuickSortExecutionTime":587}
{"arraySize":10000,"runs":0.0552,"arraytype":"Almost-Sorted-0.4","adaptiveSortExecutionTime":116,"insertionSortExecutionTime":8430,"shellSortExecutionTime":251,"heapSortExecutionTime":894,"mergeSortExecutionTime":278,"quickSortExecutionTime":199,"parallelMergeSortExecutionTime":107,"parallelQuickSortExecutionTime":563}
{"arraySize":10000,"runs":0.0505,"arraytype":"Almost-Sorted-0.4","adaptiveSortExecutionTime":116,"insertionSortExecutionTime":8172,"shellSortExecutionTime":240,"heapSortExecutionTime":832,"mergeSortExecutionTime":269,"quickSortExecutionTime":220,"parallelMergeSortExecutionTime":152,"parallelQuickSortExecutionTime":528}
{"arraySize":10000,"runs":0.0515,"arraytype":"Almost-Sorted-0.4","adaptiveSortExecutionTime":142,"insertionSortExecutionTime":8178,"shellSortExecutionTime":243,"heapSortExecutionTime":836,"mergeSortExecutionTime":270,"quickSortExecutionTime":230,"parallelMergeSortExecutionTime":143,"parallelQuickSortExecutionTime":523}
{"arraySize":10000,"runs":0.0562,"arraytype":"Almost-Sorted-0.4","adaptiveSortExecutionTime":165,"insertionSortExecutionTime":8286,"shellSortExecutionTime":244,"heapSortExecutionTime":851,"mergeSortExecutionTime":268,"quickSortExecutionTime":217,"parallelMergeSortExecutionTime":145,"parallelQuickSortExecutionTime":528}
