{"arraySize":50,"runs":0.2,"arraytype":"Almost-Sorted-0.1","adaptiveSortExecutionTime":25,"insertionSortExecutionTime":5,"shellSortExecutionTime":25,"heapSortExecutionTime":9,"mergeSortExecutionTime":5,"quickSortExecutionTime":9,"parallelMergeSortExecutionTime":3,"parallelQuickSortExecutionTime":3}
{"arraySize":50,"runs":0.2,"arraytype":"Almost-Sorted-0.1","adaptiveSortExecutionTime":6,"insertionSortExecutionTime":5,"shellSortExecutionTime":5,"heapSortExecutionTime":11,"mergeSortExecutionTime":6,"quickSortExecutionTime":8,"parallelMergeSortExecutionTime":3,"parallelQuickSortExecutionTime":3}
{"arraySize":50,"runs":0.2,"arraytype":"Almost-Sorted-0.1","adaptiveSortExecutionTime":6,"insertionSortExecutionTime":5,"shellSortExecutionTime":4,"heapSortExecutionTime":11,"mergeSortExecutionTime":6,"quickSortExecutionTime":7,"parallelMergeSortExecutionTime":4,"parallelQuickSortExecutionTime":3}
{"arraySize":50,"runs":0.2,"arraytype":"Almost-Sorted-0.1","adaptiveSortExecutionTime":6,"insertionSortExecutionTime":9,"shellSortExecutionTime":4,"heapSortExecutionTime":10,"mergeSortExecutionTime":7,"quickSortExecutionTime":6,"parallelMergeSortExecutionTime":3,"parallelQuickSortExecutionTime":2}
{"arraySize":50,"runs":0.2,"arraytype":"Almost-Sorted-0.1","adaptiveSortExecutionTime":6,"insertionSortExecutionTime":4,"shellSortExecutionTime":4,"heapSortExecutionTime":386,"mergeSortExecutionTime":7,"quickSortExecutionTime":8,"parallelMergeSortExecutionTime":4,"parallelQuickSortExecutionTime":3}
{"arraySize":50,"runs":0.2,"arraytype":"Almost-Sorted-0.1","adaptiveSortExecutionTime":6,"insertionSortExecutionTime":4,"shellSortExecutionTime":4,"heapSortExecutionTime":11,"mergeSortExecutionTime":6,"quickSortExecutionTime":8,"parallelMergeSortExecutionTime":4,"parallelQuickSortExecutionTime":4}
{"arraySize":50,"runs":0.22,"arraytype":"Almost-Sorted-0.1","adaptiveSortExecutionTime":6,"insertionSortExecutionTime":4,"shellSortExecutionTime":4,"heapSortExecutionTime":6,"mergeSortExecutionTime":6,"quickSortExecutionTime":8,"parallelMergeSortExecutionTime":3,"parallelQuickSortExecutionTime":3}
{"arraySize":50,"runs":0.2,"arraytype":"Almost-Sorted-0.1","adaptiveSortExecutionTime":6,"insertionSortExecutionTime":4,"shellSortExecutionTime":4,"heapSortExecutionTime":6,"mergeSortExecutionTime":6,"quickSortExecutionTime":9,"parallelMergeSortExecutionTime":3,"parallelQuickSortExecutionTime":3}
{"arraySize":50,"runs":0.2,"arraytype":"Almost-Sorted-0.1","adaptiveSortExecutionTime":6,"insertionSortExecutionTime":5,"shellSortExecutionTime":4,"heapSortExecutionTime":5,"mergeSortExecutionTime":5,"quickSortExecutionTime":55,"parallelMergeSortExecutionTime":4,"parallelQuickSortExecutionTime":4}
{"arraySize":50,"runs":0.2,"arraytype":"Almost-Sorted-0.1","adaptiveSortExecutionTime":6,"insertionSortExecutionTime":4,"shellSortExecutionTime":4,"heapSortExecutionTime":5,"mergeSortExecutionTime":5,"quickSortExecutionTime":8,"parallelMergeSortExecutionTime":3,"parallelQuickSortExecutionTime":2}
{"arraySize":50,"runs":0.2,"arraytype":"Almost-Sorted-0.1","adaptiveSortExecutionTime":6,"insertionSortExecutionTime":5,"shellSortExecutionTime":4,"heapSortExecutionTime":6,"mergeSortExecutionTime":6,"quickSortExecutionTime":6,"parallelMergeSortExecutionTime":3,"parallelQuickSortExecutionTime":3}
{"arraySize":50,"runs":0.2,"arraytype":"Almost-Sorted-0.1","adaptiveSortExecutionTime":6,"insertionSortExecutionTime":4,"shellSortExecutionTime":4,"heapSortExecutionTime":5,"mergeSortExecutionTime":6,"quickSortExecutionTime":10,"parallelMergeSortExecutionTime":4,"parallelQuickSortExecutionTime":4}
{"arraySize":50,"runs":0.2,"arraytype":"Almost-Sorted-0.1","adaptiveSortExecutionTime":6,"insertionSortExecutionTime":5,"shellSortExecutionTime":4,"heapSortExecutionTime":6,"mergeSortExecutionTime":6,"quickSortExecutionTime":7,"parallelMergeSortExecutionTime":3,"parallelQuickSortExecutionTime":3}
{"arraySize":50,"runs":0.18,"arraytype":"Almost-Sorted-0.1","adaptiveSortExecutionTime":6,"insertionSortExecutionTime":5,"shellSortExecutionTime":4,"heapSortExecutionTime":6,"mergeSortExecutionTime":6,"quickSortExecutionTime":7,"parallelMergeSortExecutionTime":3,"parallelQuickSortExecutionTime":3}
{"arraySize":50,"runs":0.18,"arraytype":"Almost-Sorted-0.1","adaptiveSortExecutionTime":6,"insertionSortExecutionTime":4,"shellSortExecutionTime":4,"heapSortExecutionTime":6,"mergeSortExecutionTime":6,"quickSortExecutionTime":7,"parallelMergeSortExecutionTime":3,"parallelQuickSortExecutionTime":3}
{"arraySize":50,"runs":0.2,"arraytype":"Almost-Sorted-0.1","adaptiveSortExecutionTime":7,"insertionSortExecutionTime":6,"shellSortExecutionTime":4,"heapSortExecutionTime":5,"mergeSortExecutionTime":6,"quickSortExecutionTime":7,"parallelMergeSortExecutionTime":4,"parallelQuickSortExecutionTime":3}
{"arraySize":50,"runs":0.2,"arraytype":"Almost-Sorted-0.1","adaptiveSortExecutionTime":8,"insertionSortExecutionTime":11,"shellSortExecutionTime":5,"heapSortExecutionTime":6,"mergeSortExecutionTime":6,"quickSortExecutionTime":8,"parallelMergeSortExecutionTime":3,"parallelQuickSortExecutionTime":3}
{"arraySize":50,"runs":0.2,"arraytype":"Almost-Sorted-0.1","adaptiveSortExecutionTime":6,"insertionSortExecutionTime":5,"shellSortExecutionTime":4,"heapSortExecutionTime":5,"mergeSortExecutionTime":5,"quickSortExecutionTime":8,"parallelMergeSortExecutionTime":3,"parallelQuickSortExecutionTime":3}
{"arraySize":50,"runs":0.2,"arraytype":"Almost-Sorted-0.1","adaptiveSortExecutionTime":5,"insertionSortExecutionTime":4,"shellSortExecutionTime":4,"heapSortExecutionTime":6,"mergeSortExecutionTime":6,"quickSortExecutionTime":7,"parallelMergeSortExecutionTime":4,"parallelQuickSortExecutionTime":3}
{"arraySize":50,"runs":0.2,"arraytype":"Almost-Sorted-0.1","adaptiveSortExecutionTime":7,"insertionSortExecutionTime":5,"shellSortExecutionTime":4,"heapSortExecutionTime":5,"mergeSortExecutionTime":6,"quickSortExecutionTime":7,"parallelMergeSortExecutionTime":3,"parallelQuickSortExecutionTime":3}
{"arraySize":50,"runs":0.2,"arraytype":"Almost-Sorted-0.1","adaptiveSortExecutionTime":6,"insertionSortExecutionTime":6,"shellSortExecutionTime":4,"heapSortExecutionTime":5,"mergeSortExecutionTime":6,"quickSortExecutionTime":9,"parallelMergeSortExecutionTime":66,"parallelQuickSortExecutionTime":4}
{"arraySize":50,"runs":0.2,"arraytype":"Almost-Sorted-0.1","adaptiveSortExecutionTime":6,"insertionSortExecutionTime":5,"shellSortExecutionTime":5,"heapSortExecutionTime":5,"mergeSortExecutionTime":5,"quickSortExecutionTime":7,"parallelMergeSortExecutionTime":3,"parallelQuickSortExecutionTime":3}
{"arraySize":50,"runs":0.2,"arraytype":"Almost-Sorted-0.1","adaptiveSortExecutionTime":7,"insertionSortExecutionTime":5,"shellSortExecutionTime":4,"heapSortExecutionTime":5,"mergeSortExecutionTime":6,"quickSortExecutionTime":7,"parallelMergeSortExecutionTime":3,"parallelQuickSortExecutionTime":3}
{"arraySize":50,"runs":0.2,"arraytype":"Almost-Sorted-0.1","adaptiveSortExecutionTime":5,"insertionSortExecutionTime":4,"shellSortExecutionTime":4,"heapSortExecutionTime":5,"mergeSortExecutionTime":5,"quickSortExecutionTime":7,"parallelMergeSortExecutionTime":3,"parallelQuickSortExecutionTime":2}
{"arraySize":50,"runs":0.2,"arraytype":"Almost-Sorted-0.1","adaptiveSortExecutionTime":6,"insertionSortExecutionTime":5,"shellSortExecutionTime":4,"heapSortExecutionTime":6,"mergeSortExecutionTime":6,"quickSortExecutionTime":8,"parallelMergeSortExecutionTime":3,"parallelQuickSortExecutionTime":3}
{"arraySize":50,"runs":0.2,"arraytype":"Almost-Sorted-0.1","adaptiveSortExecutionTime":8,"insertionSortExecutionTime":6,"shellSortExecutionTime":11,"heapSortExecutionTime":6,"mergeSortExecutionTime":6,"quickSortExecutionTime":9,"parallelMergeSortExecutionTime":4,"parallelQuickSortExecutionTime":4}
{"arraySize":50,"runs":0.18,"arraytype":"Almost-Sorted-0.1","adaptiveSortExecutionTime":5,"insertionSortExecutionTime":3,"shellSortExecutionTime":4,"heapSortExecutionTime":5,"mergeSortExecutionTime":7,"quickSortExecutionTime":8,"parallelMergeSortExecutionTime":2,"parallelQuickSortExecutionTime":2}
{"arraySize":50,"runs":0.2,"arraytype":"Almost-Sorted-0.1","adaptiveSortExecutionTime":7,"insertionSortExecutionTime":5,"shellSortExecutionTime":4,"heapSortExecutionTime":6,"mergeSortExecutionTime":7,"quickSortExecutionTime":13,"parallelMergeSortExecutionTime":4,"parallelQuickSortExecutionTime":7}
{"arraySize":50,"runs":0.2,"arraytype":"Almost-Sorted-0.1","adaptiveSortExecutionTime":6,"insertionSortExecutionTime":4,"shellSortExecutionTime":4,"heapSortExecutionTime":5,"mergeSortExecutionTime":6,"quickSortExecutionTime":8,"parallelMergeSortExecutionTime":3,"parallelQuickSortExecutionTime":3}
{"arraySize":50,"runs":0.2,"arraytype":"Almost-Sorted-0.1","adaptiveSortExecutionTime":5,"insertionSortExecutionTime":11,"shellSortExecutionTime":4,"heapSortExecutionTime":5,"mergeSortExecutionTime":6,"quickSortExecutionTime":8,"parallelMergeSortExecutionTime":3,"parallelQuickSortExecutionTime":3}
{"arraySize":50,"runs":0.2,"arraytype":"Almost-Sorted-0.1","adaptiveSortExecutionTime":5,"insertionSortExecutionTime":4,"shellSortExecutionTime":4,"heapSortExecutionTime":5,"mergeSortExecutionTime":6,"quickSortExecutionTime":6,"parallelMergeSortExecutionTime":3,"parallelQuickSortExecutionTime":3}
{"arraySize":50,"runs":0.2,"arraytype":"Almost-Sorted-0.1","adaptiveSortExecutionTime":6,"insertionSortExecutionTime":4,"shellSortExecutionTime":4,"heapSortExecutionTime":5,"mergeSortExecutionTime":6,"quickSortExecutionTime":7,"parallelMergeSortExecutionTime":3,"parallelQuickSortExecutionTime":11}
{"arraySize":50,"runs":0.2,"arraytype":"Almost-Sorted-0.1","adaptiveSortExecutionTime":6,"insertionSortExecutionTime":6,"shellSortExecutionTime":4,"heapSortExecutionTime":5,"mergeSortExecutionTime":6,"quickSortExecutionTime":27,"parallelMergeSortExecutionTime":4,"parallelQuickSortExecutionTime":2}
{"arraySize":50,"runs":0.2,"arraytype":"Almost-Sorted-0.1","adaptiveSortExecutionTime":5,"insertionSortExecutionTime":4,"shellSortExecutionTime":4,"heapSortExecutionTime":5,"mergeSortExecutionTime":5,"quickSortExecutionTime":4,"parallelMergeSortExecutionTime":1,"parallelQuickSortExecutionTime":1}
{"arraySize":50,"runs":0.2,"arraytype":"Almost-Sorted-0.1","adaptiveSortExecutionTime":5,"insertionSortExecutionTime":4,"shellSortExecutionTime":4,"heapSortExecutionTime":6,"mergeSortExecutionTime":5,"quickSortExecutionTime":4,"parallelMergeSortExecutionTime":1,"parallelQuickSortExecutionTime":2}
{"arraySize":50,"runs":0.2,"arraytype":"Almost-Sorted-0.1","adaptiveSortExecutionTime":6,"insertionSortExecutionTime":4,"shellSortExecutionTime":4,"heapSortExecutionTime":5,"mergeSortExecutionTime":5,"quickSortExecutionTime":4,"parallelMergeSortExecutionTime":2,"parallelQuickSortExecutionTime":2}
{"arraySize":50,"runs":0.2,"arraytype":"Almost-Sorted-0.1","adaptiveSortExecutionTime":11,"insertionSortExecutionTime":5,"shellSortExecutionTime":4,"heapSortExecutionTime":5,"mergeSortExecutionTime":5,"quickSortExecutionTime":4,"parallelMergeSortExecutionTime":2,"parallelQuickSortExecutionTime":1}
{"arraySize":50,"runs":0.2,"arraytype":"Almost-Sorted-0.1","adaptiveSortExecutionTime":6,"insertionSortExecutionTime":4,"shellSortExecutionTime":3,"heapSortExecutionTime":4,"mergeSortExecutionTime":4,"quickSortExecutionTime":4,"parallelMergeSortExecutionTime":1,"parallelQuickSortExecutionTime":1}
{"arraySize":50,"runs":0.2,"arraytype":"Almost-Sorted-0.1","adaptiveSortExecutionTime":6,"insertionSortExecutionTime":5,"shellSortExecutionTime":4,"heapSortExecutionTime":6,"mergeSortExecutionTime":6,"quickSortExecutionTime":5,"parallelMergeSortExecutionTime":2,"parallelQuickSortExecutionTime":2}
{"arraySize":50,"runs":0.2,"arraytype":"Almost-Sorted-0.1","adaptiveSortExecutionTime":6,"insertionSortExecutionTime":5,"shellSortExecutionTime":4,"heapSortExecutionTime":5,"mergeSortExecutionTime":6,"quickSortExecutionTime":4,"parallelMergeSortExecutionTime":2,"parallelQuickSortExecutionTime":2}
{"arraySize":50,"runs":0.2,"arraytype":"Almost-Sorted-0.1","adaptiveSortExecutionTime":5,"insertionSortExecutionTime":4,"shellSortExecutionTime":4,"heapSortExecutionTime":6,"mergeSortExecutionTime":5,"quickSortExecutionTime":4,"parallelMergeSortExecutionTime":2,"parallelQuickSortExecutionTime":1}
{"arraySize":50,"runs":0.2,"arraytype":"Almost-Sorted-0.1","adaptiveSortExecutionTime":6,"insertionSortExecutionTime":10,"shellSortExecutionTime":4,"heapSortExecutionTime":5,"mergeSortExecutionTime":5,"quickSortExecutionTime":4,"parallelMergeSortExecutionTime":1,"parallelQuickSortExecutionTime":2}
{"arraySize":50,"runs":0.2,"arraytype":"Almost-Sorted-0.1","adaptiveSortExecutionTime":5,"insertionSortExecutionTime":4,"shellSortExecutionTime":4,"heapSortExecutionTime":5,"mergeSortExecutionTime":5,"quickSortExecutionTime":4,"parallelMergeSortExecutionTime":1,"parallelQuickSortExecutionTime":1}
{"arraySize":50,"runs":0.2,"arraytype":"Almost-Sorted-0.1","adaptiveSortExecutionTime":4,"insertionSortExecutionTime":4,"shellSortExecutionTime":4,"heapSortExecutionTime":6,"mergeSortExecutionTime":5,"quickSortExecutionTime":4,"parallelMergeSortExecutionTime":1,"parallelQuickSortExecutionTime":1}
{"arraySize":50,"runs":0.2,"arraytype":"Almost-Sorted-0.1","adaptiveSortExecutionTime":4,"insertionSortExecutionTime":5,"shellSortExecutionTime":4,"heapSortExecutionTime":5,"mergeSortExecutionTime":5,"quickSortExecutionTime":4,"parallelMergeSortExecutionTime":2,"parallelQuickSortExecutionTime":1}
{"arraySize":50,"runs":0.2,"arraytype":"Almost-Sorted-0.1","adaptiveSortExecutionTime":5,"insertionSortExecutionTime":4,"shellSortExecutionTime":4,"heapSortExecutionTime":5,"mergeSortExecutionTime":5,"quickSortExecutionTime":4,"parallelMergeSortExecutionTime":1,"parallelQuickSortExecutionTime":1}
{"arraySize":50,"runs":0.2,"arraytype":"Almost-Sorted-0.1","adaptiveSortExecutionTime":6,"insertionSortExecutionTime":5,"shellSortExecutionTime":4,"heapSortExecutionTime":6,"mergeSortExecutionTime":5,"quickSortExecutionTime":5,"parallelMergeSortExecutionTime":2,"parallelQuickSortExecutionTime":2}
{"arraySize":50,"runs":0.2,"arraytype":"Almost-Sorted-0.1","adaptiveSortExecutionTime":6,"insertionSortExecutionTime":5,"shellSortExecutionTime":4,"heapSortExecutionTime":6,"mergeSortExecutionTime":6,"quickSortExecutionTime":4,"parallelMergeSortExecutionTime":2,"parallelQuickSortExecutionTime":1}
{"arraySize":50,"runs":0.2,"arraytype":"Almost-Sorted-0.1","adaptiveSortExecutionTime":12,"insertionSortExecutionTime":4,"shellSortExecutionTime":4,"heapSortExecutionTime":5,"mergeSortExecutionTime":185,"quickSortExecutionTime":6,"parallelMergeSortExecutionTime":2,"parallelQuickSortExecutionTime":2}
{"arraySize":50,"runs":0.2,"arraytype":"Almost-Sorted-0.1","adaptiveSortExecutionTime":6,"insertionSortExecutionTime":5,"shellSortExecutionTime":4,"heapSortExecutionTime":5,"mergeSortExecutionTime":6,"quickSortExecutionTime":5,"parallelMergeSortExecutionTime":2,"parallelQuickSortExecutionTime":2}
{"arraySize":50,"runs":0.2,"arraytype":"Almost-Sorted-0.1","adaptiveSortExecutionTime":7,"insertionSortExecutionTime":6,"shellSortExecutionTime":11,"heapSortExecutionTime":6,"mergeSortExecutionTime":6,"quickSortExecutionTime":4,"parallelMergeSortExecutionTime":2,"parallelQuickSortExecutionTime":2}
{"arraySize":50,"runs":0.2,"arraytype":"Almost-Sorted-0.1","adaptiveSortExecutionTime":6,"insertionSortExecutionTime":5,"shellSortExecutionTime":4,"heapSortExecutionTime":6,"mergeSortExecutionTime":5,"quickSortExecutionTime":4,"parallelMergeSortExecutionTime":1,"parallelQuickSortExecutionTime":1}
{"arraySize":50,"runs":0.2,"arraytype":"Almost-Sorted-0.1","adaptiveSortExecutionTime":5,"insertionSortExecutionTime":5,"shellSortExecutionTime":4,"heapSortExecutionTime":6,"mergeSortExecutionTime":5,"quickSortExecutionTime":4,"parallelMergeSortExecutionTime":1,"parallelQuickSortExecutionTime":1}
{"arraySize":50,"runs":0.2,"arraytype":"Almost-Sorted-0.1","adaptiveSortExecutionTime":6,"insertionSortExecutionTime":10,"shellSortExecutionTime":4,"heapSortExecutionTime":5,"mergeSortExecutionTime":5,"quickSortExecutionTime":4,"parallelMergeSortExecutionTime":2,"parallelQuickSortExecutionTime":1}
{"arraySize":50,"runs":0.2,"arraytype":"Almost-Sorted-0.1","adaptiveSortExecutionTime":6,"insertionSortExecutionTime":4,"shellSortExecutionTime":4,"heapSortExecutionTime":5,"mergeSortExecutionTime":5,"quickSortExecutionTime":4,"parallelMergeSortExecutionTime":2,"parallelQuickSortExecutionTime":1}
{"arraySize":50,"runs":0.2,"arraytype":"Almost-Sorted-0.1","adaptiveSortExecutionTime":6,"insertionSortExecutionTime":5,"shellSortExecutionTime":4,"heapSortExecutionTime":6,"mergeSortExecutionTime":5,"quickSortExecutionTime":4,"parallelMergeSortExecutionTime":2,"parallelQuickSortExecutionTime":1}
{"arraySize":50,"runs":0.2,"arraytype":"Almost-Sorted-0.1","adaptiveSortExecutionTime":5,"insertionSortExecutionTime":4,"shellSortExecutionTime":4,"heapSortExecutionTime":5,"mergeSortExecutionTime":4,"quickSortExecutionTime":4,"parallelMergeSortExecutionTime":1,"parallelQuickSortExecutionTime":1}
{"arraySize":50,"runs":0.2,"arraytype":"Almost-Sorted-0.1","adaptiveSortExecutionTime":5,"insertionSortExecutionTime":4,"shellSortExecutionTime":4,"heapSortExecutionTime":5,"mergeSortExecutionTime":6,"quickSortExecutionTime":4,"parallelMergeSortExecutionTime":1,"parallelQuickSortExecutionTime":1}
{"arraySize":50,"runs":0.2,"arraytype":"Almost-Sorted-0.1","adaptiveSortExecutionTime":7,"insertionSortExecutionTime":6,"shellSortExecutionTime":5,"heapSortExecutionTime":5,"mergeSortExecutionTime":5,"quickSortExecutionTime":4,"parallelMergeSortExecutionTime":2,"parallelQuickSortExecutionTime":1}
{"arraySize":50,"runs":0.2,"arraytype":"Almost-Sorted-0.1","adaptiveSortExecutionTime":11,"insertionSortExecutionTime":6,"shellSortExecutionTime":5,"heapSortExecutionTime":6,"mergeSortExecutionTime":6,"quickSortExecutionTime":4,"parallelMergeSortExecutionTime":2,"parallelQuickSortExecutionTime":1}
{"arraySize":50,"runs":0.2,"arraytype":"Almost-Sorted-0.1","adaptiveSortExecutionTime":6,"insertionSortExecutionTime":5,"shellSortExecutionTime":5,"heapSortExecutionTime":6,"mergeSortExecutionTime":5,"quickSortExecutionTime":4,"parallelMergeSortExecutionTime":2,"parallelQuickSortExecutionTime":2}
{"arraySize":50,"runs":0.2,"arraytype":"Almost-Sorted-0.1","adaptiveSortExecutionTime":6,"insertionSortExecutionTime":5,"shellSortExecutionTime":4,"heapSortExecutionTime":6,"mergeSortExecutionTime":5,"quickSortExecutionTime":4,"parallelMergeSortExecutionTime":2,"parallelQuickSortExecutionTime":2}
{"arraySize":50,"runs":0.2,"arraytype":"Almost-Sorted-0.1","adaptiveSortExecutionTime":7,"insertionSortExecutionTime":5,"shellSortExecutionTime":4,"heapSortExecutionTime":5,"mergeSortExecutionTime":7,"quickSortExecutionTime":4,"parallelMergeSortExecutionTime":2,"parallelQuickSortExecutionTime":1}
{"arraySize":50,"runs":0.2,"arraytype":"Almost-Sorted-0.1","adaptiveSortExecutionTime":6,"insertionSortExecutionTime":4,"shellSortExecutionTime":4,"heapSortExecutionTime":5,"mergeSortExecutionTime":5,"quickSortExecutionTime":4,"parallelMergeSortExecutionTime":2,"parallelQuickSortExecutionTime":2}
{"arraySize":50,"runs":0.2,"arraytype":"Almost-Sorted-0.1","adaptiveSortExecutionTime":6,"insertionSortExecutionTime":5,"shellSortExecutionTime":4,"heapSortExecutionTime":5,"mergeSortExecutionTime":5,"quickSortExecutionTime":4,"parallelMergeSortExecutionTime":1,"parallelQuickSortExecutionTime":1}
{"arraySize":50,"runs":0.2,"arraytype":"Almost-Sorted-0.1","adaptiveSortExecutionTime":5,"insertionSortExecutionTime":5,"shellSortExecutionTime":4,"heapSortExecutionTime":5,"mergeSortExecutionTime":5,"quickSortExecutionTime":4,"parallelMergeSortExecutionTime":2,"parallelQuickSortExecutionTime":2}
{"arraySize":50,"runs":0.2,"arraytype":"Almost-Sorted-0.1","adaptiveSortExecutionTime":6,"insertionSortExecutionTime":9,"shellSortExecutionTime":4,"heapSortExecutionTime":6,"mergeSortExecutionTime":5,"quickSortExecutionTime":4,"parallelMergeSortExecutionTime":2,"parallelQuickSortExecutionTime":2}
{"arraySize":50,"runs":0.2,"arraytype":"Almost-Sorted-0.1","adaptiveSortExecutionTime":6,"insertionSortExecutionTime":6,"shellSortExecutionTime":4,"heapSortExecutionTime":5,"mergeSortExecutionTime":5,"quickSortExecutionTime":4,"parallelMergeSortExecutionTime":1,"parallelQuickSortExecutionTime":1}
{"arraySize":50,"runs":0.2,"arraytype":"Almost-Sorted-0.1","adaptiveSortExecutionTime":6,"insertionSortExecutionTime":5,"shellSortExecutionTime":4,"heapSortExecutionTime":5,"mergeSortExecutionTime":5,"quickSortExecutionTime":4,"parallelMergeSortExecutionTime":2,"parallelQuickSortExecutionTime":1}
{"arraySize":50,"runs":0.2,"arraytype":"Almost-Sorted-0.1","adaptiveSortExecutionTime":6,"insertionSortExecutionTime":5,"shellSortExecutionTime":4,"heapSortExecutionTime":5,"mergeSortExecutionTime":5,"quickSortExecutionTime":4,"parallelMergeSortExecutionTime":1,"parallelQuickSortExecutionTime":2}
{"arraySize":50,"runs":0.2,"arraytype":"Almost-Sorted-0.1","adaptiveSortExecutionTime":6,"insertionSortExecutionTime":4,"shellSortExecutionTime":4,"heapSortExecutionTime":5,"mergeSortExecutionTime":5,"quickSortExecutionTime":4,"parallelMergeSortExecutionTime":2,"parallelQuickSortExecutionTime":1}
{"arraySize":50,"runs":0.2,"arraytype":"Almost-Sorted-0.1","adaptiveSortExecutionTime":14,"insertionSortExecutionTime":5,"shellSortExecutionTime":5,"heapSortExecutionTime":6,"mergeSortExecutionTime":6,"quickSortExecutionTime":4,"parallelMergeSortExecutionTime":2,"parallelQuickSortExecutionTime":1}
{"arraySize":50,"runs":0.2,"arraytype":"Almost-Sorted-0.1","adaptiveSortExecutionTime":6,"insertionSortExecutionTime":5,"shellSortExecutionTime":4,"heapSortExecutionTime":5,"mergeSortExecutionTime":5,"quickSortExecutionTime":4,"parallelMergeSortExecutionTime":1,"parallelQuickSortExecutionTime":2}
{"arraySize":50,"runs":0.2,"arraytype":"Almost-Sorted-0.1","adaptiveSortExecutionTime":6,"insertionSortExecutionTime":6,"shellSortExecutionTime":5,"heapSortExecutionTime":6,"mergeSortExecutionTime":6,"quickSortExecutionTime":5,"parallelMergeSortExecutionTime":2,"parallelQuickSortExecutionTime":2}
{"arraySize":50,"runs":0.2,"arraytype":"Almost-Sorted-0.1","adaptiveSortExecutionTime":5,"insertionSortExecutionTime":5,"shellSortExecutionTime":4,"heapSortExecutionTime":5,"mergeSortExecutionTime":5,"quickSortExecutionTime":4,"parallelMergeSortExecutionTime":2,"parallelQuickSortExecutionTime":2}
{"arraySize":50,"runs":0.2,"arraytype":"Almost-Sorted-0.1","adaptiveSortExecutionTime":6,"insertionSortExecutionTime":5,"shellSortExecutionTime":11,"heapSortExecutionTime":6,"mergeSortExecutionTime":5,"quickSortExecutionTime":4,"parallelMergeSortExecutionTime":1,"parallelQuickSortExecutionTime":1}
{"arraySize":50,"runs":0.2,"arraytype":"Almost-Sorted-0.1","adaptiveSortExecutionTime":5,"insertionSortExecutionTime":5,"shellSortExecutionTime":4,"heapSortExecutionTime":5,"mergeSortExecutionTime":5,"quickSortExecutionTime":4,"parallelMergeSortExecutionTime":2,"parallelQuickSortExecutionTime":1}
{"arraySize":50,"runs":0.18,"arraytype":"Almost-Sorted-0.1","adaptiveSortExecutionTime":6,"insertionSortExecutionTime":5,"shellSortExecutionTime":4,"heapSortExecutionTime":5,"mergeSortExecutionTime":5,"quickSortExecutionTime":4,"parallelMergeSortExecutionTime":1,"parallelQuickSortExecutionTime":1}
{"arraySize":50,"runs":0.18,"arraytype":"Almost-Sorted-0.1","adaptiveSortExecutionTime":7,"insertionSortExecutionTime":22,"shellSortExecutionTime":7,"heapSortExecutionTime":6,"mergeSortExecutionTime":6,"quickSortExecutionTime":4,"parallelMergeSortExecutionTime":2,"parallelQuickSortExecutionTime":2}
{"arraySize":50,"runs":0.2,"arraytype":"Almost-Sorted-0.1","adaptiveSortExecutionTime":4,"insertionSortExecutionTime":4,"shellSortExecutionTime":3,"heapSortExecutionTime":5,"mergeSortExecutionTime":4,"quickSortExecutionTime":4,"parallelMergeSortExecutionTime":1,"parallelQuickSortExecutionTime":1}
{"arraySize":50,"runs":0.2,"arraytype":"Almost-Sorted-0.1","adaptiveSortExecutionTime":6,"insertionSortExecutionTime":5,"shellSortExecutionTime":4,"heapSortExecutionTime":5,"mergeSortExecutionTime":5,"quickSortExecutionTime":4,"parallelMergeSortExecutionTime":2,"parallelQuickSortExecutionTime":1}
{"arraySize":50,"runs":0.2,"arraytype":"Almost-Sorted-0.1","adaptiveSortExecutionTime":6,"insertionSortExecutionTime":6,"shellSortExecutionTime":4,"heapSortExecutionTime":6,"mergeSortExecutionTime":5,"quickSortExecutionTime":4,"parallelMergeSortExecutionTime":2,"parallelQuickSortExecutionTime":2}
{"arraySize":50,"runs":0.2,"arraytype":"Almost-Sorted-0.1","adaptiveSortExecutionTime":31,"insertionSortExecutionTime":6,"shellSortExecutionTime":4,"heapSortExecutionTime":5,"mergeSortExecutionTime":5,"quickSortExecutionTime":3,"parallelMergeSortExecutionTime":1,"parallelQuickSortExecutionTime":1}
{"arraySize":50,"runs":0.2,"arraytype":"Almost-Sorted-0.1","adaptiveSortExecutionTime":7,"insertionSortExecutionTime":4,"shellSortExecutionTime":4,"heapSortExecutionTime":5,"mergeSortExecutionTime":290,"quickSortExecutionTime":5,"parallelMergeSortExecutionTime":2,"parallelQuickSortExecutionTime":2}
{"arraySize":50,"runs":0.2,"arraytype":"Almost-Sorted-0.1","adaptiveSortExecutionTime":6,"insertionSortExecutionTime":6,"shellSortExecutionTime":4,"heapSortExecutionTime":6,"mergeSortExecutionTime":5,"quickSortExecutionTime":4,"parallelMergeSortExecutionTime":2,"parallelQuickSortExecutionTime":2}
{"arraySize":50,"runs":0.2,"arraytype":"Almost-Sorted-0.1","adaptiveSortExecutionTime":5,"insertionSortExecutionTime":4,"shellSortExecutionTime":4,"heapSortExecutionTime":5,"mergeSortExecutionTime":5,"quickSortExecutionTime":4,"parallelMergeSortExecutionTime":1,"parallelQuickSortExecutionTime":1}
{"arraySize":50,"runs":0.2,"arraytype":"Almost-Sorted-0.1","adaptiveSortExecutionTime":5,"insertionSortExecutionTime":5,"shellSortExecutionTime":4,"heapSortExecutionTime":5,"mergeSortExecutionTime":5,"quickSortExecutionTime":4,"parallelMergeSortExecutionTime":2,"parallelQuickSortExecutionTime":2}
{"arraySize":50,"runs":0.2,"arraytype":"Almost-Sorted-0.1","adaptiveSortExecutionTime":7,"insertionSortExecutionTime":6,"shellSortExecutionTime":4,"heapSortExecutionTime":6,"mergeSortExecutionTime":6,"quickSortExecutionTime":4,"parallelMergeSortExecutionTime":2,"parallelQuickSortExecutionTime":2}
{"arraySize":50,"runs":0.2,"arraytype":"Almost-Sorted-0.1","adaptiveSortExecutionTime":7,"insertionSortExecutionTime":6,"shellSortExecutionTime":4,"heapSortExecutionTime":6,"mergeSortExecutionTime":6,"quickSortExecutionTime":4,"parallelMergeSortExecutionTime":2,"parallelQuickSortExecutionTime":2}
{"arraySize":50,"runs":0.2,"arraytype":"Almost-Sorted-0.1","adaptiveSortExecutionTime":6,"insertionSortExecutionTime":5,"shellSortExecutionTime":4,"heapSortExecutionTime":5,"mergeSortExecutionTime":6,"quickSortExecutionTime":4,"parallelMergeSortExecutionTime":2,"parallelQuickSortExecutionTime":2}
{"arraySize":50,"runs":0.2,"arraytype":"Almost-Sorted-0.1","adaptiveSortExecutionTime":5,"insertionSortExecutionTime":60,"shellSortExecutionTime":4,"heapSortExecutionTime":6,"mergeSortExecutionTime":6,"quickSortExecutionTime":4,"parallelMergeSortExecutionTime":2,"parallelQuickSortExecutionTime":1}
{"arraySize":50,"runs":0.2,"arraytype":"Almost-Sorted-0.1","adaptiveSortExecutionTime":6,"insertionSortExecutionTime":5,"shellSortExecutionTime":5,"heapSortExecutionTime":6,"mergeSortExecutionTime":6,"quickSortExecutionTime":5,"parallelMergeSortExecutionTime":2,"parallelQuickSortExecutionTime":1}
{"arraySize":50,"runs":0.2,"arraytype":"Almost-Sorted-0.1","adaptiveSortExecutionTime":5,"insertionSortExecutionTime":5,"shellSortExecutionTime":4,"heapSortExecutionTime":5,"mergeSortExecutionTime":5,"quickSortExecutionTime":4,"parallelMergeSortExecutionTime":2,"parallelQuickSortExecutionTime":2}
{"arraySize":50,"runs":0.2,"arraytype":"Almost-Sorted-0.1","adaptiveSortExecutionTime":5,"insertionSortExecutionTime":5,"shellSortExecutionTime":4,"heapSortExecutionTime":5,"mergeSortExecutionTime":5,"quickSortExecutionTime":4,"parallelMergeSortExecutionTime":1,"parallelQuickSortExecutionTime":1}
{"arraySize":50,"runs":0.2,"arraytype":"Almost-Sorted-0.1","adaptiveSortExecutionTime":20,"insertionSortExecutionTime":6,"shellSortExecutionTime":5,"heapSortExecutionTime":6,"mergeSortExecutionTime":5,"quickSortExecutionTime":4,"parallelMergeSortExecutionTime":2,"parallelQuickSortExecutionTime":1}
{"arraySize":50,"runs":0.2,"arraytype":"Almost-Sorted-0.1","adaptiveSortExecutionTime":6,"insertionSortExecutionTime":5,"shellSortExecutionTime":4,"heapSortExecutionTime":5,"mergeSortExecutionTime":6,"quickSortExecutionTime":4,"parallelMergeSortExecutionTime":2,"parallelQuickSortExecutionTime":2}
{"arraySize":50,"runs":0.2,"arraytype":"Almost-Sorted-0.1","adaptiveSortExecutionTime":7,"insertionSortExecutionTime":6,"shellSortExecutionTime":5,"heapSortExecutionTime":6,"mergeSortExecutionTime":6,"quickSortExecutionTime":5,"parallelMergeSortExecutionTime":1,"parallelQuickSortExecutionTime":1}
{"arraySize":50,"runs":0.2,"arraytype":"Almost-Sorted-0.1","adaptiveSortExecutionTime":7,"insertionSortExecutionTime":6,"shellSortExecutionTime":4,"heapSortExecutionTime":6,"mergeSortExecutionTime":6,"quickSortExecutionTime":8,"parallelMergeSortExecutionTime":2,"parallelQuickSortExecutionTime":2}
{"arraySize":50,"runs":0.2,"arraytype":"Almost-Sorted-0.1","adaptiveSortExecutionTime":6,"insertionSortExecutionTime":5,"shellSortExecutionTime":5,"heapSortExecutionTime":6,"mergeSortExecutionTime":6,"quickSortExecutionTime":5,"parallelMergeSortExecutionTime":2,"parallelQuickSortExecutionTime":1}
{"arraySize":50,"runs":0.2,"arraytype":"Almost-Sorted-0.1","adaptiveSortExecutionTime":7,"insertionSortExecutionTime":2,"shellSortExecutionTime":5,"heapSortExecutionTime":6,"mergeSortExecutionTime":6,"quickSortExecutionTime":4,"parallelMergeSortExecutionTime":2,"parallelQuickSortExecutionTime":2}
