{"arraySize":50,"runs":0.52,"arraytype":"Random","adaptiveSortExecutionTime":24,"insertionSortExecutionTime":18,"shellSortExecutionTime":12,"heapSortExecutionTime":52,"mergeSortExecutionTime":27,"quickSortExecutionTime":205,"parallelMergeSortExecutionTime":14,"parallelQuickSortExecutionTime":13}
{"arraySize":50,"runs":0.48,"arraytype":"Random","adaptiveSortExecutionTime":14,"insertionSortExecutionTime":26,"shellSortExecutionTime":15,"heapSortExecutionTime":24,"mergeSortExecutionTime":46,"quickSortExecutionTime":24,"parallelMergeSortExecutionTime":11,"parallelQuickSortExecutionTime":11}
{"arraySize":50,"runs":0.52,"arraytype":"Random","adaptiveSortExecutionTime":17,"insertionSortExecutionTime":16,"shellSortExecutionTime":10,"heapSortExecutionTime":9,"mergeSortExecutionTime":29,"quickSortExecutionTime":19,"parallelMergeSortExecutionTime":14,"parallelQuickSortExecutionTime":22}
{"arraySize":50,"runs":0.54,"arraytype":"Random","adaptiveSortExecutionTime":16,"insertionSortExecutionTime":24,"shellSortExecutionTime":16,"heapSortExecutionTime":15,"mergeSortExecutionTime":43,"quickSortExecutionTime":29,"parallelMergeSortExecutionTime":16,"parallelQuickSortExecutionTime":13}
{"arraySize":50,"runs":0.52,"arraytype":"Random","adaptiveSortExecutionTime":14,"insertionSortExecutionTime":34,"shellSortExecutionTime":18,"heapSortExecutionTime":15,"mergeSortExecutionTime":53,"quickSortExecutionTime":18,"parallelMergeSortExecutionTime":12,"parallelQuickSortExecutionTime":11}
{"arraySize":50,"runs":0.48,"arraytype":"Random","adaptiveSortExecutionTime":17,"insertionSortExecutionTime":57,"shellSortExecutionTime":13,"heapSortExecutionTime":13,"mergeSortExecutionTime":11,"quickSortExecutionTime":19,"parallelMergeSortExecutionTime":15,"parallelQuickSortExecutionTime":15}
{"arraySize":50,"runs":0.54,"arraytype":"Random","adaptiveSortExecutionTime":10,"insertionSortExecutionTime":16,"shellSortExecutionTime":11,"heapSortExecutionTime":9,"mergeSortExecutionTime":6,"quickSortExecutionTime":14,"parallelMergeSortExecutionTime":9,"parallelQuickSortExecutionTime":9}
{"arraySize":50,"runs":0.48,"arraytype":"Random","adaptiveSortExecutionTime":16,"insertionSortExecutionTime":21,"shellSortExecutionTime":15,"heapSortExecutionTime":17,"mergeSortExecutionTime":9,"quickSortExecutionTime":20,"parallelMergeSortExecutionTime":14,"parallelQuickSortExecutionTime":13}
{"arraySize":50,"runs":0.48,"arraytype":"Random","adaptiveSortExecutionTime":13,"insertionSortExecutionTime":25,"shellSortExecutionTime":16,"heapSortExecutionTime":13,"mergeSortExecutionTime":9,"quickSortExecutionTime":17,"parallelMergeSortExecutionTime":12,"parallelQuickSortExecutionTime":11}
{"arraySize":50,"runs":0.54,"arraytype":"Random","adaptiveSortExecutionTime":17,"insertionSortExecutionTime":29,"shellSortExecutionTime":15,"heapSortExecutionTime":13,"mergeSortExecutionTime":8,"quickSortExecutionTime":34,"parallelMergeSortExecutionTime":15,"parallelQuickSortExecutionTime":13}
{"arraySize":50,"runs":0.48,"arraytype":"Random","adaptiveSortExecutionTime":14,"insertionSortExecutionTime":23,"shellSortExecutionTime":16,"heapSortExecutionTime":15,"mergeSortExecutionTime":9,"quickSortExecutionTime":18,"parallelMergeSortExecutionTime":13,"parallelQuickSortExecutionTime":13}
{"arraySize":50,"runs":0.48,"arraytype":"Random","adaptiveSortExecutionTime":5,"insertionSortExecutionTime":22,"shellSortExecutionTime":14,"heapSortExecutionTime":14,"mergeSortExecutionTime":8,"quickSortExecutionTime":19,"parallelMergeSortExecutionTime":3,"parallelQuickSortExecutionTime":3}
{"arraySize":50,"runs":0.5,"arraytype":"Random","adaptiveSortExecutionTime":6,"insertionSortExecutionTime":25,"shellSortExecutionTime":17,"heapSortExecutionTime":14,"mergeSortExecutionTime":9,"quickSortExecutionTime":7,"parallelMergeSortExecutionTime":4,"parallelQuickSortExecutionTime":4}
{"arraySize":50,"runs":0.44,"arraytype":"Random","adaptiveSortExecutionTime":50,"insertionSortExecutionTime":20,"shellSortExecutionTime":16,"heapSortExecutionTime":17,"mergeSortExecutionTime":10,"quickSortExecutionTime":7,"parallelMergeSortExecutionTime":4,"parallelQuickSortExecutionTime":2}
{"arraySize":50,"runs":0.54,"arraytype":"Random","adaptiveSortExecutionTime":5,"insertionSortExecutionTime":25,"shellSortExecutionTime":15,"heapSortExecutionTime":15,"mergeSortExecutionTime":9,"quickSortExecutionTime":7,"parallelMergeSortExecutionTime":4,"parallelQuickSortExecutionTime":4}
{"arraySize":50,"runs":0.44,"arraytype":"Random","adaptiveSortExecutionTime":40,"insertionSortExecutionTime":26,"shellSortExecutionTime":16,"heapSortExecutionTime":14,"mergeSortExecutionTime":10,"quickSortExecutionTime":7,"parallelMergeSortExecutionTime":3,"parallelQuickSortExecutionTime":4}
{"arraySize":50,"runs":0.54,"arraytype":"Random","adaptiveSortExecutionTime":4,"insertionSortExecutionTime":25,"shellSortExecutionTime":14,"heapSortExecutionTime":9,"mergeSortExecutionTime":6,"quickSortExecutionTime":5,"parallelMergeSortExecutionTime":2,"parallelQuickSortExecutionTime":2}
{"arraySize":50,"runs":0.46,"arraytype":"Random","adaptiveSortExecutionTime":6,"insertionSortExecutionTime":23,"shellSortExecutionTime":16,"heapSortExecutionTime":27,"mergeSortExecutionTime":8,"quickSortExecutionTime":8,"parallelMergeSortExecutionTime":4,"parallelQuickSortExecutionTime":3}
{"arraySize":50,"runs":0.48,"arraytype":"Random","adaptiveSortExecutionTime":5,"insertionSortExecutionTime":23,"shellSortExecutionTime":15,"heapSortExecutionTime":15,"mergeSortExecutionTime":9,"quickSortExecutionTime":6,"parallelMergeSortExecutionTime":3,"parallelQuickSortExecutionTime":2}
{"arraySize":50,"runs":0.54,"arraytype":"Random","adaptiveSortExecutionTime":7,"insertionSortExecutionTime":21,"shellSortExecutionTime":14,"heapSortExecutionTime":14,"mergeSortExecutionTime":9,"quickSortExecutionTime":7,"parallelMergeSortExecutionTime":4,"parallelQuickSortExecutionTime":4}
{"arraySize":50,"runs":0.48,"arraytype":"Random","adaptiveSortExecutionTime":11,"insertionSortExecutionTime":26,"shellSortExecutionTime":16,"heapSortExecutionTime":18,"mergeSortExecutionTime":9,"quickSortExecutionTime":6,"parallelMergeSortExecutionTime":4,"parallelQuickSortExecutionTime":2}
{"arraySize":50,"runs":0.5,"arraytype":"Random","adaptiveSortExecutionTime":6,"insertionSortExecutionTime":26,"shellSortExecutionTime":16,"heapSortExecutionTime":9,"mergeSortExecutionTime":9,"quickSortExecutionTime":7,"parallelMergeSortExecutionTime":3,"parallelQuickSortExecutionTime":3}
{"arraySize":50,"runs":0.54,"arraytype":"Random","adaptiveSortExecutionTime":4,"insertionSortExecutionTime":24,"shellSortExecutionTime":16,"heapSortExecutionTime":9,"mergeSortExecutionTime":9,"quickSortExecutionTime":7,"parallelMergeSortExecutionTime":4,"parallelQuickSortExecutionTime":3}
{"arraySize":50,"runs":0.48,"arraytype":"Random","adaptiveSortExecutionTime":5,"insertionSortExecutionTime":25,"shellSortExecutionTime":14,"heapSortExecutionTime":10,"mergeSortExecutionTime":12,"quickSortExecutionTime":7,"parallelMergeSortExecutionTime":2,"parallelQuickSortExecutionTime":2}
{"arraySize":50,"runs":0.46,"arraytype":"Random","adaptiveSortExecutionTime":4,"insertionSortExecutionTime":17,"shellSortExecutionTime":11,"heapSortExecutionTime":7,"mergeSortExecutionTime":7,"quickSortExecutionTime":5,"parallelMergeSortExecutionTime":3,"parallelQuickSortExecutionTime":1}
{"arraySize":50,"runs":0.46,"arraytype":"Random","adaptiveSortExecutionTime":5,"insertionSortExecutionTime":24,"shellSortExecutionTime":16,"heapSortExecutionTime":10,"mergeSortExecutionTime":9,"quickSortExecutionTime":6,"parallelMergeSortExecutionTime":2,"parallelQuickSortExecutionTime":3}
{"arraySize":50,"runs":0.5,"arraytype":"Random","adaptiveSortExecutionTime":6,"insertionSortExecutionTime":22,"shellSortExecutionTime":17,"heapSortExecutionTime":11,"mergeSortExecutionTime":11,"quickSortExecutionTime":9,"parallelMergeSortExecutionTime":4,"parallelQuickSortExecutionTime":3}
{"arraySize":50,"runs":0.48,"arraytype":"Random","adaptiveSortExecutionTime":5,"insertionSortExecutionTime":21,"shellSortExecutionTime":15,"heapSortExecutionTime":10,"mergeSortExecutionTime":22,"quickSortExecutionTime":11,"parallelMergeSortExecutionTime":3,"parallelQuickSortExecutionTime":2}
{"arraySize":50,"runs":0.48,"arraytype":"Random","adaptiveSortExecutionTime":6,"insertionSortExecutionTime":30,"shellSortExecutionTime":17,"heapSortExecutionTime":10,"mergeSortExecutionTime":10,"quickSortExecutionTime":8,"parallelMergeSortExecutionTime":4,"parallelQuickSortExecutionTime":4}
{"arraySize":50,"runs":0.52,"arraytype":"Random","adaptiveSortExecutionTime":6,"insertionSortExecutionTime":20,"shellSortExecutionTime":13,"heapSortExecutionTime":8,"mergeSortExecutionTime":8,"quickSortExecutionTime":7,"parallelMergeSortExecutionTime":3,"parallelQuickSortExecutionTime":3}
{"arraySize":50,"runs":0.44,"arraytype":"Random","adaptiveSortExecutionTime":52,"insertionSortExecutionTime":22,"shellSortExecutionTime":15,"heapSortExecutionTime":9,"mergeSortExecutionTime":9,"quickSortExecutionTime":9,"parallelMergeSortExecutionTime":4,"parallelQuickSortExecutionTime":3}
{"arraySize":50,"runs":0.54,"arraytype":"Random","adaptiveSortExecutionTime":10,"insertionSortExecutionTime":27,"shellSortExecutionTime":15,"heapSortExecutionTime":10,"mergeSortExecutionTime":68,"quickSortExecutionTime":8,"parallelMergeSortExecutionTime":3,"parallelQuickSortExecutionTime":3}
{"arraySize":50,"runs":0.62,"arraytype":"Random","adaptiveSortExecutionTime":7,"insertionSortExecutionTime":25,"shellSortExecutionTime":17,"heapSortExecutionTime":10,"mergeSortExecutionTime":26,"quickSortExecutionTime":9,"parallelMergeSortExecutionTime":4,"parallelQuickSortExecutionTime":16}
{"arraySize":50,"runs":0.54,"arraytype":"Random","adaptiveSortExecutionTime":5,"insertionSortExecutionTime":25,"shellSortExecutionTime":14,"heapSortExecutionTime":10,"mergeSortExecutionTime":6,"quickSortExecutionTime":8,"parallelMergeSortExecutionTime":4,"parallelQuickSortExecutionTime":3}
{"arraySize":50,"runs":0.5,"arraytype":"Random","adaptiveSortExecutionTime":5,"insertionSortExecutionTime":28,"shellSortExecutionTime":16,"heapSortExecutionTime":10,"mergeSortExecutionTime":8,"quickSortExecutionTime":6,"parallelMergeSortExecutionTime":3,"parallelQuickSortExecutionTime":4}
{"arraySize":50,"runs":0.48,"arraytype":"Random","adaptiveSortExecutionTime":5,"insertionSortExecutionTime":24,"shellSortExecutionTime":17,"heapSortExecutionTime":10,"mergeSortExecutionTime":6,"quickSortExecutionTime":7,"parallelMergeSortExecutionTime":3,"parallelQuickSortExecutionTime":2}
{"arraySize":50,"runs":0.6,"arraytype":"Random","adaptiveSortExecutionTime":6,"insertionSortExecutionTime":25,"shellSortExecutionTime":19,"heapSortExecutionTime":9,"mergeSortExecutionTime":6,"quickSortExecutionTime":7,"parallelMergeSortExecutionTime":4,"parallelQuickSortExecutionTime":3}
{"arraySize":50,"runs":0.44,"arraytype":"Random","adaptiveSortExecutionTime":59,"insertionSortExecutionTime":27,"shellSortExecutionTime":15,"heapSortExecutionTime":11,"mergeSortExecutionTime":11,"quickSortExecutionTime":9,"parallelMergeSortExecutionTime":3,"parallelQuickSortExecutionTime":4}
{"arraySize":50,"runs":0.52,"arraytype":"Random","adaptiveSortExecutionTime":4,"insertionSortExecutionTime":25,"shellSortExecutionTime":15,"heapSortExecutionTime":10,"mergeSortExecutionTime":6,"quickSortExecutionTime":6,"parallelMergeSortExecutionTime":3,"parallelQuickSortExecutionTime":2}
{"arraySize":50,"runs":0.54,"arraytype":"Random","adaptiveSortExecutionTime":5,"insertionSortExecutionTime":23,"shellSortExecutionTime":16,"heapSortExecutionTime":10,"mergeSortExecutionTime":6,"quickSortExecutionTime":7,"parallelMergeSortExecutionTime":3,"parallelQuickSortExecutionTime":3}
{"arraySize":50,"runs":0.52,"arraytype":"Random","adaptiveSortExecutionTime":7,"insertionSortExecutionTime":24,"shellSortExecutionTime":16,"heapSortExecutionTime":13,"mergeSortExecutionTime":6,"quickSortExecutionTime":6,"parallelMergeSortExecutionTime":3,"parallelQuickSortExecutionTime":3}
{"arraySize":50,"runs":0.48,"arraytype":"Random","adaptiveSortExecutionTime":6,"insertionSortExecutionTime":25,"shellSortExecutionTime":15,"heapSortExecutionTime":11,"mergeSortExecutionTime":5,"quickSortExecutionTime":6,"parallelMergeSortExecutionTime":3,"parallelQuickSortExecutionTime":2}
{"arraySize":50,"runs":0.54,"arraytype":"Random","adaptiveSortExecutionTime":5,"insertionSortExecutionTime":25,"shellSortExecutionTime":16,"heapSortExecutionTime":10,"mergeSortExecutionTime":6,"quickSortExecutionTime":6,"parallelMergeSortExecutionTime":3,"parallelQuickSortExecutionTime":3}
{"arraySize":50,"runs":0.5,"arraytype":"Random","adaptiveSortExecutionTime":5,"insertionSortExecutionTime":25,"shellSortExecutionTime":15,"heapSortExecutionTime":11,"mergeSortExecutionTime":6,"quickSortExecutionTime":7,"parallelMergeSortExecutionTime":4,"parallelQuickSortExecutionTime":3}
{"arraySize":50,"runs":0.56,"arraytype":"Random","adaptiveSortExecutionTime":5,"insertionSortExecutionTime":26,"shellSortExecutionTime":16,"heapSortExecutionTime":9,"mergeSortExecutionTime":6,"quickSortExecutionTime":6,"parallelMergeSortExecutionTime":3,"parallelQuickSortExecutionTime":2}
{"arraySize":50,"runs":0.56,"arraytype":"Random","adaptiveSortExecutionTime":6,"insertionSortExecutionTime":22,"shellSortExecutionTime":13,"heapSortExecutionTime":9,"mergeSortExecutionTime":6,"quickSortExecutionTime":7,"parallelMergeSortExecutionTime":3,"parallelQuickSortExecutionTime":3}
{"arraySize":50,"runs":0.42,"arraytype":"Random","adaptiveSortExecutionTime":43,"insertionSortExecutionTime":26,"shellSortExecutionTime":14,"heapSortExecutionTime":10,"mergeSortExecutionTime":6,"quickSortExecutionTime":7,"parallelMergeSortExecutionTime":4,"parallelQuickSortExecutionTime":4}
{"arraySize":50,"runs":0.48,"arraytype":"Random","adaptiveSortExecutionTime":5,"insertionSortExecutionTime":22,"shellSortExecutionTime":14,"heapSortExecutionTime":10,"mergeSortExecutionTime":6,"quickSortExecutionTime":7,"parallelMergeSortExecutionTime":3,"parallelQuickSortExecutionTime":3}
{"arraySize":50,"runs":0.54,"arraytype":"Random","adaptiveSortExecutionTime":4,"insertionSortExecutionTime":16,"shellSortExecutionTime":11,"heapSortExecutionTime":7,"mergeSortExecutionTime":4,"quickSortExecutionTime":5,"parallelMergeSortExecutionTime":2,"parallelQuickSortExecutionTime":2}
{"arraySize":50,"runs":0.5,"arraytype":"Random","adaptiveSortExecutionTime":6,"insertionSortExecutionTime":25,"shellSortExecutionTime":14,"heapSortExecutionTime":9,"mergeSortExecutionTime":6,"quickSortExecutionTime":213,"parallelMergeSortExecutionTime":6,"parallelQuickSortExecutionTime":4}
{"arraySize":50,"runs":0.54,"arraytype":"Random","adaptiveSortExecutionTime":6,"insertionSortExecutionTime":26,"shellSortExecutionTime":18,"heapSortExecutionTime":10,"mergeSortExecutionTime":6,"quickSortExecutionTime":7,"parallelMergeSortExecutionTime":4,"parallelQuickSortExecutionTime":3}
{"arraySize":50,"runs":0.48,"arraytype":"Random","adaptiveSortExecutionTime":6,"insertionSortExecutionTime":30,"shellSortExecutionTime":16,"heapSortExecutionTime":10,"mergeSortExecutionTime":6,"quickSortExecutionTime":7,"parallelMergeSortExecutionTime":4,"parallelQuickSortExecutionTime":3}
{"arraySize":50,"runs":0.56,"arraytype":"Random","adaptiveSortExecutionTime":6,"insertionSortExecutionTime":25,"shellSortExecutionTime":16,"heapSortExecutionTime":10,"mergeSortExecutionTime":6,"quickSortExecutionTime":8,"parallelMergeSortExecutionTime":4,"parallelQuickSortExecutionTime":4}
{"arraySize":50,"runs":0.54,"arraytype":"Random","adaptiveSortExecutionTime":6,"insertionSortExecutionTime":21,"shellSortExecutionTime":16,"heapSortExecutionTime":10,"mergeSortExecutionTime":6,"quickSortExecutionTime":8,"parallelMergeSortExecutionTime":4,"parallelQuickSortExecutionTime":3}
{"arraySize":50,"runs":0.56,"arraytype":"Random","adaptiveSortExecutionTime":5,"insertionSortExecutionTime":30,"shellSortExecutionTime":16,"heapSortExecutionTime":10,"mergeSortExecutionTime":22,"quickSortExecutionTime":14,"parallelMergeSortExecutionTime":4,"parallelQuickSortExecutionTime":3}
{"arraySize":50,"runs":0.56,"arraytype":"Random","adaptiveSortExecutionTime":5,"insertionSortExecutionTime":29,"shellSortExecutionTime":15,"heapSortExecutionTime":9,"mergeSortExecutionTime":8,"quickSortExecutionTime":7,"parallelMergeSortExecutionTime":4,"parallelQuickSortExecutionTime":2}
{"arraySize":50,"runs":0.54,"arraytype":"Random","adaptiveSortExecutionTime":7,"insertionSortExecutionTime":22,"shellSortExecutionTime":19,"heapSortExecutionTime":10,"mergeSortExecutionTime":6,"quickSortExecutionTime":25,"parallelMergeSortExecutionTime":4,"parallelQuickSortExecutionTime":2}
{"arraySize":50,"runs":0.5,"arraytype":"Random","adaptiveSortExecutionTime":5,"insertionSortExecutionTime":25,"shellSortExecutionTime":14,"heapSortExecutionTime":10,"mergeSortExecutionTime":6,"quickSortExecutionTime":7,"parallelMergeSortExecutionTime":3,"parallelQuickSortExecutionTime":3}
{"arraySize":50,"runs":0.56,"arraytype":"Random","adaptiveSortExecutionTime":6,"insertionSortExecutionTime":20,"shellSortExecutionTime":13,"heapSortExecutionTime":10,"mergeSortExecutionTime":5,"quickSortExecutionTime":7,"parallelMergeSortExecutionTime":3,"parallelQuickSortExecutionTime":3}
{"arraySize":50,"runs":0.52,"arraytype":"Random","adaptiveSortExecutionTime":7,"insertionSortExecutionTime":25,"shellSortExecutionTime":16,"heapSortExecutionTime":9,"mergeSortExecutionTime":6,"quickSortExecutionTime":7,"parallelMergeSortExecutionTime":3,"parallelQuickSortExecutionTime":3}
{"arraySize":50,"runs":0.48,"arraytype":"Random","adaptiveSortExecutionTime":5,"insertionSortExecutionTime":26,"shellSortExecutionTime":17,"heapSortExecutionTime":11,"mergeSortExecutionTime":6,"quickSortExecutionTime":6,"parallelMergeSortExecutionTime":3,"parallelQuickSortExecutionTime":3}
{"arraySize":50,"runs":0.46,"arraytype":"Random","adaptiveSortExecutionTime":6,"insertionSortExecutionTime":22,"shellSortExecutionTime":15,"heapSortExecutionTime":10,"mergeSortExecutionTime":6,"quickSortExecutionTime":9,"parallelMergeSortExecutionTime":4,"parallelQuickSortExecutionTime":3}
{"arraySize":50,"runs":0.5,"arraytype":"Random","adaptiveSortExecutionTime":6,"insertionSortExecutionTime":25,"shellSortExecutionTime":15,"heapSortExecutionTime":11,"mergeSortExecutionTime":6,"quickSortExecutionTime":8,"parallelMergeSortExecutionTime":3,"parallelQuickSortExecutionTime":4}
{"arraySize":50,"runs":0.48,"arraytype":"Random","adaptiveSortExecutionTime":5,"insertionSortExecutionTime":26,"shellSortExecutionTime":17,"heapSortExecutionTime":11,"mergeSortExecutionTime":6,"quickSortExecutionTime":7,"parallelMergeSortExecutionTime":4,"parallelQuickSortExecutionTime":2}
{"arraySize":50,"runs":0.48,"arraytype":"Random","adaptiveSortExecutionTime":6,"insertionSortExecutionTime":22,"shellSortExecutionTime":19,"heapSortExecutionTime":10,"mergeSortExecutionTime":6,"quickSortExecutionTime":18,"parallelMergeSortExecutionTime":4,"parallelQuickSortExecutionTime":3}
{"arraySize":50,"runs":0.54,"arraytype":"Random","adaptiveSortExecutionTime":5,"insertionSortExecutionTime":29,"shellSortExecutionTime":16,"heapSortExecutionTime":10,"mergeSortExecutionTime":7,"quickSortExecutionTime":8,"parallelMergeSortExecutionTime":3,"parallelQuickSortExecutionTime":3}
{"arraySize":50,"runs":0.46,"arraytype":"Random","adaptiveSortExecutionTime":6,"insertionSortExecutionTime":26,"shellSortExecutionTime":17,"heapSortExecutionTime":10,"mergeSortExecutionTime":7,"quickSortExecutionTime":7,"parallelMergeSortExecutionTime":8,"parallelQuickSortExecutionTime":3}
{"arraySize":50,"runs":0.52,"arraytype":"Random","adaptiveSortExecutionTime":5,"insertionSortExecutionTime":21,"shellSortExecutionTime":13,"heapSortExecutionTime":10,"mergeSortExecutionTime":6,"quickSortExecutionTime":9,"parallelMergeSortExecutionTime":4,"parallelQuickSortExecutionTime":4}
{"arraySize":50,"runs":0.58,"arraytype":"Random","adaptiveSortExecutionTime":4,"insertionSortExecutionTime":30,"shellSortExecutionTime":16,"heapSortExecutionTime":10,"mergeSortExecutionTime":6,"quickSortExecutionTime":6,"parallelMergeSortExecutionTime":3,"parallelQuickSortExecutionTime":3}
{"arraySize":50,"runs":0.54,"arraytype":"Random","adaptiveSortExecutionTime":5,"insertionSortExecutionTime":24,"shellSortExecutionTime":14,"heapSortExecutionTime":9,"mergeSortExecutionTime":6,"quickSortExecutionTime":7,"parallelMergeSortExecutionTime":3,"parallelQuickSortExecutionTime":3}
{"arraySize":50,"runs":0.52,"arraytype":"Random","adaptiveSortExecutionTime":6,"insertionSortExecutionTime":23,"shellSortExecutionTime":15,"heapSortExecutionTime":9,"mergeSortExecutionTime":6,"quickSortExecutionTime":7,"parallelMergeSortExecutionTime":4,"parallelQuickSortExecutionTime":3}
{"arraySize":50,"runs":0.48,"arraytype":"Random","adaptiveSortExecutionTime":5,"insertionSortExecutionTime":29,"shellSortExecutionTime":13,"heapSortExecutionTime":9,"mergeSortExecutionTime":6,"quickSortExecutionTime":6,"parallelMergeSortExecutionTime":3,"parallelQuickSortExecutionTime":3}
{"arraySize":50,"runs":0.54,"arraytype":"Random","adaptiveSortExecutionTime":5,"insertionSortExecutionTime":27,"shellSortExecutionTime":18,"heapSortExecutionTime":10,"mergeSortExecutionTime":6,"quickSortExecutionTime":6,"parallelMergeSortExecutionTime":3,"parallelQuickSortExecutionTime":6}
{"arraySize":50,"runs":0.44,"arraytype":"Random","adaptiveSortExecutionTime":19,"insertionSortExecutionTime":25,"shellSortExecutionTime":16,"heapSortExecutionTime":10,"mergeSortExecutionTime":6,"quickSortExecutionTime":7,"parallelMergeSortExecutionTime":3,"parallelQuickSortExecutionTime":3}
{"arraySize":50,"runs":0.48,"arraytype":"Random","adaptiveSortExecutionTime":5,"insertionSortExecutionTime":27,"shellSortExecutionTime":16,"heapSortExecutionTime":10,"mergeSortExecutionTime":5,"quickSortExecutionTime":7,"parallelMergeSortExecutionTime":3,"parallelQuickSortExecutionTime":2}
{"arraySize":50,"runs":0.48,"arraytype":"Random","adaptiveSortExecutionTime":5,"insertionSortExecutionTime":28,"shellSortExecutionTime":13,"heapSortExecutionTime":9,"mergeSortExecutionTime":7,"quickSortExecutionTime":6,"parallelMergeSortExecutionTime":3,"parallelQuickSortExecutionTime":2}
{"arraySize":50,"runs":0.56,"arraytype":"Random","adaptiveSortExecutionTime":5,"insertionSortExecutionTime":22,"shellSortExecutionTime":19,"heapSortExecutionTime":10,"mergeSortExecutionTime":6,"quickSortExecutionTime":7,"parallelMergeSortExecutionTime":3,"parallelQuickSortExecutionTime":3}
{"arraySize":50,"runs":0.5,"arraytype":"Random","adaptiveSortExecutionTime":7,"insertionSortExecutionTime":28,"shellSortExecutionTime":14,"heapSortExecutionTime":10,"mergeSortExecutionTime":6,"quickSortExecutionTime":8,"parallelMergeSortExecutionTime":5,"parallelQuickSortExecutionTime":4}
{"arraySize":50,"runs":0.5,"arraytype":"Random","adaptiveSortExecutionTime":6,"insertionSortExecutionTime":29,"shellSortExecutionTime":15,"heapSortExecutionTime":10,"mergeSortExecutionTime":5,"quickSortExecutionTime":8,"parallelMergeSortExecutionTime":3,"parallelQuickSortExecutionTime":3}
{"arraySize":50,"runs":0.52,"arraytype":"Random","adaptiveSortExecutionTime":7,"insertionSortExecutionTime":22,"shellSortExecutionTime":16,"heapSortExecutionTime":11,"mergeSortExecutionTime":6,"quickSortExecutionTime":9,"parallelMergeSortExecutionTime":4,"parallelQuickSortExecutionTime":4}
{"arraySize":50,"runs":0.56,"arraytype":"Random","adaptiveSortExecutionTime":8,"insertionSortExecutionTime":32,"shellSortExecutionTime":17,"heapSortExecutionTime":9,"mergeSortExecutionTime":6,"quickSortExecutionTime":10,"parallelMergeSortExecutionTime":71,"parallelQuickSortExecutionTime":6}
{"arraySize":50,"runs":0.46,"arraytype":"Random","adaptiveSortExecutionTime":6,"insertionSortExecutionTime":22,"shellSortExecutionTime":16,"heapSortExecutionTime":11,"mergeSortExecutionTime":6,"quickSortExecutionTime":8,"parallelMergeSortExecutionTime":3,"parallelQuickSortExecutionTime":3}
{"arraySize":50,"runs":0.5,"arraytype":"Random","adaptiveSortExecutionTime":5,"insertionSortExecutionTime":22,"shellSortExecutionTime":16,"heapSortExecutionTime":10,"mergeSortExecutionTime":29,"quickSortExecutionTime":7,"parallelMergeSortExecutionTime":4,"parallelQuickSortExecutionTime":3}
{"arraySize":50,"runs":0.58,"arraytype":"Random","adaptiveSortExecutionTime":7,"insertionSortExecutionTime":28,"shellSortExecutionTime":25,"heapSortExecutionTime":12,"mergeSortExecutionTime":6,"quickSortExecutionTime":7,"parallelMergeSortExecutionTime":4,"parallelQuickSortExecutionTime":3}
{"arraySize":50,"runs":0.52,"arraytype":"Random","adaptiveSortExecutionTime":5,"insertionSortExecutionTime":21,"shellSortExecutionTime":21,"heapSortExecutionTime":11,"mergeSortExecutionTime":5,"quickSortExecutionTime":7,"parallelMergeSortExecutionTime":4,"parallelQuickSortExecutionTime":2}
{"arraySize":50,"runs":0.44,"arraytype":"Random","adaptiveSortExecutionTime":15,"insertionSortExecutionTime":25,"shellSortExecutionTime":15,"heapSortExecutionTime":9,"mergeSortExecutionTime":5,"quickSortExecutionTime":6,"parallelMergeSortExecutionTime":3,"parallelQuickSortExecutionTime":2}
{"arraySize":50,"runs":0.54,"arraytype":"Random","adaptiveSortExecutionTime":5,"insertionSortExecutionTime":26,"shellSortExecutionTime":15,"heapSortExecutionTime":11,"mergeSortExecutionTime":6,"quickSortExecutionTime":7,"parallelMergeSortExecutionTime":4,"parallelQuickSortExecutionTime":3}
{"arraySize":50,"runs":0.48,"arraytype":"Random","adaptiveSortExecutionTime":5,"insertionSortExecutionTime":18,"shellSortExecutionTime":15,"heapSortExecutionTime":10,"mergeSortExecutionTime":6,"quickSortExecutionTime":7,"parallelMergeSortExecutionTime":4,"parallelQuickSortExecutionTime":3}
{"arraySize":50,"runs":0.54,"arraytype":"Random","adaptiveSortExecutionTime":9,"insertionSortExecutionTime":28,"shellSortExecutionTime":17,"heapSortExecutionTime":10,"mergeSortExecutionTime":6,"quickSortExecutionTime":7,"parallelMergeSortExecutionTime":3,"parallelQuickSortExecutionTime":3}
{"arraySize":50,"runs":0.54,"arraytype":"Random","adaptiveSortExecutionTime":4,"insertionSortExecutionTime":29,"shellSortExecutionTime":16,"heapSortExecutionTime":10,"mergeSortExecutionTime":5,"quickSortExecutionTime":7,"parallelMergeSortExecutionTime":3,"parallelQuickSortExecutionTime":2}
{"arraySize":50,"runs":0.52,"arraytype":"Random","adaptiveSortExecutionTime":5,"insertionSortExecutionTime":22,"shellSortExecutionTime":16,"heapSortExecutionTime":9,"mergeSortExecutionTime":5,"quickSortExecutionTime":6,"parallelMergeSortExecutionTime":3,"parallelQuickSortExecutionTime":3}
{"arraySize":50,"runs":0.56,"arraytype":"Random","adaptiveSortExecutionTime":6,"insertionSortExecutionTime":316,"shellSortExecutionTime":18,"heapSortExecutionTime":11,"mergeSortExecutionTime":6,"quickSortExecutionTime":8,"parallelMergeSortExecutionTime":4,"parallelQuickSortExecutionTime":3}
{"arraySize":50,"runs":0.56,"arraytype":"Random","adaptiveSortExecutionTime":6,"insertionSortExecutionTime":38,"shellSortExecutionTime":18,"heapSortExecutionTime":10,"mergeSortExecutionTime":6,"quickSortExecutionTime":8,"parallelMergeSortExecutionTime":4,"parallelQuickSortExecutionTime":4}
{"arraySize":50,"runs":0.48,"arraytype":"Random","adaptiveSortExecutionTime":5,"insertionSortExecutionTime":6,"shellSortExecutionTime":16,"heapSortExecutionTime":10,"mergeSortExecutionTime":6,"quickSortExecutionTime":6,"parallelMergeSortExecutionTime":3,"parallelQuickSortExecutionTime":2}
{"arraySize":50,"runs":0.54,"arraytype":"Random","adaptiveSortExecutionTime":6,"insertionSortExecutionTime":6,"shellSortExecutionTime":15,"heapSortExecutionTime":11,"mergeSortExecutionTime":6,"quickSortExecutionTime":7,"parallelMergeSortExecutionTime":3,"parallelQuickSortExecutionTime":3}
{"arraySize":50,"runs":0.54,"arraytype":"Random","adaptiveSortExecutionTime":6,"insertionSortExecutionTime":5,"shellSortExecutionTime":16,"heapSortExecutionTime":10,"mergeSortExecutionTime":6,"quickSortExecutionTime":7,"parallelMergeSortExecutionTime":4,"parallelQuickSortExecutionTime":3}
{"arraySize":50,"runs":0.5,"arraytype":"Random","adaptiveSortExecutionTime":6,"insertionSortExecutionTime":5,"shellSortExecutionTime":20,"heapSortExecutionTime":11,"mergeSortExecutionTime":6,"quickSortExecutionTime":7,"parallelMergeSortExecutionTime":3,"parallelQuickSortExecutionTime":3}
{"arraySize":50,"runs":0.48,"arraytype":"Random","adaptiveSortExecutionTime":7,"insertionSortExecutionTime":6,"shellSortExecutionTime":15,"heapSortExecutionTime":9,"mergeSortExecutionTime":5,"quickSortExecutionTime":51,"parallelMergeSortExecutionTime":3,"parallelQuickSortExecutionTime":148}
{"arraySize":50,"runs":0.5,"arraytype":"Random","adaptiveSortExecutionTime":5,"insertionSortExecutionTime":5,"shellSortExecutionTime":16,"heapSortExecutionTime":11,"mergeSortExecutionTime":6,"quickSortExecutionTime":6,"parallelMergeSortExecutionTime":3,"parallelQuickSortExecutionTime":3}
{"arraySize":50,"runs":0.54,"arraytype":"Random","adaptiveSortExecutionTime":6,"insertionSortExecutionTime":4,"shellSortExecutionTime":16,"heapSortExecutionTime":10,"mergeSortExecutionTime":6,"quickSortExecutionTime":18,"parallelMergeSortExecutionTime":4,"parallelQuickSortExecutionTime":3}
