{"arraySize":500,"runs":0.01,"arraytype":"Almost-Sorted-0.2","insertionSortExecutionTime":39,"shellSortExecutionTime":22,"heapSortExecutionTime":65,"mergeSortExecutionTime":71,"quickSortExecutionTime":16,"parallelMergeSortExecutionTime":13}
{"arraySize":500,"runs":0.01,"arraytype":"Almost-Sorted-0.2","insertionSortExecutionTime":45,"shellSortExecutionTime":23,"heapSortExecutionTime":61,"mergeSortExecutionTime":31,"quickSortExecutionTime":14,"parallelMergeSortExecutionTime":11}
{"arraySize":500,"runs":0.012,"arraytype":"Almost-Sorted-0.2","insertionSortExecutionTime":45,"shellSortExecutionTime":22,"heapSortExecutionTime":59,"mergeSortExecutionTime":30,"quickSortExecutionTime":14,"parallelMergeSortExecutionTime":12}
{"arraySize":500,"runs":0.01,"arraytype":"Almost-Sorted-0.2","insertionSortExecutionTime":34,"shellSortExecutionTime":18,"heapSortExecutionTime":76,"mergeSortExecutionTime":25,"quickSortExecutionTime":15,"parallelMergeSortExecutionTime":112}
{"arraySize":500,"runs":0.01,"arraytype":"Almost-Sorted-0.2","insertionSortExecutionTime":94,"shellSortExecutionTime":45,"heapSortExecutionTime":79,"mergeSortExecutionTime":31,"quickSortExecutionTime":18,"parallelMergeSortExecutionTime":11}
{"arraySize":500,"runs":0.012,"arraytype":"Almost-Sorted-0.2","insertionSortExecutionTime":44,"shellSortExecutionTime":22,"heapSortExecutionTime":59,"mergeSortExecutionTime":30,"quickSortExecutionTime":15,"parallelMergeSortExecutionTime":11}
{"arraySize":500,"runs":0.012,"arraytype":"Almost-Sorted-0.2","insertionSortExecutionTime":43,"shellSortExecutionTime":23,"heapSortExecutionTime":58,"mergeSortExecutionTime":30,"quickSortExecutionTime":14,"parallelMergeSortExecutionTime":11}
{"arraySize":500,"runs":0.012,"arraytype":"Almost-Sorted-0.2","insertionSortExecutionTime":41,"shellSortExecutionTime":21,"heapSortExecutionTime":57,"mergeSortExecutionTime":31,"quickSortExecutionTime":14,"parallelMergeSortExecutionTime":12}
{"arraySize":500,"runs":0.012,"arraytype":"Almost-Sorted-0.2","insertionSortExecutionTime":45,"shellSortExecutionTime":23,"heapSortExecutionTime":60,"mergeSortExecutionTime":30,"quickSortExecutionTime":15,"parallelMergeSortExecutionTime":12}
{"arraySize":500,"runs":0.014,"arraytype":"Almost-Sorted-0.2","insertionSortExecutionTime":45,"shellSortExecutionTime":20,"heapSortExecutionTime":59,"mergeSortExecutionTime":48,"quickSortExecutionTime":15,"parallelMergeSortExecutionTime":11}
{"arraySize":500,"runs":0.01,"arraytype":"Almost-Sorted-0.2","insertionSortExecutionTime":38,"shellSortExecutionTime":19,"heapSortExecutionTime":52,"mergeSortExecutionTime":25,"quickSortExecutionTime":13,"parallelMergeSortExecutionTime":50}
{"arraySize":500,"runs":0.012,"arraytype":"Almost-Sorted-0.2","insertionSortExecutionTime":40,"shellSortExecutionTime":20,"heapSortExecutionTime":59,"mergeSortExecutionTime":28,"quickSortExecutionTime":14,"parallelMergeSortExecutionTime":10}
{"arraySize":500,"runs":0.01,"arraytype":"Almost-Sorted-0.2","insertionSortExecutionTime":40,"shellSortExecutionTime":22,"heapSortExecutionTime":58,"mergeSortExecutionTime":29,"quickSortExecutionTime":14,"parallelMergeSortExecutionTime":10}
{"arraySize":500,"runs":0.01,"arraytype":"Almost-Sorted-0.2","insertionSortExecutionTime":37,"shellSortExecutionTime":21,"heapSortExecutionTime":57,"mergeSortExecutionTime":30,"quickSortExecutionTime":13,"parallelMergeSortExecutionTime":10}
{"arraySize":500,"runs":0.012,"arraytype":"Almost-Sorted-0.2","insertionSortExecutionTime":39,"shellSortExecutionTime":20,"heapSortExecutionTime":41,"mergeSortExecutionTime":20,"quickSortExecutionTime":13,"parallelMergeSortExecutionTime":8}
{"arraySize":500,"runs":0.012,"arraytype":"Almost-Sorted-0.2","insertionSortExecutionTime":47,"shellSortExecutionTime":23,"heapSortExecutionTime":62,"mergeSortExecutionTime":31,"quickSortExecutionTime":15,"parallelMergeSortExecutionTime":12}
{"arraySize":500,"runs":0.01,"arraytype":"Almost-Sorted-0.2","insertionSortExecutionTime":44,"shellSortExecutionTime":29,"heapSortExecutionTime":59,"mergeSortExecutionTime":31,"quickSortExecutionTime":15,"parallelMergeSortExecutionTime":11}
{"arraySize":500,"runs":0.012,"arraytype":"Almost-Sorted-0.2","insertionSortExecutionTime":44,"shellSortExecutionTime":21,"heapSortExecutionTime":59,"mergeSortExecutionTime":30,"quickSortExecutionTime":14,"parallelMergeSortExecutionTime":19}
{"arraySize":500,"runs":0.01,"arraytype":"Almost-Sorted-0.2","insertionSortExecutionTime":44,"shellSortExecutionTime":20,"heapSortExecutionTime":55,"mergeSortExecutionTime":22,"quickSortExecutionTime":10,"parallelMergeSortExecutionTime":8}
{"arraySize":500,"runs":0.01,"arraytype":"Almost-Sorted-0.2","insertionSortExecutionTime":41,"shellSortExecutionTime":16,"heapSortExecutionTime":95,"mergeSortExecutionTime":20,"quickSortExecutionTime":10,"parallelMergeSortExecutionTime":8}
{"arraySize":500,"runs":0.01,"arraytype":"Almost-Sorted-0.2","insertionSortExecutionTime":45,"shellSortExecutionTime":20,"heapSortExecutionTime":54,"mergeSortExecutionTime":20,"quickSortExecutionTime":11,"parallelMergeSortExecutionTime":17}
{"arraySize":500,"runs":0.012,"arraytype":"Almost-Sorted-0.2","insertionSortExecutionTime":43,"shellSortExecutionTime":20,"heapSortExecutionTime":52,"mergeSortExecutionTime":20,"quickSortExecutionTime":10,"parallelMergeSortExecutionTime":7}
{"arraySize":500,"runs":0.01,"arraytype":"Almost-Sorted-0.2","insertionSortExecutionTime":42,"shellSortExecutionTime":20,"heapSortExecutionTime":43,"mergeSortExecutionTime":21,"quickSortExecutionTime":16,"parallelMergeSortExecutionTime":9}
{"arraySize":500,"runs":0.012,"arraytype":"Almost-Sorted-0.2","insertionSortExecutionTime":45,"shellSortExecutionTime":19,"heapSortExecutionTime":54,"mergeSortExecutionTime":20,"quickSortExecutionTime":10,"parallelMergeSortExecutionTime":8}
{"arraySize":500,"runs":0.01,"arraytype":"Almost-Sorted-0.2","insertionSortExecutionTime":38,"shellSortExecutionTime":20,"heapSortExecutionTime":55,"mergeSortExecutionTime":27,"quickSortExecutionTime":13,"parallelMergeSortExecutionTime":10}
{"arraySize":500,"runs":0.01,"arraytype":"Almost-Sorted-0.2","insertionSortExecutionTime":45,"shellSortExecutionTime":19,"heapSortExecutionTime":61,"mergeSortExecutionTime":20,"quickSortExecutionTime":11,"parallelMergeSortExecutionTime":8}
{"arraySize":500,"runs":0.012,"arraytype":"Almost-Sorted-0.2","insertionSortExecutionTime":43,"shellSortExecutionTime":22,"heapSortExecutionTime":52,"mergeSortExecutionTime":20,"quickSortExecutionTime":10,"parallelMergeSortExecutionTime":7}
{"arraySize":500,"runs":0.012,"arraytype":"Almost-Sorted-0.2","insertionSortExecutionTime":27,"shellSortExecutionTime":17,"heapSortExecutionTime":42,"mergeSortExecutionTime":20,"quickSortExecutionTime":11,"parallelMergeSortExecutionTime":8}
{"arraySize":500,"runs":0.01,"arraytype":"Almost-Sorted-0.2","insertionSortExecutionTime":44,"shellSortExecutionTime":21,"heapSortExecutionTime":59,"mergeSortExecutionTime":31,"quickSortExecutionTime":15,"parallelMergeSortExecutionTime":11}
{"arraySize":500,"runs":0.01,"arraytype":"Almost-Sorted-0.2","insertionSortExecutionTime":36,"shellSortExecutionTime":21,"heapSortExecutionTime":46,"mergeSortExecutionTime":21,"quickSortExecutionTime":11,"parallelMergeSortExecutionTime":8}
{"arraySize":500,"runs":0.01,"arraytype":"Almost-Sorted-0.2","insertionSortExecutionTime":27,"shellSortExecutionTime":16,"heapSortExecutionTime":41,"mergeSortExecutionTime":21,"quickSortExecutionTime":18,"parallelMergeSortExecutionTime":104}
{"arraySize":500,"runs":0.01,"arraytype":"Almost-Sorted-0.2","insertionSortExecutionTime":46,"shellSortExecutionTime":22,"heapSortExecutionTime":208,"mergeSortExecutionTime":32,"quickSortExecutionTime":15,"parallelMergeSortExecutionTime":11}
{"arraySize":500,"runs":0.014,"arraytype":"Almost-Sorted-0.2","insertionSortExecutionTime":43,"shellSortExecutionTime":23,"heapSortExecutionTime":64,"mergeSortExecutionTime":33,"quickSortExecutionTime":16,"parallelMergeSortExecutionTime":12}
{"arraySize":500,"runs":0.014,"arraytype":"Almost-Sorted-0.2","insertionSortExecutionTime":48,"shellSortExecutionTime":23,"heapSortExecutionTime":53,"mergeSortExecutionTime":31,"quickSortExecutionTime":14,"parallelMergeSortExecutionTime":11}
{"arraySize":500,"runs":0.016,"arraytype":"Almost-Sorted-0.2","insertionSortExecutionTime":42,"shellSortExecutionTime":22,"heapSortExecutionTime":50,"mergeSortExecutionTime":31,"quickSortExecutionTime":15,"parallelMergeSortExecutionTime":12}
{"arraySize":500,"runs":0.01,"arraytype":"Almost-Sorted-0.2","insertionSortExecutionTime":42,"shellSortExecutionTime":21,"heapSortExecutionTime":50,"mergeSortExecutionTime":31,"quickSortExecutionTime":15,"parallelMergeSortExecutionTime":11}
{"arraySize":500,"runs":0.01,"arraytype":"Almost-Sorted-0.2","insertionSortExecutionTime":64,"shellSortExecutionTime":21,"heapSortExecutionTime":88,"mergeSortExecutionTime":30,"quickSortExecutionTime":14,"parallelMergeSortExecutionTime":11}
{"arraySize":500,"runs":0.01,"arraytype":"Almost-Sorted-0.2","insertionSortExecutionTime":47,"shellSortExecutionTime":24,"heapSortExecutionTime":52,"mergeSortExecutionTime":31,"quickSortExecutionTime":15,"parallelMergeSortExecutionTime":11}
{"arraySize":500,"runs":0.01,"arraytype":"Almost-Sorted-0.2","insertionSortExecutionTime":44,"shellSortExecutionTime":19,"heapSortExecutionTime":48,"mergeSortExecutionTime":24,"quickSortExecutionTime":11,"parallelMergeSortExecutionTime":7}
{"arraySize":500,"runs":0.01,"arraytype":"Almost-Sorted-0.2","insertionSortExecutionTime":32,"shellSortExecutionTime":16,"heapSortExecutionTime":38,"mergeSortExecutionTime":21,"quickSortExecutionTime":10,"parallelMergeSortExecutionTime":8}
{"arraySize":500,"runs":0.014,"arraytype":"Almost-Sorted-0.2","insertionSortExecutionTime":41,"shellSortExecutionTime":20,"heapSortExecutionTime":48,"mergeSortExecutionTime":30,"quickSortExecutionTime":14,"parallelMergeSortExecutionTime":11}
{"arraySize":500,"runs":0.01,"arraytype":"Almost-Sorted-0.2","insertionSortExecutionTime":44,"shellSortExecutionTime":22,"heapSortExecutionTime":54,"mergeSortExecutionTime":31,"quickSortExecutionTime":15,"parallelMergeSortExecutionTime":12}
{"arraySize":500,"runs":0.016,"arraytype":"Almost-Sorted-0.2","insertionSortExecutionTime":42,"shellSortExecutionTime":22,"heapSortExecutionTime":52,"mergeSortExecutionTime":31,"quickSortExecutionTime":15,"parallelMergeSortExecutionTime":12}
{"arraySize":500,"runs":0.012,"arraytype":"Almost-Sorted-0.2","insertionSortExecutionTime":42,"shellSortExecutionTime":20,"heapSortExecutionTime":49,"mergeSortExecutionTime":29,"quickSortExecutionTime":14,"parallelMergeSortExecutionTime":10}
{"arraySize":500,"runs":0.01,"arraytype":"Almost-Sorted-0.2","insertionSortExecutionTime":43,"shellSortExecutionTime":22,"heapSortExecutionTime":52,"mergeSortExecutionTime":30,"quickSortExecutionTime":14,"parallelMergeSortExecutionTime":11}
{"arraySize":500,"runs":0.01,"arraytype":"Almost-Sorted-0.2","insertionSortExecutionTime":40,"shellSortExecutionTime":21,"heapSortExecutionTime":50,"mergeSortExecutionTime":30,"quickSortExecutionTime":15,"parallelMergeSortExecutionTime":11}
{"arraySize":500,"runs":0.01,"arraytype":"Almost-Sorted-0.2","insertionSortExecutionTime":44,"shellSortExecutionTime":23,"heapSortExecutionTime":55,"mergeSortExecutionTime":32,"quickSortExecutionTime":15,"parallelMergeSortExecutionTime":12}
{"arraySize":500,"runs":0.01,"arraytype":"Almost-Sorted-0.2","insertionSortExecutionTime":39,"shellSortExecutionTime":22,"heapSortExecutionTime":52,"mergeSortExecutionTime":34,"quickSortExecutionTime":14,"parallelMergeSortExecutionTime":9}
{"arraySize":500,"runs":0.01,"arraytype":"Almost-Sorted-0.2","insertionSortExecutionTime":40,"shellSortExecutionTime":21,"heapSortExecutionTime":50,"mergeSortExecutionTime":31,"quickSortExecutionTime":15,"parallelMergeSortExecutionTime":11}
{"arraySize":500,"runs":0.01,"arraytype":"Almost-Sorted-0.2","insertionSortExecutionTime":41,"shellSortExecutionTime":19,"heapSortExecutionTime":46,"mergeSortExecutionTime":27,"quickSortExecutionTime":16,"parallelMergeSortExecutionTime":13}
{"arraySize":500,"runs":0.012,"arraytype":"Almost-Sorted-0.2","insertionSortExecutionTime":43,"shellSortExecutionTime":22,"heapSortExecutionTime":51,"mergeSortExecutionTime":35,"quickSortExecutionTime":16,"parallelMergeSortExecutionTime":13}
{"arraySize":500,"runs":0.01,"arraytype":"Almost-Sorted-0.2","insertionSortExecutionTime":39,"shellSortExecutionTime":20,"heapSortExecutionTime":47,"mergeSortExecutionTime":28,"quickSortExecutionTime":16,"parallelMergeSortExecutionTime":10}
{"arraySize":500,"runs":0.012,"arraytype":"Almost-Sorted-0.2","insertionSortExecutionTime":46,"shellSortExecutionTime":22,"heapSortExecutionTime":50,"mergeSortExecutionTime":30,"quickSortExecutionTime":14,"parallelMergeSortExecutionTime":11}
{"arraySize":500,"runs":0.012,"arraytype":"Almost-Sorted-0.2","insertionSortExecutionTime":45,"shellSortExecutionTime":21,"heapSortExecutionTime":52,"mergeSortExecutionTime":33,"quickSortExecutionTime":16,"parallelMergeSortExecutionTime":14}
{"arraySize":500,"runs":0.01,"arraytype":"Almost-Sorted-0.2","insertionSortExecutionTime":38,"shellSortExecutionTime":20,"heapSortExecutionTime":50,"mergeSortExecutionTime":28,"quickSortExecutionTime":14,"parallelMergeSortExecutionTime":11}
{"arraySize":500,"runs":0.01,"arraytype":"Almost-Sorted-0.2","insertionSortExecutionTime":45,"shellSortExecutionTime":22,"heapSortExecutionTime":52,"mergeSortExecutionTime":34,"quickSortExecutionTime":18,"parallelMergeSortExecutionTime":13}
{"arraySize":500,"runs":0.01,"arraytype":"Almost-Sorted-0.2","insertionSortExecutionTime":38,"shellSortExecutionTime":22,"heapSortExecutionTime":786,"mergeSortExecutionTime":32,"quickSortExecutionTime":18,"parallelMergeSortExecutionTime":12}
{"arraySize":500,"runs":0.012,"arraytype":"Almost-Sorted-0.2","insertionSortExecutionTime":46,"shellSortExecutionTime":22,"heapSortExecutionTime":52,"mergeSortExecutionTime":32,"quickSortExecutionTime":16,"parallelMergeSortExecutionTime":12}
{"arraySize":500,"runs":0.012,"arraytype":"Almost-Sorted-0.2","insertionSortExecutionTime":45,"shellSortExecutionTime":22,"heapSortExecutionTime":50,"mergeSortExecutionTime":34,"quickSortExecutionTime":16,"parallelMergeSortExecutionTime":13}
{"arraySize":500,"runs":0.018,"arraytype":"Almost-Sorted-0.2","insertionSortExecutionTime":43,"shellSortExecutionTime":22,"heapSortExecutionTime":55,"mergeSortExecutionTime":34,"quickSortExecutionTime":17,"parallelMergeSortExecutionTime":13}
{"arraySize":500,"runs":0.01,"arraytype":"Almost-Sorted-0.2","insertionSortExecutionTime":26,"shellSortExecutionTime":16,"heapSortExecutionTime":38,"mergeSortExecutionTime":22,"quickSortExecutionTime":10,"parallelMergeSortExecutionTime":8}
{"arraySize":500,"runs":0.012,"arraytype":"Almost-Sorted-0.2","insertionSortExecutionTime":40,"shellSortExecutionTime":17,"heapSortExecutionTime":38,"mergeSortExecutionTime":22,"quickSortExecutionTime":12,"parallelMergeSortExecutionTime":9}
{"arraySize":500,"runs":0.012,"arraytype":"Almost-Sorted-0.2","insertionSortExecutionTime":45,"shellSortExecutionTime":21,"heapSortExecutionTime":66,"mergeSortExecutionTime":33,"quickSortExecutionTime":16,"parallelMergeSortExecutionTime":13}
{"arraySize":500,"runs":0.014,"arraytype":"Almost-Sorted-0.2","insertionSortExecutionTime":45,"shellSortExecutionTime":22,"heapSortExecutionTime":54,"mergeSortExecutionTime":33,"quickSortExecutionTime":17,"parallelMergeSortExecutionTime":13}
{"arraySize":500,"runs":0.01,"arraytype":"Almost-Sorted-0.2","insertionSortExecutionTime":40,"shellSortExecutionTime":20,"heapSortExecutionTime":48,"mergeSortExecutionTime":27,"quickSortExecutionTime":13,"parallelMergeSortExecutionTime":11}
{"arraySize":500,"runs":0.012,"arraytype":"Almost-Sorted-0.2","insertionSortExecutionTime":40,"shellSortExecutionTime":20,"heapSortExecutionTime":48,"mergeSortExecutionTime":30,"quickSortExecutionTime":16,"parallelMergeSortExecutionTime":12}
{"arraySize":500,"runs":0.012,"arraytype":"Almost-Sorted-0.2","insertionSortExecutionTime":46,"shellSortExecutionTime":23,"heapSortExecutionTime":51,"mergeSortExecutionTime":33,"quickSortExecutionTime":17,"parallelMergeSortExecutionTime":12}
{"arraySize":500,"runs":0.01,"arraytype":"Almost-Sorted-0.2","insertionSortExecutionTime":41,"shellSortExecutionTime":22,"heapSortExecutionTime":52,"mergeSortExecutionTime":31,"quickSortExecutionTime":16,"parallelMergeSortExecutionTime":13}
{"arraySize":500,"runs":0.012,"arraytype":"Almost-Sorted-0.2","insertionSortExecutionTime":41,"shellSortExecutionTime":30,"heapSortExecutionTime":47,"mergeSortExecutionTime":27,"quickSortExecutionTime":14,"parallelMergeSortExecutionTime":11}
{"arraySize":500,"runs":0.01,"arraytype":"Almost-Sorted-0.2","insertionSortExecutionTime":44,"shellSortExecutionTime":23,"heapSortExecutionTime":46,"mergeSortExecutionTime":27,"quickSortExecutionTime":15,"parallelMergeSortExecutionTime":12}
{"arraySize":500,"runs":0.01,"arraytype":"Almost-Sorted-0.2","insertionSortExecutionTime":39,"shellSortExecutionTime":21,"heapSortExecutionTime":49,"mergeSortExecutionTime":29,"quickSortExecutionTime":15,"parallelMergeSortExecutionTime":12}
{"arraySize":500,"runs":0.012,"arraytype":"Almost-Sorted-0.2","insertionSortExecutionTime":43,"shellSortExecutionTime":20,"heapSortExecutionTime":49,"mergeSortExecutionTime":29,"quickSortExecutionTime":13,"parallelMergeSortExecutionTime":12}
{"arraySize":500,"runs":0.01,"arraytype":"Almost-Sorted-0.2","insertionSortExecutionTime":38,"shellSortExecutionTime":20,"heapSortExecutionTime":52,"mergeSortExecutionTime":62,"quickSortExecutionTime":45,"parallelMergeSortExecutionTime":20}
{"arraySize":500,"runs":0.014,"arraytype":"Almost-Sorted-0.2","insertionSortExecutionTime":43,"shellSortExecutionTime":20,"heapSortExecutionTime":83,"mergeSortExecutionTime":45,"quickSortExecutionTime":16,"parallelMergeSortExecutionTime":13}
{"arraySize":500,"runs":0.01,"arraytype":"Almost-Sorted-0.2","insertionSortExecutionTime":44,"shellSortExecutionTime":25,"heapSortExecutionTime":54,"mergeSortExecutionTime":32,"quickSortExecutionTime":15,"parallelMergeSortExecutionTime":13}
{"arraySize":500,"runs":0.01,"arraytype":"Almost-Sorted-0.2","insertionSortExecutionTime":41,"shellSortExecutionTime":22,"heapSortExecutionTime":50,"mergeSortExecutionTime":32,"quickSortExecutionTime":16,"parallelMergeSortExecutionTime":13}
{"arraySize":500,"runs":0.012,"arraytype":"Almost-Sorted-0.2","insertionSortExecutionTime":47,"shellSortExecutionTime":23,"heapSortExecutionTime":51,"mergeSortExecutionTime":32,"quickSortExecutionTime":14,"parallelMergeSortExecutionTime":11}
{"arraySize":500,"runs":0.01,"arraytype":"Almost-Sorted-0.2","insertionSortExecutionTime":43,"shellSortExecutionTime":23,"heapSortExecutionTime":51,"mergeSortExecutionTime":30,"quickSortExecutionTime":15,"parallelMergeSortExecutionTime":12}
{"arraySize":500,"runs":0.01,"arraytype":"Almost-Sorted-0.2","insertionSortExecutionTime":41,"shellSortExecutionTime":21,"heapSortExecutionTime":49,"mergeSortExecutionTime":29,"quickSortExecutionTime":16,"parallelMergeSortExecutionTime":12}
{"arraySize":500,"runs":0.01,"arraytype":"Almost-Sorted-0.2","insertionSortExecutionTime":43,"shellSortExecutionTime":22,"heapSortExecutionTime":53,"mergeSortExecutionTime":31,"quickSortExecutionTime":16,"parallelMergeSortExecutionTime":12}
{"arraySize":500,"runs":0.012,"arraytype":"Almost-Sorted-0.2","insertionSortExecutionTime":45,"shellSortExecutionTime":23,"heapSortExecutionTime":50,"mergeSortExecutionTime":30,"quickSortExecutionTime":15,"parallelMergeSortExecutionTime":12}
{"arraySize":500,"runs":0.01,"arraytype":"Almost-Sorted-0.2","insertionSortExecutionTime":45,"shellSortExecutionTime":22,"heapSortExecutionTime":52,"mergeSortExecutionTime":30,"quickSortExecutionTime":14,"parallelMergeSortExecutionTime":12}
{"arraySize":500,"runs":0.012,"arraytype":"Almost-Sorted-0.2","insertionSortExecutionTime":47,"shellSortExecutionTime":23,"heapSortExecutionTime":52,"mergeSortExecutionTime":30,"quickSortExecutionTime":15,"parallelMergeSortExecutionTime":12}
{"arraySize":500,"runs":0.014,"arraytype":"Almost-Sorted-0.2","insertionSortExecutionTime":41,"shellSortExecutionTime":21,"heapSortExecutionTime":48,"mergeSortExecutionTime":27,"quickSortExecutionTime":13,"parallelMergeSortExecutionTime":11}
{"arraySize":500,"runs":0.01,"arraytype":"Almost-Sorted-0.2","insertionSortExecutionTime":44,"shellSortExecutionTime":21,"heapSortExecutionTime":52,"mergeSortExecutionTime":30,"quickSortExecutionTime":14,"parallelMergeSortExecutionTime":11}
{"arraySize":500,"runs":0.01,"arraytype":"Almost-Sorted-0.2","insertionSortExecutionTime":45,"shellSortExecutionTime":21,"heapSortExecutionTime":51,"mergeSortExecutionTime":29,"quickSortExecutionTime":13,"parallelMergeSortExecutionTime":12}
{"arraySize":500,"runs":0.01,"arraytype":"Almost-Sorted-0.2","insertionSortExecutionTime":42,"shellSortExecutionTime":21,"heapSortExecutionTime":49,"mergeSortExecutionTime":28,"quickSortExecutionTime":13,"parallelMergeSortExecutionTime":11}
{"arraySize":500,"runs":0.01,"arraytype":"Almost-Sorted-0.2","insertionSortExecutionTime":41,"shellSortExecutionTime":20,"heapSortExecutionTime":50,"mergeSortExecutionTime":29,"quickSortExecutionTime":14,"parallelMergeSortExecutionTime":12}
{"arraySize":500,"runs":0.012,"arraytype":"Almost-Sorted-0.2","insertionSortExecutionTime":41,"shellSortExecutionTime":22,"heapSortExecutionTime":50,"mergeSortExecutionTime":28,"quickSortExecutionTime":14,"parallelMergeSortExecutionTime":12}
{"arraySize":500,"runs":0.01,"arraytype":"Almost-Sorted-0.2","insertionSortExecutionTime":39,"shellSortExecutionTime":21,"heapSortExecutionTime":50,"mergeSortExecutionTime":30,"quickSortExecutionTime":14,"parallelMergeSortExecutionTime":11}
{"arraySize":500,"runs":0.012,"arraytype":"Almost-Sorted-0.2","insertionSortExecutionTime":39,"shellSortExecutionTime":20,"heapSortExecutionTime":50,"mergeSortExecutionTime":30,"quickSortExecutionTime":14,"parallelMergeSortExecutionTime":10}
{"arraySize":500,"runs":0.01,"arraytype":"Almost-Sorted-0.2","insertionSortExecutionTime":45,"shellSortExecutionTime":21,"heapSortExecutionTime":49,"mergeSortExecutionTime":27,"quickSortExecutionTime":13,"parallelMergeSortExecutionTime":11}
{"arraySize":500,"runs":0.012,"arraytype":"Almost-Sorted-0.2","insertionSortExecutionTime":42,"shellSortExecutionTime":21,"heapSortExecutionTime":50,"mergeSortExecutionTime":27,"quickSortExecutionTime":14,"parallelMergeSortExecutionTime":12}
{"arraySize":500,"runs":0.012,"arraytype":"Almost-Sorted-0.2","insertionSortExecutionTime":46,"shellSortExecutionTime":20,"heapSortExecutionTime":50,"mergeSortExecutionTime":20,"quickSortExecutionTime":11,"parallelMergeSortExecutionTime":8}
{"arraySize":500,"runs":0.012,"arraytype":"Almost-Sorted-0.2","insertionSortExecutionTime":42,"shellSortExecutionTime":20,"heapSortExecutionTime":50,"mergeSortExecutionTime":27,"quickSortExecutionTime":14,"parallelMergeSortExecutionTime":11}
{"arraySize":500,"runs":0.01,"arraytype":"Almost-Sorted-0.2","insertionSortExecutionTime":43,"shellSortExecutionTime":21,"heapSortExecutionTime":50,"mergeSortExecutionTime":28,"quickSortExecutionTime":13,"parallelMergeSortExecutionTime":11}
{"arraySize":500,"runs":0.012,"arraytype":"Almost-Sorted-0.2","insertionSortExecutionTime":41,"shellSortExecutionTime":20,"heapSortExecutionTime":49,"mergeSortExecutionTime":29,"quickSortExecutionTime":13,"parallelMergeSortExecutionTime":11}
{"arraySize":500,"runs":0.01,"arraytype":"Almost-Sorted-0.2","insertionSortExecutionTime":41,"shellSortExecutionTime":20,"heapSortExecutionTime":49,"mergeSortExecutionTime":27,"quickSortExecutionTime":13,"parallelMergeSortExecutionTime":11}
{"arraySize":500,"runs":0.012,"arraytype":"Almost-Sorted-0.2","insertionSortExecutionTime":46,"shellSortExecutionTime":20,"heapSortExecutionTime":49,"mergeSortExecutionTime":20,"quickSortExecutionTime":11,"parallelMergeSortExecutionTime":8}
{"arraySize":500,"runs":0.012,"arraytype":"Almost-Sorted-0.2","insertionSortExecutionTime":42,"shellSortExecutionTime":21,"heapSortExecutionTime":50,"mergeSortExecutionTime":28,"quickSortExecutionTime":13,"parallelMergeSortExecutionTime":12}
