{"arraySize":10000,"runs":1.0,"arraytype":"Reverse-Sorted","insertionSortExecutionTime":29045,"shellSortExecutionTime":148,"heapSortExecutionTime":862,"mergeSortExecutionTime":319,"quickSortExecutionTime":182,"parallelMergeSortExecutionTime":69}
{"arraySize":10000,"runs":1.0,"arraytype":"Reverse-Sorted","insertionSortExecutionTime":28007,"shellSortExecutionTime":227,"heapSortExecutionTime":1073,"mergeSortExecutionTime":371,"quickSortExecutionTime":122,"parallelMergeSortExecutionTime":54}
{"arraySize":10000,"runs":1.0,"arraytype":"Reverse-Sorted","insertionSortExecutionTime":28081,"shellSortExecutionTime":141,"heapSortExecutionTime":812,"mergeSortExecutionTime":307,"quickSortExecutionTime":101,"parallelMergeSortExecutionTime":72}
{"arraySize":10000,"runs":1.0,"arraytype":"Reverse-Sorted","insertionSortExecutionTime":28539,"shellSortExecutionTime":140,"heapSortExecutionTime":823,"mergeSortExecutionTime":298,"quickSortExecutionTime":97,"parallelMergeSortExecutionTime":87}
{"arraySize":10000,"runs":1.0,"arraytype":"Reverse-Sorted","insertionSortExecutionTime":31378,"shellSortExecutionTime":249,"heapSortExecutionTime":1241,"mergeSortExecutionTime":457,"quickSortExecutionTime":152,"parallelMergeSortExecutionTime":282}
{"arraySize":10000,"runs":1.0,"arraytype":"Reverse-Sorted","insertionSortExecutionTime":32011,"shellSortExecutionTime":142,"heapSortExecutionTime":947,"mergeSortExecutionTime":349,"quickSortExecutionTime":157,"parallelMergeSortExecutionTime":216}
{"arraySize":10000,"runs":1.0,"arraytype":"Reverse-Sorted","insertionSortExecutionTime":26887,"shellSortExecutionTime":146,"heapSortExecutionTime":770,"mergeSortExecutionTime":325,"quickSortExecutionTime":97,"parallelMergeSortExecutionTime":107}
{"arraySize":10000,"runs":1.0,"arraytype":"Reverse-Sorted","insertionSortExecutionTime":30350,"shellSortExecutionTime":218,"heapSortExecutionTime":851,"mergeSortExecutionTime":479,"quickSortExecutionTime":128,"parallelMergeSortExecutionTime":71}
{"arraySize":10000,"runs":1.0,"arraytype":"Reverse-Sorted","insertionSortExecutionTime":27321,"shellSortExecutionTime":141,"heapSortExecutionTime":817,"mergeSortExecutionTime":310,"quickSortExecutionTime":101,"parallelMergeSortExecutionTime":89}
{"arraySize":10000,"runs":1.0,"arraytype":"Reverse-Sorted","insertionSortExecutionTime":29820,"shellSortExecutionTime":137,"heapSortExecutionTime":785,"mergeSortExecutionTime":332,"quickSortExecutionTime":98,"parallelMergeSortExecutionTime":70}
{"arraySize":10000,"runs":1.0,"arraytype":"Reverse-Sorted","insertionSortExecutionTime":27556,"shellSortExecutionTime":141,"heapSortExecutionTime":887,"mergeSortExecutionTime":311,"quickSortExecutionTime":102,"parallelMergeSortExecutionTime":110}
{"arraySize":10000,"runs":1.0,"arraytype":"Reverse-Sorted","insertionSortExecutionTime":31033,"shellSortExecutionTime":137,"heapSortExecutionTime":810,"mergeSortExecutionTime":309,"quickSortExecutionTime":101,"parallelMergeSortExecutionTime":58}
{"arraySize":10000,"runs":1.0,"arraytype":"Reverse-Sorted","insertionSortExecutionTime":27141,"shellSortExecutionTime":187,"heapSortExecutionTime":1167,"mergeSortExecutionTime":532,"quickSortExecutionTime":188,"parallelMergeSortExecutionTime":74}
{"arraySize":10000,"runs":1.0,"arraytype":"Reverse-Sorted","insertionSortExecutionTime":33088,"shellSortExecutionTime":141,"heapSortExecutionTime":800,"mergeSortExecutionTime":309,"quickSortExecutionTime":101,"parallelMergeSortExecutionTime":50}
{"arraySize":10000,"runs":1.0,"arraytype":"Reverse-Sorted","insertionSortExecutionTime":27145,"shellSortExecutionTime":141,"heapSortExecutionTime":805,"mergeSortExecutionTime":305,"quickSortExecutionTime":102,"parallelMergeSortExecutionTime":100}
{"arraySize":10000,"runs":1.0,"arraytype":"Reverse-Sorted","insertionSortExecutionTime":29186,"shellSortExecutionTime":136,"heapSortExecutionTime":947,"mergeSortExecutionTime":499,"quickSortExecutionTime":108,"parallelMergeSortExecutionTime":79}
{"arraySize":10000,"runs":1.0,"arraytype":"Reverse-Sorted","insertionSortExecutionTime":31106,"shellSortExecutionTime":137,"heapSortExecutionTime":806,"mergeSortExecutionTime":299,"quickSortExecutionTime":98,"parallelMergeSortExecutionTime":73}
{"arraySize":10000,"runs":1.0,"arraytype":"Reverse-Sorted","insertionSortExecutionTime":27919,"shellSortExecutionTime":144,"heapSortExecutionTime":802,"mergeSortExecutionTime":316,"quickSortExecutionTime":101,"parallelMergeSortExecutionTime":95}
{"arraySize":10000,"runs":1.0,"arraytype":"Reverse-Sorted","insertionSortExecutionTime":32050,"shellSortExecutionTime":137,"heapSortExecutionTime":832,"mergeSortExecutionTime":336,"quickSortExecutionTime":100,"parallelMergeSortExecutionTime":111}
{"arraySize":10000,"runs":1.0,"arraytype":"Reverse-Sorted","insertionSortExecutionTime":28461,"shellSortExecutionTime":142,"heapSortExecutionTime":801,"mergeSortExecutionTime":335,"quickSortExecutionTime":100,"parallelMergeSortExecutionTime":94}
{"arraySize":10000,"runs":1.0,"arraytype":"Reverse-Sorted","insertionSortExecutionTime":30125,"shellSortExecutionTime":142,"heapSortExecutionTime":920,"mergeSortExecutionTime":340,"quickSortExecutionTime":102,"parallelMergeSortExecutionTime":84}
{"arraySize":10000,"runs":1.0,"arraytype":"Reverse-Sorted","insertionSortExecutionTime":27399,"shellSortExecutionTime":142,"heapSortExecutionTime":820,"mergeSortExecutionTime":310,"quickSortExecutionTime":101,"parallelMergeSortExecutionTime":62}
{"arraySize":10000,"runs":1.0,"arraytype":"Reverse-Sorted","insertionSortExecutionTime":28911,"shellSortExecutionTime":142,"heapSortExecutionTime":814,"mergeSortExecutionTime":308,"quickSortExecutionTime":100,"parallelMergeSortExecutionTime":82}
{"arraySize":10000,"runs":1.0,"arraytype":"Reverse-Sorted","insertionSortExecutionTime":28718,"shellSortExecutionTime":142,"heapSortExecutionTime":807,"mergeSortExecutionTime":320,"quickSortExecutionTime":112,"parallelMergeSortExecutionTime":99}
{"arraySize":10000,"runs":1.0,"arraytype":"Reverse-Sorted","insertionSortExecutionTime":28455,"shellSortExecutionTime":144,"heapSortExecutionTime":841,"mergeSortExecutionTime":358,"quickSortExecutionTime":101,"parallelMergeSortExecutionTime":83}
{"arraySize":10000,"runs":1.0,"arraytype":"Reverse-Sorted","insertionSortExecutionTime":28340,"shellSortExecutionTime":211,"heapSortExecutionTime":1226,"mergeSortExecutionTime":460,"quickSortExecutionTime":157,"parallelMergeSortExecutionTime":484}
{"arraySize":10000,"runs":1.0,"arraytype":"Reverse-Sorted","insertionSortExecutionTime":34710,"shellSortExecutionTime":142,"heapSortExecutionTime":809,"mergeSortExecutionTime":309,"quickSortExecutionTime":101,"parallelMergeSortExecutionTime":68}
{"arraySize":10000,"runs":1.0,"arraytype":"Reverse-Sorted","insertionSortExecutionTime":27961,"shellSortExecutionTime":147,"heapSortExecutionTime":812,"mergeSortExecutionTime":315,"quickSortExecutionTime":101,"parallelMergeSortExecutionTime":68}
{"arraySize":10000,"runs":1.0,"arraytype":"Reverse-Sorted","insertionSortExecutionTime":27061,"shellSortExecutionTime":287,"heapSortExecutionTime":815,"mergeSortExecutionTime":310,"quickSortExecutionTime":101,"parallelMergeSortExecutionTime":64}
{"arraySize":10000,"runs":1.0,"arraytype":"Reverse-Sorted","insertionSortExecutionTime":34500,"shellSortExecutionTime":166,"heapSortExecutionTime":793,"mergeSortExecutionTime":320,"quickSortExecutionTime":101,"parallelMergeSortExecutionTime":53}
{"arraySize":10000,"runs":1.0,"arraytype":"Reverse-Sorted","insertionSortExecutionTime":32048,"shellSortExecutionTime":153,"heapSortExecutionTime":823,"mergeSortExecutionTime":312,"quickSortExecutionTime":101,"parallelMergeSortExecutionTime":72}
{"arraySize":10000,"runs":1.0,"arraytype":"Reverse-Sorted","insertionSortExecutionTime":33550,"shellSortExecutionTime":142,"heapSortExecutionTime":986,"mergeSortExecutionTime":339,"quickSortExecutionTime":108,"parallelMergeSortExecutionTime":250}
{"arraySize":10000,"runs":1.0,"arraytype":"Reverse-Sorted","insertionSortExecutionTime":27010,"shellSortExecutionTime":142,"heapSortExecutionTime":990,"mergeSortExecutionTime":467,"quickSortExecutionTime":167,"parallelMergeSortExecutionTime":270}
{"arraySize":10000,"runs":1.0,"arraytype":"Reverse-Sorted","insertionSortExecutionTime":29208,"shellSortExecutionTime":222,"heapSortExecutionTime":813,"mergeSortExecutionTime":322,"quickSortExecutionTime":102,"parallelMergeSortExecutionTime":110}
{"arraySize":10000,"runs":1.0,"arraytype":"Reverse-Sorted","insertionSortExecutionTime":27524,"shellSortExecutionTime":142,"heapSortExecutionTime":1499,"mergeSortExecutionTime":431,"quickSortExecutionTime":158,"parallelMergeSortExecutionTime":161}
{"arraySize":10000,"runs":1.0,"arraytype":"Reverse-Sorted","insertionSortExecutionTime":28728,"shellSortExecutionTime":142,"heapSortExecutionTime":871,"mergeSortExecutionTime":404,"quickSortExecutionTime":110,"parallelMergeSortExecutionTime":240}
{"arraySize":10000,"runs":1.0,"arraytype":"Reverse-Sorted","insertionSortExecutionTime":28382,"shellSortExecutionTime":142,"heapSortExecutionTime":807,"mergeSortExecutionTime":690,"quickSortExecutionTime":101,"parallelMergeSortExecutionTime":60}
{"arraySize":10000,"runs":1.0,"arraytype":"Reverse-Sorted","insertionSortExecutionTime":27597,"shellSortExecutionTime":160,"heapSortExecutionTime":1322,"mergeSortExecutionTime":451,"quickSortExecutionTime":232,"parallelMergeSortExecutionTime":102}
{"arraySize":10000,"runs":1.0,"arraytype":"Reverse-Sorted","insertionSortExecutionTime":27418,"shellSortExecutionTime":142,"heapSortExecutionTime":1077,"mergeSortExecutionTime":560,"quickSortExecutionTime":149,"parallelMergeSortExecutionTime":97}
{"arraySize":10000,"runs":1.0,"arraytype":"Reverse-Sorted","insertionSortExecutionTime":32068,"shellSortExecutionTime":211,"heapSortExecutionTime":1110,"mergeSortExecutionTime":527,"quickSortExecutionTime":188,"parallelMergeSortExecutionTime":138}
{"arraySize":10000,"runs":1.0,"arraytype":"Reverse-Sorted","insertionSortExecutionTime":35962,"shellSortExecutionTime":141,"heapSortExecutionTime":805,"mergeSortExecutionTime":308,"quickSortExecutionTime":100,"parallelMergeSortExecutionTime":71}
{"arraySize":10000,"runs":1.0,"arraytype":"Reverse-Sorted","insertionSortExecutionTime":27187,"shellSortExecutionTime":142,"heapSortExecutionTime":833,"mergeSortExecutionTime":312,"quickSortExecutionTime":102,"parallelMergeSortExecutionTime":74}
{"arraySize":10000,"runs":1.0,"arraytype":"Reverse-Sorted","insertionSortExecutionTime":28226,"shellSortExecutionTime":200,"heapSortExecutionTime":961,"mergeSortExecutionTime":356,"quickSortExecutionTime":101,"parallelMergeSortExecutionTime":61}
{"arraySize":10000,"runs":1.0,"arraytype":"Reverse-Sorted","insertionSortExecutionTime":28236,"shellSortExecutionTime":169,"heapSortExecutionTime":939,"mergeSortExecutionTime":439,"quickSortExecutionTime":131,"parallelMergeSortExecutionTime":250}
{"arraySize":10000,"runs":1.0,"arraytype":"Reverse-Sorted","insertionSortExecutionTime":28676,"shellSortExecutionTime":223,"heapSortExecutionTime":1356,"mergeSortExecutionTime":603,"quickSortExecutionTime":236,"parallelMergeSortExecutionTime":259}
{"arraySize":10000,"runs":1.0,"arraytype":"Reverse-Sorted","insertionSortExecutionTime":29984,"shellSortExecutionTime":219,"heapSortExecutionTime":930,"mergeSortExecutionTime":308,"quickSortExecutionTime":101,"parallelMergeSortExecutionTime":67}
{"arraySize":10000,"runs":1.0,"arraytype":"Reverse-Sorted","insertionSortExecutionTime":28278,"shellSortExecutionTime":185,"heapSortExecutionTime":869,"mergeSortExecutionTime":449,"quickSortExecutionTime":211,"parallelMergeSortExecutionTime":112}
{"arraySize":10000,"runs":1.0,"arraytype":"Reverse-Sorted","insertionSortExecutionTime":34580,"shellSortExecutionTime":146,"heapSortExecutionTime":814,"mergeSortExecutionTime":317,"quickSortExecutionTime":105,"parallelMergeSortExecutionTime":116}
{"arraySize":10000,"runs":1.0,"arraytype":"Reverse-Sorted","insertionSortExecutionTime":32173,"shellSortExecutionTime":140,"heapSortExecutionTime":805,"mergeSortExecutionTime":308,"quickSortExecutionTime":101,"parallelMergeSortExecutionTime":79}
{"arraySize":10000,"runs":1.0,"arraytype":"Reverse-Sorted","insertionSortExecutionTime":36292,"shellSortExecutionTime":235,"heapSortExecutionTime":1213,"mergeSortExecutionTime":322,"quickSortExecutionTime":253,"parallelMergeSortExecutionTime":395}
{"arraySize":10000,"runs":1.0,"arraytype":"Reverse-Sorted","insertionSortExecutionTime":30121,"shellSortExecutionTime":176,"heapSortExecutionTime":877,"mergeSortExecutionTime":511,"quickSortExecutionTime":111,"parallelMergeSortExecutionTime":75}
{"arraySize":10000,"runs":1.0,"arraytype":"Reverse-Sorted","insertionSortExecutionTime":29039,"shellSortExecutionTime":241,"heapSortExecutionTime":1118,"mergeSortExecutionTime":445,"quickSortExecutionTime":102,"parallelMergeSortExecutionTime":61}
{"arraySize":10000,"runs":1.0,"arraytype":"Reverse-Sorted","insertionSortExecutionTime":31058,"shellSortExecutionTime":148,"heapSortExecutionTime":814,"mergeSortExecutionTime":342,"quickSortExecutionTime":105,"parallelMergeSortExecutionTime":68}
{"arraySize":10000,"runs":1.0,"arraytype":"Reverse-Sorted","insertionSortExecutionTime":28429,"shellSortExecutionTime":195,"heapSortExecutionTime":950,"mergeSortExecutionTime":483,"quickSortExecutionTime":165,"parallelMergeSortExecutionTime":180}
{"arraySize":10000,"runs":1.0,"arraytype":"Reverse-Sorted","insertionSortExecutionTime":27281,"shellSortExecutionTime":141,"heapSortExecutionTime":812,"mergeSortExecutionTime":309,"quickSortExecutionTime":197,"parallelMergeSortExecutionTime":88}
{"arraySize":10000,"runs":1.0,"arraytype":"Reverse-Sorted","insertionSortExecutionTime":28993,"shellSortExecutionTime":142,"heapSortExecutionTime":918,"mergeSortExecutionTime":323,"quickSortExecutionTime":101,"parallelMergeSortExecutionTime":71}
{"arraySize":10000,"runs":1.0,"arraytype":"Reverse-Sorted","insertionSortExecutionTime":27261,"shellSortExecutionTime":247,"heapSortExecutionTime":830,"mergeSortExecutionTime":432,"quickSortExecutionTime":101,"parallelMergeSortExecutionTime":123}
{"arraySize":10000,"runs":1.0,"arraytype":"Reverse-Sorted","insertionSortExecutionTime":27252,"shellSortExecutionTime":255,"heapSortExecutionTime":1102,"mergeSortExecutionTime":314,"quickSortExecutionTime":100,"parallelMergeSortExecutionTime":52}
{"arraySize":10000,"runs":1.0,"arraytype":"Reverse-Sorted","insertionSortExecutionTime":28244,"shellSortExecutionTime":140,"heapSortExecutionTime":806,"mergeSortExecutionTime":424,"quickSortExecutionTime":159,"parallelMergeSortExecutionTime":91}
{"arraySize":10000,"runs":1.0,"arraytype":"Reverse-Sorted","insertionSortExecutionTime":27551,"shellSortExecutionTime":142,"heapSortExecutionTime":801,"mergeSortExecutionTime":309,"quickSortExecutionTime":121,"parallelMergeSortExecutionTime":58}
{"arraySize":10000,"runs":1.0,"arraytype":"Reverse-Sorted","insertionSortExecutionTime":30024,"shellSortExecutionTime":137,"heapSortExecutionTime":816,"mergeSortExecutionTime":316,"quickSortExecutionTime":109,"parallelMergeSortExecutionTime":70}
{"arraySize":10000,"runs":1.0,"arraytype":"Reverse-Sorted","insertionSortExecutionTime":29279,"shellSortExecutionTime":141,"heapSortExecutionTime":814,"mergeSortExecutionTime":309,"quickSortExecutionTime":101,"parallelMergeSortExecutionTime":63}
{"arraySize":10000,"runs":1.0,"arraytype":"Reverse-Sorted","insertionSortExecutionTime":27091,"shellSortExecutionTime":136,"heapSortExecutionTime":800,"mergeSortExecutionTime":318,"quickSortExecutionTime":98,"parallelMergeSortExecutionTime":88}
{"arraySize":10000,"runs":1.0,"arraytype":"Reverse-Sorted","insertionSortExecutionTime":28048,"shellSortExecutionTime":137,"heapSortExecutionTime":796,"mergeSortExecutionTime":299,"quickSortExecutionTime":98,"parallelMergeSortExecutionTime":72}
{"arraySize":10000,"runs":1.0,"arraytype":"Reverse-Sorted","insertionSortExecutionTime":31196,"shellSortExecutionTime":268,"heapSortExecutionTime":1238,"mergeSortExecutionTime":576,"quickSortExecutionTime":172,"parallelMergeSortExecutionTime":80}
{"arraySize":10000,"runs":1.0,"arraytype":"Reverse-Sorted","insertionSortExecutionTime":27381,"shellSortExecutionTime":142,"heapSortExecutionTime":807,"mergeSortExecutionTime":387,"quickSortExecutionTime":100,"parallelMergeSortExecutionTime":67}
{"arraySize":10000,"runs":1.0,"arraytype":"Reverse-Sorted","insertionSortExecutionTime":27117,"shellSortExecutionTime":163,"heapSortExecutionTime":816,"mergeSortExecutionTime":370,"quickSortExecutionTime":153,"parallelMergeSortExecutionTime":309}
{"arraySize":10000,"runs":1.0,"arraytype":"Reverse-Sorted","insertionSortExecutionTime":29416,"shellSortExecutionTime":192,"heapSortExecutionTime":872,"mergeSortExecutionTime":330,"quickSortExecutionTime":110,"parallelMergeSortExecutionTime":240}
{"arraySize":10000,"runs":1.0,"arraytype":"Reverse-Sorted","insertionSortExecutionTime":27320,"shellSortExecutionTime":193,"heapSortExecutionTime":986,"mergeSortExecutionTime":376,"quickSortExecutionTime":110,"parallelMergeSortExecutionTime":65}
{"arraySize":10000,"runs":1.0,"arraytype":"Reverse-Sorted","insertionSortExecutionTime":27926,"shellSortExecutionTime":284,"heapSortExecutionTime":1166,"mergeSortExecutionTime":344,"quickSortExecutionTime":117,"parallelMergeSortExecutionTime":82}
{"arraySize":10000,"runs":1.0,"arraytype":"Reverse-Sorted","insertionSortExecutionTime":27823,"shellSortExecutionTime":183,"heapSortExecutionTime":1122,"mergeSortExecutionTime":436,"quickSortExecutionTime":195,"parallelMergeSortExecutionTime":97}
{"arraySize":10000,"runs":1.0,"arraytype":"Reverse-Sorted","insertionSortExecutionTime":26481,"shellSortExecutionTime":251,"heapSortExecutionTime":1119,"mergeSortExecutionTime":573,"quickSortExecutionTime":148,"parallelMergeSortExecutionTime":86}
{"arraySize":10000,"runs":1.0,"arraytype":"Reverse-Sorted","insertionSortExecutionTime":26890,"shellSortExecutionTime":151,"heapSortExecutionTime":787,"mergeSortExecutionTime":330,"quickSortExecutionTime":98,"parallelMergeSortExecutionTime":126}
{"arraySize":10000,"runs":1.0,"arraytype":"Reverse-Sorted","insertionSortExecutionTime":29554,"shellSortExecutionTime":142,"heapSortExecutionTime":802,"mergeSortExecutionTime":309,"quickSortExecutionTime":101,"parallelMergeSortExecutionTime":548}
{"arraySize":10000,"runs":1.0,"arraytype":"Reverse-Sorted","insertionSortExecutionTime":27862,"shellSortExecutionTime":137,"heapSortExecutionTime":825,"mergeSortExecutionTime":298,"quickSortExecutionTime":111,"parallelMergeSortExecutionTime":135}
{"arraySize":10000,"runs":1.0,"arraytype":"Reverse-Sorted","insertionSortExecutionTime":27473,"shellSortExecutionTime":137,"heapSortExecutionTime":793,"mergeSortExecutionTime":317,"quickSortExecutionTime":97,"parallelMergeSortExecutionTime":104}
{"arraySize":10000,"runs":1.0,"arraytype":"Reverse-Sorted","insertionSortExecutionTime":28416,"shellSortExecutionTime":141,"heapSortExecutionTime":829,"mergeSortExecutionTime":327,"quickSortExecutionTime":98,"parallelMergeSortExecutionTime":118}
{"arraySize":10000,"runs":1.0,"arraytype":"Reverse-Sorted","insertionSortExecutionTime":29051,"shellSortExecutionTime":144,"heapSortExecutionTime":821,"mergeSortExecutionTime":372,"quickSortExecutionTime":111,"parallelMergeSortExecutionTime":98}
{"arraySize":10000,"runs":1.0,"arraytype":"Reverse-Sorted","insertionSortExecutionTime":27785,"shellSortExecutionTime":201,"heapSortExecutionTime":892,"mergeSortExecutionTime":370,"quickSortExecutionTime":107,"parallelMergeSortExecutionTime":156}
{"arraySize":10000,"runs":1.0,"arraytype":"Reverse-Sorted","insertionSortExecutionTime":27177,"shellSortExecutionTime":195,"heapSortExecutionTime":1082,"mergeSortExecutionTime":925,"quickSortExecutionTime":216,"parallelMergeSortExecutionTime":418}
{"arraySize":10000,"runs":1.0,"arraytype":"Reverse-Sorted","insertionSortExecutionTime":29393,"shellSortExecutionTime":231,"heapSortExecutionTime":973,"mergeSortExecutionTime":353,"quickSortExecutionTime":101,"parallelMergeSortExecutionTime":91}
{"arraySize":10000,"runs":1.0,"arraytype":"Reverse-Sorted","insertionSortExecutionTime":28168,"shellSortExecutionTime":161,"heapSortExecutionTime":987,"mergeSortExecutionTime":373,"quickSortExecutionTime":275,"parallelMergeSortExecutionTime":302}
{"arraySize":10000,"runs":1.0,"arraytype":"Reverse-Sorted","insertionSortExecutionTime":28062,"shellSortExecutionTime":142,"heapSortExecutionTime":993,"mergeSortExecutionTime":359,"quickSortExecutionTime":105,"parallelMergeSortExecutionTime":255}
{"arraySize":10000,"runs":1.0,"arraytype":"Reverse-Sorted","insertionSortExecutionTime":28037,"shellSortExecutionTime":143,"heapSortExecutionTime":988,"mergeSortExecutionTime":422,"quickSortExecutionTime":167,"parallelMergeSortExecutionTime":302}
{"arraySize":10000,"runs":1.0,"arraytype":"Reverse-Sorted","insertionSortExecutionTime":28290,"shellSortExecutionTime":233,"heapSortExecutionTime":879,"mergeSortExecutionTime":511,"quickSortExecutionTime":147,"parallelMergeSortExecutionTime":560}
{"arraySize":10000,"runs":1.0,"arraytype":"Reverse-Sorted","insertionSortExecutionTime":28049,"shellSortExecutionTime":145,"heapSortExecutionTime":1051,"mergeSortExecutionTime":466,"quickSortExecutionTime":107,"parallelMergeSortExecutionTime":75}
{"arraySize":10000,"runs":1.0,"arraytype":"Reverse-Sorted","insertionSortExecutionTime":36527,"shellSortExecutionTime":143,"heapSortExecutionTime":801,"mergeSortExecutionTime":310,"quickSortExecutionTime":101,"parallelMergeSortExecutionTime":94}
{"arraySize":10000,"runs":1.0,"arraytype":"Reverse-Sorted","insertionSortExecutionTime":37873,"shellSortExecutionTime":284,"heapSortExecutionTime":1234,"mergeSortExecutionTime":667,"quickSortExecutionTime":222,"parallelMergeSortExecutionTime":264}
{"arraySize":10000,"runs":1.0,"arraytype":"Reverse-Sorted","insertionSortExecutionTime":34982,"shellSortExecutionTime":181,"heapSortExecutionTime":1044,"mergeSortExecutionTime":415,"quickSortExecutionTime":107,"parallelMergeSortExecutionTime":326}
{"arraySize":10000,"runs":1.0,"arraytype":"Reverse-Sorted","insertionSortExecutionTime":32188,"shellSortExecutionTime":236,"heapSortExecutionTime":1126,"mergeSortExecutionTime":518,"quickSortExecutionTime":183,"parallelMergeSortExecutionTime":85}
{"arraySize":10000,"runs":1.0,"arraytype":"Reverse-Sorted","insertionSortExecutionTime":33575,"shellSortExecutionTime":244,"heapSortExecutionTime":1035,"mergeSortExecutionTime":512,"quickSortExecutionTime":181,"parallelMergeSortExecutionTime":99}
{"arraySize":10000,"runs":1.0,"arraytype":"Reverse-Sorted","insertionSortExecutionTime":33911,"shellSortExecutionTime":142,"heapSortExecutionTime":798,"mergeSortExecutionTime":310,"quickSortExecutionTime":101,"parallelMergeSortExecutionTime":84}
{"arraySize":10000,"runs":1.0,"arraytype":"Reverse-Sorted","insertionSortExecutionTime":28739,"shellSortExecutionTime":142,"heapSortExecutionTime":800,"mergeSortExecutionTime":346,"quickSortExecutionTime":101,"parallelMergeSortExecutionTime":73}
{"arraySize":10000,"runs":1.0,"arraytype":"Reverse-Sorted","insertionSortExecutionTime":31379,"shellSortExecutionTime":141,"heapSortExecutionTime":803,"mergeSortExecutionTime":312,"quickSortExecutionTime":100,"parallelMergeSortExecutionTime":57}
{"arraySize":10000,"runs":1.0,"arraytype":"Reverse-Sorted","insertionSortExecutionTime":34633,"shellSortExecutionTime":222,"heapSortExecutionTime":890,"mergeSortExecutionTime":309,"quickSortExecutionTime":109,"parallelMergeSortExecutionTime":80}
{"arraySize":10000,"runs":1.0,"arraytype":"Reverse-Sorted","insertionSortExecutionTime":32772,"shellSortExecutionTime":245,"heapSortExecutionTime":1228,"mergeSortExecutionTime":516,"quickSortExecutionTime":176,"parallelMergeSortExecutionTime":333}
{"arraySize":10000,"runs":1.0,"arraytype":"Reverse-Sorted","insertionSortExecutionTime":31766,"shellSortExecutionTime":142,"heapSortExecutionTime":805,"mergeSortExecutionTime":316,"quickSortExecutionTime":101,"parallelMergeSortExecutionTime":67}
{"arraySize":10000,"runs":1.0,"arraytype":"Reverse-Sorted","insertionSortExecutionTime":36260,"shellSortExecutionTime":238,"heapSortExecutionTime":851,"mergeSortExecutionTime":786,"quickSortExecutionTime":100,"parallelMergeSortExecutionTime":55}
{"arraySize":10000,"runs":1.0,"arraytype":"Reverse-Sorted","insertionSortExecutionTime":33597,"shellSortExecutionTime":142,"heapSortExecutionTime":804,"mergeSortExecutionTime":315,"quickSortExecutionTime":101,"parallelMergeSortExecutionTime":73}
{"arraySize":10000,"runs":1.0,"arraytype":"Reverse-Sorted","insertionSortExecutionTime":36070,"shellSortExecutionTime":258,"heapSortExecutionTime":1139,"mergeSortExecutionTime":310,"quickSortExecutionTime":101,"parallelMergeSortExecutionTime":69}
