{"arraySize":1000,"runs":0.013,"arraytype":"Almost-Sorted-0.33","adaptiveSortExecutionTime":7,"insertionSortExecutionTime":92,"shellSortExecutionTime":29,"heapSortExecutionTime":69,"mergeSortExecutionTime":32,"quickSortExecutionTime":12,"parallelMergeSortExecutionTime":11,"parallelQuickSortExecutionTime":9}
{"arraySize":1000,"runs":0.007,"arraytype":"Almost-Sorted-0.33","adaptiveSortExecutionTime":7,"insertionSortExecutionTime":88,"shellSortExecutionTime":28,"heapSortExecutionTime":70,"mergeSortExecutionTime":31,"quickSortExecutionTime":12,"parallelMergeSortExecutionTime":10,"parallelQuickSortExecutionTime":8}
{"arraySize":1000,"runs":0.006,"arraytype":"Almost-Sorted-0.33","adaptiveSortExecutionTime":7,"insertionSortExecutionTime":87,"shellSortExecutionTime":29,"heapSortExecutionTime":86,"mergeSortExecutionTime":30,"quickSortExecutionTime":11,"parallelMergeSortExecutionTime":10,"parallelQuickSortExecutionTime":8}
{"arraySize":1000,"runs":0.009,"arraytype":"Almost-Sorted-0.33","adaptiveSortExecutionTime":7,"insertionSortExecutionTime":86,"shellSortExecutionTime":26,"heapSortExecutionTime":67,"mergeSortExecutionTime":31,"quickSortExecutionTime":11,"parallelMergeSortExecutionTime":10,"parallelQuickSortExecutionTime":9}
{"arraySize":1000,"runs":0.007,"arraytype":"Almost-Sorted-0.33","adaptiveSortExecutionTime":13,"insertionSortExecutionTime":162,"shellSortExecutionTime":59,"heapSortExecutionTime":97,"mergeSortExecutionTime":49,"quickSortExecutionTime":17,"parallelMergeSortExecutionTime":16,"parallelQuickSortExecutionTime":15}
{"arraySize":1000,"runs":0.008,"arraytype":"Almost-Sorted-0.33","adaptiveSortExecutionTime":14,"insertionSortExecutionTime":157,"shellSortExecutionTime":41,"heapSortExecutionTime":101,"mergeSortExecutionTime":52,"quickSortExecutionTime":16,"parallelMergeSortExecutionTime":16,"parallelQuickSortExecutionTime":15}
{"arraySize":1000,"runs":0.008,"arraytype":"Almost-Sorted-0.33","adaptiveSortExecutionTime":7,"insertionSortExecutionTime":89,"shellSortExecutionTime":30,"heapSortExecutionTime":69,"mergeSortExecutionTime":32,"quickSortExecutionTime":11,"parallelMergeSortExecutionTime":10,"parallelQuickSortExecutionTime":8}
{"arraySize":1000,"runs":0.013,"arraytype":"Almost-Sorted-0.33","adaptiveSortExecutionTime":8,"insertionSortExecutionTime":90,"shellSortExecutionTime":40,"heapSortExecutionTime":66,"mergeSortExecutionTime":31,"quickSortExecutionTime":12,"parallelMergeSortExecutionTime":11,"parallelQuickSortExecutionTime":9}
{"arraySize":1000,"runs":0.009,"arraytype":"Almost-Sorted-0.33","adaptiveSortExecutionTime":7,"insertionSortExecutionTime":84,"shellSortExecutionTime":27,"heapSortExecutionTime":67,"mergeSortExecutionTime":30,"quickSortExecutionTime":11,"parallelMergeSortExecutionTime":10,"parallelQuickSortExecutionTime":8}
{"arraySize":1000,"runs":0.009,"arraytype":"Almost-Sorted-0.33","adaptiveSortExecutionTime":7,"insertionSortExecutionTime":86,"shellSortExecutionTime":27,"heapSortExecutionTime":67,"mergeSortExecutionTime":29,"quickSortExecutionTime":11,"parallelMergeSortExecutionTime":11,"parallelQuickSortExecutionTime":9}
{"arraySize":1000,"runs":0.008,"arraytype":"Almost-Sorted-0.33","adaptiveSortExecutionTime":7,"insertionSortExecutionTime":118,"shellSortExecutionTime":28,"heapSortExecutionTime":106,"mergeSortExecutionTime":31,"quickSortExecutionTime":25,"parallelMergeSortExecutionTime":10,"parallelQuickSortExecutionTime":8}
{"arraySize":1000,"runs":0.012,"arraytype":"Almost-Sorted-0.33","adaptiveSortExecutionTime":7,"insertionSortExecutionTime":126,"shellSortExecutionTime":28,"heapSortExecutionTime":81,"mergeSortExecutionTime":30,"quickSortExecutionTime":11,"parallelMergeSortExecutionTime":10,"parallelQuickSortExecutionTime":8}
{"arraySize":1000,"runs":0.01,"arraytype":"Almost-Sorted-0.33","adaptiveSortExecutionTime":7,"insertionSortExecutionTime":88,"shellSortExecutionTime":28,"heapSortExecutionTime":67,"mergeSortExecutionTime":30,"quickSortExecutionTime":11,"parallelMergeSortExecutionTime":10,"parallelQuickSortExecutionTime":8}
{"arraySize":1000,"runs":0.011,"arraytype":"Almost-Sorted-0.33","adaptiveSortExecutionTime":7,"insertionSortExecutionTime":86,"shellSortExecutionTime":27,"heapSortExecutionTime":67,"mergeSortExecutionTime":30,"quickSortExecutionTime":11,"parallelMergeSortExecutionTime":10,"parallelQuickSortExecutionTime":8}
{"arraySize":1000,"runs":0.012,"arraytype":"Almost-Sorted-0.33","adaptiveSortExecutionTime":8,"insertionSortExecutionTime":176,"shellSortExecutionTime":28,"heapSortExecutionTime":70,"mergeSortExecutionTime":31,"quickSortExecutionTime":11,"parallelMergeSortExecutionTime":10,"parallelQuickSortExecutionTime":9}
{"arraySize":1000,"runs":0.01,"arraytype":"Almost-Sorted-0.33","adaptiveSortExecutionTime":7,"insertionSortExecutionTime":105,"shellSortExecutionTime":26,"heapSortExecutionTime":67,"mergeSortExecutionTime":30,"quickSortExecutionTime":11,"parallelMergeSortExecutionTime":10,"parallelQuickSortExecutionTime":8}
{"arraySize":1000,"runs":0.008,"arraytype":"Almost-Sorted-0.33","adaptiveSortExecutionTime":7,"insertionSortExecutionTime":95,"shellSortExecutionTime":29,"heapSortExecutionTime":70,"mergeSortExecutionTime":32,"quickSortExecutionTime":11,"parallelMergeSortExecutionTime":10,"parallelQuickSortExecutionTime":8}
{"arraySize":1000,"runs":0.009,"arraytype":"Almost-Sorted-0.33","adaptiveSortExecutionTime":7,"insertionSortExecutionTime":93,"shellSortExecutionTime":66,"heapSortExecutionTime":67,"mergeSortExecutionTime":30,"quickSortExecutionTime":11,"parallelMergeSortExecutionTime":10,"parallelQuickSortExecutionTime":8}
{"arraySize":1000,"runs":0.012,"arraytype":"Almost-Sorted-0.33","adaptiveSortExecutionTime":7,"insertionSortExecutionTime":104,"shellSortExecutionTime":28,"heapSortExecutionTime":67,"mergeSortExecutionTime":30,"quickSortExecutionTime":11,"parallelMergeSortExecutionTime":9,"parallelQuickSortExecutionTime":8}
{"arraySize":1000,"runs":0.008,"arraytype":"Almost-Sorted-0.33","adaptiveSortExecutionTime":7,"insertionSortExecutionTime":84,"shellSortExecutionTime":27,"heapSortExecutionTime":67,"mergeSortExecutionTime":29,"quickSortExecutionTime":11,"parallelMergeSortExecutionTime":10,"parallelQuickSortExecutionTime":9}
{"arraySize":1000,"runs":0.011,"arraytype":"Almost-Sorted-0.33","adaptiveSortExecutionTime":25,"insertionSortExecutionTime":91,"shellSortExecutionTime":28,"heapSortExecutionTime":67,"mergeSortExecutionTime":30,"quickSortExecutionTime":12,"parallelMergeSortExecutionTime":10,"parallelQuickSortExecutionTime":29}
{"arraySize":1000,"runs":0.011,"arraytype":"Almost-Sorted-0.33","adaptiveSortExecutionTime":7,"insertionSortExecutionTime":90,"shellSortExecutionTime":27,"heapSortExecutionTime":105,"mergeSortExecutionTime":30,"quickSortExecutionTime":11,"parallelMergeSortExecutionTime":10,"parallelQuickSortExecutionTime":8}
{"arraySize":1000,"runs":0.005,"arraytype":"Almost-Sorted-0.33","adaptiveSortExecutionTime":7,"insertionSortExecutionTime":126,"shellSortExecutionTime":28,"heapSortExecutionTime":67,"mergeSortExecutionTime":30,"quickSortExecutionTime":11,"parallelMergeSortExecutionTime":10,"parallelQuickSortExecutionTime":8}
{"arraySize":1000,"runs":0.006,"arraytype":"Almost-Sorted-0.33","adaptiveSortExecutionTime":7,"insertionSortExecutionTime":87,"shellSortExecutionTime":26,"heapSortExecutionTime":68,"mergeSortExecutionTime":30,"quickSortExecutionTime":11,"parallelMergeSortExecutionTime":10,"parallelQuickSortExecutionTime":9}
{"arraySize":1000,"runs":0.005,"arraytype":"Almost-Sorted-0.33","adaptiveSortExecutionTime":7,"insertionSortExecutionTime":82,"shellSortExecutionTime":27,"heapSortExecutionTime":68,"mergeSortExecutionTime":30,"quickSortExecutionTime":11,"parallelMergeSortExecutionTime":10,"parallelQuickSortExecutionTime":8}
{"arraySize":1000,"runs":0.011,"arraytype":"Almost-Sorted-0.33","adaptiveSortExecutionTime":7,"insertionSortExecutionTime":89,"shellSortExecutionTime":26,"heapSortExecutionTime":86,"mergeSortExecutionTime":48,"quickSortExecutionTime":30,"parallelMergeSortExecutionTime":10,"parallelQuickSortExecutionTime":8}
{"arraySize":1000,"runs":0.01,"arraytype":"Almost-Sorted-0.33","adaptiveSortExecutionTime":7,"insertionSortExecutionTime":103,"shellSortExecutionTime":41,"heapSortExecutionTime":67,"mergeSortExecutionTime":30,"quickSortExecutionTime":11,"parallelMergeSortExecutionTime":10,"parallelQuickSortExecutionTime":9}
{"arraySize":1000,"runs":0.007,"arraytype":"Almost-Sorted-0.33","adaptiveSortExecutionTime":7,"insertionSortExecutionTime":87,"shellSortExecutionTime":27,"heapSortExecutionTime":67,"mergeSortExecutionTime":30,"quickSortExecutionTime":11,"parallelMergeSortExecutionTime":10,"parallelQuickSortExecutionTime":8}
{"arraySize":1000,"runs":0.009,"arraytype":"Almost-Sorted-0.33","adaptiveSortExecutionTime":7,"insertionSortExecutionTime":87,"shellSortExecutionTime":29,"heapSortExecutionTime":67,"mergeSortExecutionTime":30,"quickSortExecutionTime":32,"parallelMergeSortExecutionTime":11,"parallelQuickSortExecutionTime":9}
{"arraySize":1000,"runs":0.009,"arraytype":"Almost-Sorted-0.33","adaptiveSortExecutionTime":7,"insertionSortExecutionTime":94,"shellSortExecutionTime":37,"heapSortExecutionTime":70,"mergeSortExecutionTime":62,"quickSortExecutionTime":11,"parallelMergeSortExecutionTime":10,"parallelQuickSortExecutionTime":9}
{"arraySize":1000,"runs":0.01,"arraytype":"Almost-Sorted-0.33","adaptiveSortExecutionTime":7,"insertionSortExecutionTime":84,"shellSortExecutionTime":28,"heapSortExecutionTime":67,"mergeSortExecutionTime":30,"quickSortExecutionTime":11,"parallelMergeSortExecutionTime":10,"parallelQuickSortExecutionTime":8}
{"arraySize":1000,"runs":0.004,"arraytype":"Almost-Sorted-0.33","adaptiveSortExecutionTime":7,"insertionSortExecutionTime":90,"shellSortExecutionTime":28,"heapSortExecutionTime":67,"mergeSortExecutionTime":30,"quickSortExecutionTime":11,"parallelMergeSortExecutionTime":10,"parallelQuickSortExecutionTime":9}
{"arraySize":1000,"runs":0.009,"arraytype":"Almost-Sorted-0.33","adaptiveSortExecutionTime":7,"insertionSortExecutionTime":98,"shellSortExecutionTime":29,"heapSortExecutionTime":71,"mergeSortExecutionTime":31,"quickSortExecutionTime":12,"parallelMergeSortExecutionTime":11,"parallelQuickSortExecutionTime":10}
{"arraySize":1000,"runs":0.009,"arraytype":"Almost-Sorted-0.33","adaptiveSortExecutionTime":8,"insertionSortExecutionTime":86,"shellSortExecutionTime":28,"heapSortExecutionTime":67,"mergeSortExecutionTime":30,"quickSortExecutionTime":11,"parallelMergeSortExecutionTime":9,"parallelQuickSortExecutionTime":9}
{"arraySize":1000,"runs":0.011,"arraytype":"Almost-Sorted-0.33","adaptiveSortExecutionTime":7,"insertionSortExecutionTime":87,"shellSortExecutionTime":28,"heapSortExecutionTime":67,"mergeSortExecutionTime":30,"quickSortExecutionTime":11,"parallelMergeSortExecutionTime":10,"parallelQuickSortExecutionTime":8}
{"arraySize":1000,"runs":0.014,"arraytype":"Almost-Sorted-0.33","adaptiveSortExecutionTime":7,"insertionSortExecutionTime":106,"shellSortExecutionTime":43,"heapSortExecutionTime":70,"mergeSortExecutionTime":31,"quickSortExecutionTime":11,"parallelMergeSortExecutionTime":10,"parallelQuickSortExecutionTime":8}
{"arraySize":1000,"runs":0.008,"arraytype":"Almost-Sorted-0.33","adaptiveSortExecutionTime":8,"insertionSortExecutionTime":107,"shellSortExecutionTime":30,"heapSortExecutionTime":70,"mergeSortExecutionTime":32,"quickSortExecutionTime":12,"parallelMergeSortExecutionTime":11,"parallelQuickSortExecutionTime":9}
{"arraySize":1000,"runs":0.01,"arraytype":"Almost-Sorted-0.33","adaptiveSortExecutionTime":7,"insertionSortExecutionTime":92,"shellSortExecutionTime":29,"heapSortExecutionTime":70,"mergeSortExecutionTime":31,"quickSortExecutionTime":12,"parallelMergeSortExecutionTime":11,"parallelQuickSortExecutionTime":9}
{"arraySize":1000,"runs":0.01,"arraytype":"Almost-Sorted-0.33","adaptiveSortExecutionTime":8,"insertionSortExecutionTime":89,"shellSortExecutionTime":27,"heapSortExecutionTime":69,"mergeSortExecutionTime":31,"quickSortExecutionTime":11,"parallelMergeSortExecutionTime":11,"parallelQuickSortExecutionTime":9}
{"arraySize":1000,"runs":0.009,"arraytype":"Almost-Sorted-0.33","adaptiveSortExecutionTime":7,"insertionSortExecutionTime":90,"shellSortExecutionTime":29,"heapSortExecutionTime":69,"mergeSortExecutionTime":32,"quickSortExecutionTime":12,"parallelMergeSortExecutionTime":10,"parallelQuickSortExecutionTime":9}
{"arraySize":1000,"runs":0.01,"arraytype":"Almost-Sorted-0.33","adaptiveSortExecutionTime":8,"insertionSortExecutionTime":88,"shellSortExecutionTime":88,"heapSortExecutionTime":81,"mergeSortExecutionTime":41,"quickSortExecutionTime":12,"parallelMergeSortExecutionTime":11,"parallelQuickSortExecutionTime":9}
{"arraySize":1000,"runs":0.008,"arraytype":"Almost-Sorted-0.33","adaptiveSortExecutionTime":7,"insertionSortExecutionTime":88,"shellSortExecutionTime":28,"heapSortExecutionTime":71,"mergeSortExecutionTime":36,"quickSortExecutionTime":12,"parallelMergeSortExecutionTime":10,"parallelQuickSortExecutionTime":8}
{"arraySize":1000,"runs":0.007,"arraytype":"Almost-Sorted-0.33","adaptiveSortExecutionTime":7,"insertionSortExecutionTime":85,"shellSortExecutionTime":28,"heapSortExecutionTime":69,"mergeSortExecutionTime":31,"quickSortExecutionTime":12,"parallelMergeSortExecutionTime":10,"parallelQuickSortExecutionTime":8}
{"arraySize":1000,"runs":0.011,"arraytype":"Almost-Sorted-0.33","adaptiveSortExecutionTime":7,"insertionSortExecutionTime":85,"shellSortExecutionTime":28,"heapSortExecutionTime":69,"mergeSortExecutionTime":35,"quickSortExecutionTime":11,"parallelMergeSortExecutionTime":11,"parallelQuickSortExecutionTime":9}
{"arraySize":1000,"runs":0.009,"arraytype":"Almost-Sorted-0.33","adaptiveSortExecutionTime":7,"insertionSortExecutionTime":90,"shellSortExecutionTime":29,"heapSortExecutionTime":71,"mergeSortExecutionTime":31,"quickSortExecutionTime":12,"parallelMergeSortExecutionTime":11,"parallelQuickSortExecutionTime":9}
{"arraySize":1000,"runs":0.012,"arraytype":"Almost-Sorted-0.33","adaptiveSortExecutionTime":7,"insertionSortExecutionTime":88,"shellSortExecutionTime":27,"heapSortExecutionTime":70,"mergeSortExecutionTime":32,"quickSortExecutionTime":11,"parallelMergeSortExecutionTime":11,"parallelQuickSortExecutionTime":8}
{"arraySize":1000,"runs":0.008,"arraytype":"Almost-Sorted-0.33","adaptiveSortExecutionTime":7,"insertionSortExecutionTime":89,"shellSortExecutionTime":28,"heapSortExecutionTime":69,"mergeSortExecutionTime":31,"quickSortExecutionTime":11,"parallelMergeSortExecutionTime":11,"parallelQuickSortExecutionTime":8}
{"arraySize":1000,"runs":0.01,"arraytype":"Almost-Sorted-0.33","adaptiveSortExecutionTime":12,"insertionSortExecutionTime":109,"shellSortExecutionTime":30,"heapSortExecutionTime":84,"mergeSortExecutionTime":47,"quickSortExecutionTime":15,"parallelMergeSortExecutionTime":15,"parallelQuickSortExecutionTime":14}
{"arraySize":1000,"runs":0.009,"arraytype":"Almost-Sorted-0.33","adaptiveSortExecutionTime":7,"insertionSortExecutionTime":116,"shellSortExecutionTime":50,"heapSortExecutionTime":84,"mergeSortExecutionTime":32,"quickSortExecutionTime":12,"parallelMergeSortExecutionTime":12,"parallelQuickSortExecutionTime":9}
{"arraySize":1000,"runs":0.009,"arraytype":"Almost-Sorted-0.33","adaptiveSortExecutionTime":7,"insertionSortExecutionTime":105,"shellSortExecutionTime":41,"heapSortExecutionTime":84,"mergeSortExecutionTime":30,"quickSortExecutionTime":11,"parallelMergeSortExecutionTime":11,"parallelQuickSortExecutionTime":25}
{"arraySize":1000,"runs":0.008,"arraytype":"Almost-Sorted-0.33","adaptiveSortExecutionTime":10,"insertionSortExecutionTime":83,"shellSortExecutionTime":27,"heapSortExecutionTime":101,"mergeSortExecutionTime":67,"quickSortExecutionTime":11,"parallelMergeSortExecutionTime":10,"parallelQuickSortExecutionTime":8}
{"arraySize":1000,"runs":0.008,"arraytype":"Almost-Sorted-0.33","adaptiveSortExecutionTime":7,"insertionSortExecutionTime":139,"shellSortExecutionTime":41,"heapSortExecutionTime":65,"mergeSortExecutionTime":30,"quickSortExecutionTime":11,"parallelMergeSortExecutionTime":10,"parallelQuickSortExecutionTime":8}
{"arraySize":1000,"runs":0.012,"arraytype":"Almost-Sorted-0.33","adaptiveSortExecutionTime":7,"insertionSortExecutionTime":82,"shellSortExecutionTime":28,"heapSortExecutionTime":65,"mergeSortExecutionTime":29,"quickSortExecutionTime":11,"parallelMergeSortExecutionTime":10,"parallelQuickSortExecutionTime":8}
{"arraySize":1000,"runs":0.012,"arraytype":"Almost-Sorted-0.33","adaptiveSortExecutionTime":7,"insertionSortExecutionTime":83,"shellSortExecutionTime":26,"heapSortExecutionTime":66,"mergeSortExecutionTime":30,"quickSortExecutionTime":11,"parallelMergeSortExecutionTime":9,"parallelQuickSortExecutionTime":8}
{"arraySize":1000,"runs":0.009,"arraytype":"Almost-Sorted-0.33","adaptiveSortExecutionTime":9,"insertionSortExecutionTime":88,"shellSortExecutionTime":28,"heapSortExecutionTime":126,"mergeSortExecutionTime":103,"quickSortExecutionTime":13,"parallelMergeSortExecutionTime":10,"parallelQuickSortExecutionTime":9}
{"arraySize":1000,"runs":0.007,"arraytype":"Almost-Sorted-0.33","adaptiveSortExecutionTime":26,"insertionSortExecutionTime":86,"shellSortExecutionTime":26,"heapSortExecutionTime":65,"mergeSortExecutionTime":29,"quickSortExecutionTime":11,"parallelMergeSortExecutionTime":10,"parallelQuickSortExecutionTime":9}
{"arraySize":1000,"runs":0.012,"arraytype":"Almost-Sorted-0.33","adaptiveSortExecutionTime":7,"insertionSortExecutionTime":85,"shellSortExecutionTime":47,"heapSortExecutionTime":82,"mergeSortExecutionTime":29,"quickSortExecutionTime":11,"parallelMergeSortExecutionTime":10,"parallelQuickSortExecutionTime":8}
{"arraySize":1000,"runs":0.009,"arraytype":"Almost-Sorted-0.33","adaptiveSortExecutionTime":7,"insertionSortExecutionTime":157,"shellSortExecutionTime":26,"heapSortExecutionTime":65,"mergeSortExecutionTime":29,"quickSortExecutionTime":11,"parallelMergeSortExecutionTime":10,"parallelQuickSortExecutionTime":8}
{"arraySize":1000,"runs":0.007,"arraytype":"Almost-Sorted-0.33","adaptiveSortExecutionTime":7,"insertionSortExecutionTime":86,"shellSortExecutionTime":27,"heapSortExecutionTime":65,"mergeSortExecutionTime":29,"quickSortExecutionTime":10,"parallelMergeSortExecutionTime":9,"parallelQuickSortExecutionTime":8}
{"arraySize":1000,"runs":0.009,"arraytype":"Almost-Sorted-0.33","adaptiveSortExecutionTime":7,"insertionSortExecutionTime":84,"shellSortExecutionTime":27,"heapSortExecutionTime":65,"mergeSortExecutionTime":50,"quickSortExecutionTime":46,"parallelMergeSortExecutionTime":10,"parallelQuickSortExecutionTime":8}
{"arraySize":1000,"runs":0.011,"arraytype":"Almost-Sorted-0.33","adaptiveSortExecutionTime":7,"insertionSortExecutionTime":104,"shellSortExecutionTime":62,"heapSortExecutionTime":104,"mergeSortExecutionTime":44,"quickSortExecutionTime":11,"parallelMergeSortExecutionTime":10,"parallelQuickSortExecutionTime":8}
{"arraySize":1000,"runs":0.008,"arraytype":"Almost-Sorted-0.33","adaptiveSortExecutionTime":7,"insertionSortExecutionTime":85,"shellSortExecutionTime":26,"heapSortExecutionTime":65,"mergeSortExecutionTime":29,"quickSortExecutionTime":11,"parallelMergeSortExecutionTime":9,"parallelQuickSortExecutionTime":8}
{"arraySize":1000,"runs":0.009,"arraytype":"Almost-Sorted-0.33","adaptiveSortExecutionTime":7,"insertionSortExecutionTime":86,"shellSortExecutionTime":26,"heapSortExecutionTime":67,"mergeSortExecutionTime":29,"quickSortExecutionTime":11,"parallelMergeSortExecutionTime":30,"parallelQuickSortExecutionTime":25}
{"arraySize":1000,"runs":0.006,"arraytype":"Almost-Sorted-0.33","adaptiveSortExecutionTime":7,"insertionSortExecutionTime":81,"shellSortExecutionTime":26,"heapSortExecutionTime":157,"mergeSortExecutionTime":62,"quickSortExecutionTime":11,"parallelMergeSortExecutionTime":9,"parallelQuickSortExecutionTime":27}
{"arraySize":1000,"runs":0.005,"arraytype":"Almost-Sorted-0.33","adaptiveSortExecutionTime":7,"insertionSortExecutionTime":82,"shellSortExecutionTime":26,"heapSortExecutionTime":65,"mergeSortExecutionTime":29,"quickSortExecutionTime":11,"parallelMergeSortExecutionTime":9,"parallelQuickSortExecutionTime":8}
{"arraySize":1000,"runs":0.009,"arraytype":"Almost-Sorted-0.33","adaptiveSortExecutionTime":7,"insertionSortExecutionTime":84,"shellSortExecutionTime":26,"heapSortExecutionTime":65,"mergeSortExecutionTime":29,"quickSortExecutionTime":11,"parallelMergeSortExecutionTime":10,"parallelQuickSortExecutionTime":8}
{"arraySize":1000,"runs":0.012,"arraytype":"Almost-Sorted-0.33","adaptiveSortExecutionTime":7,"insertionSortExecutionTime":88,"shellSortExecutionTime":28,"heapSortExecutionTime":103,"mergeSortExecutionTime":31,"quickSortExecutionTime":27,"parallelMergeSortExecutionTime":10,"parallelQuickSortExecutionTime":9}
{"arraySize":1000,"runs":0.007,"arraytype":"Almost-Sorted-0.33","adaptiveSortExecutionTime":7,"insertionSortExecutionTime":84,"shellSortExecutionTime":27,"heapSortExecutionTime":65,"mergeSortExecutionTime":29,"quickSortExecutionTime":11,"parallelMergeSortExecutionTime":9,"parallelQuickSortExecutionTime":8}
{"arraySize":1000,"runs":0.015,"arraytype":"Almost-Sorted-0.33","adaptiveSortExecutionTime":7,"insertionSortExecutionTime":82,"shellSortExecutionTime":26,"heapSortExecutionTime":66,"mergeSortExecutionTime":29,"quickSortExecutionTime":32,"parallelMergeSortExecutionTime":10,"parallelQuickSortExecutionTime":25}
{"arraySize":1000,"runs":0.01,"arraytype":"Almost-Sorted-0.33","adaptiveSortExecutionTime":7,"insertionSortExecutionTime":87,"shellSortExecutionTime":27,"heapSortExecutionTime":103,"mergeSortExecutionTime":30,"quickSortExecutionTime":11,"parallelMergeSortExecutionTime":9,"parallelQuickSortExecutionTime":7}
{"arraySize":1000,"runs":0.008,"arraytype":"Almost-Sorted-0.33","adaptiveSortExecutionTime":7,"insertionSortExecutionTime":125,"shellSortExecutionTime":58,"heapSortExecutionTime":79,"mergeSortExecutionTime":29,"quickSortExecutionTime":11,"parallelMergeSortExecutionTime":9,"parallelQuickSortExecutionTime":8}
{"arraySize":1000,"runs":0.01,"arraytype":"Almost-Sorted-0.33","adaptiveSortExecutionTime":7,"insertionSortExecutionTime":97,"shellSortExecutionTime":26,"heapSortExecutionTime":65,"mergeSortExecutionTime":30,"quickSortExecutionTime":11,"parallelMergeSortExecutionTime":10,"parallelQuickSortExecutionTime":8}
{"arraySize":1000,"runs":0.01,"arraytype":"Almost-Sorted-0.33","adaptiveSortExecutionTime":7,"insertionSortExecutionTime":84,"shellSortExecutionTime":26,"heapSortExecutionTime":65,"mergeSortExecutionTime":29,"quickSortExecutionTime":10,"parallelMergeSortExecutionTime":9,"parallelQuickSortExecutionTime":8}
{"arraySize":1000,"runs":0.005,"arraytype":"Almost-Sorted-0.33","adaptiveSortExecutionTime":7,"insertionSortExecutionTime":84,"shellSortExecutionTime":26,"heapSortExecutionTime":65,"mergeSortExecutionTime":69,"quickSortExecutionTime":27,"parallelMergeSortExecutionTime":24,"parallelQuickSortExecutionTime":8}
{"arraySize":1000,"runs":0.008,"arraytype":"Almost-Sorted-0.33","adaptiveSortExecutionTime":7,"insertionSortExecutionTime":124,"shellSortExecutionTime":62,"heapSortExecutionTime":66,"mergeSortExecutionTime":30,"quickSortExecutionTime":11,"parallelMergeSortExecutionTime":10,"parallelQuickSortExecutionTime":8}
{"arraySize":1000,"runs":0.01,"arraytype":"Almost-Sorted-0.33","adaptiveSortExecutionTime":7,"insertionSortExecutionTime":86,"shellSortExecutionTime":27,"heapSortExecutionTime":65,"mergeSortExecutionTime":29,"quickSortExecutionTime":11,"parallelMergeSortExecutionTime":10,"parallelQuickSortExecutionTime":8}
{"arraySize":1000,"runs":0.01,"arraytype":"Almost-Sorted-0.33","adaptiveSortExecutionTime":7,"insertionSortExecutionTime":86,"shellSortExecutionTime":28,"heapSortExecutionTime":67,"mergeSortExecutionTime":30,"quickSortExecutionTime":11,"parallelMergeSortExecutionTime":9,"parallelQuickSortExecutionTime":8}
{"arraySize":1000,"runs":0.009,"arraytype":"Almost-Sorted-0.33","adaptiveSortExecutionTime":26,"insertionSortExecutionTime":90,"shellSortExecutionTime":28,"heapSortExecutionTime":67,"mergeSortExecutionTime":30,"quickSortExecutionTime":11,"parallelMergeSortExecutionTime":10,"parallelQuickSortExecutionTime":10}
{"arraySize":1000,"runs":0.008,"arraytype":"Almost-Sorted-0.33","adaptiveSortExecutionTime":7,"insertionSortExecutionTime":107,"shellSortExecutionTime":63,"heapSortExecutionTime":69,"mergeSortExecutionTime":31,"quickSortExecutionTime":12,"parallelMergeSortExecutionTime":11,"parallelQuickSortExecutionTime":9}
{"arraySize":1000,"runs":0.007,"arraytype":"Almost-Sorted-0.33","adaptiveSortExecutionTime":10,"insertionSortExecutionTime":101,"shellSortExecutionTime":27,"heapSortExecutionTime":66,"mergeSortExecutionTime":30,"quickSortExecutionTime":13,"parallelMergeSortExecutionTime":12,"parallelQuickSortExecutionTime":31}
{"arraySize":1000,"runs":0.009,"arraytype":"Almost-Sorted-0.33","adaptiveSortExecutionTime":7,"insertionSortExecutionTime":85,"shellSortExecutionTime":27,"heapSortExecutionTime":68,"mergeSortExecutionTime":30,"quickSortExecutionTime":11,"parallelMergeSortExecutionTime":10,"parallelQuickSortExecutionTime":9}
{"arraySize":1000,"runs":0.011,"arraytype":"Almost-Sorted-0.33","adaptiveSortExecutionTime":7,"insertionSortExecutionTime":86,"shellSortExecutionTime":26,"heapSortExecutionTime":65,"mergeSortExecutionTime":28,"quickSortExecutionTime":12,"parallelMergeSortExecutionTime":9,"parallelQuickSortExecutionTime":8}
{"arraySize":1000,"runs":0.007,"arraytype":"Almost-Sorted-0.33","adaptiveSortExecutionTime":7,"insertionSortExecutionTime":82,"shellSortExecutionTime":26,"heapSortExecutionTime":66,"mergeSortExecutionTime":30,"quickSortExecutionTime":11,"parallelMergeSortExecutionTime":10,"parallelQuickSortExecutionTime":8}
{"arraySize":1000,"runs":0.011,"arraytype":"Almost-Sorted-0.33","adaptiveSortExecutionTime":8,"insertionSortExecutionTime":84,"shellSortExecutionTime":26,"heapSortExecutionTime":65,"mergeSortExecutionTime":48,"quickSortExecutionTime":26,"parallelMergeSortExecutionTime":10,"parallelQuickSortExecutionTime":9}
{"arraySize":1000,"runs":0.009,"arraytype":"Almost-Sorted-0.33","adaptiveSortExecutionTime":7,"insertionSortExecutionTime":88,"shellSortExecutionTime":27,"heapSortExecutionTime":104,"mergeSortExecutionTime":30,"quickSortExecutionTime":11,"parallelMergeSortExecutionTime":10,"parallelQuickSortExecutionTime":8}
{"arraySize":1000,"runs":0.01,"arraytype":"Almost-Sorted-0.33","adaptiveSortExecutionTime":7,"insertionSortExecutionTime":126,"shellSortExecutionTime":27,"heapSortExecutionTime":68,"mergeSortExecutionTime":30,"quickSortExecutionTime":11,"parallelMergeSortExecutionTime":10,"parallelQuickSortExecutionTime":9}
{"arraySize":1000,"runs":0.01,"arraytype":"Almost-Sorted-0.33","adaptiveSortExecutionTime":7,"insertionSortExecutionTime":87,"shellSortExecutionTime":27,"heapSortExecutionTime":67,"mergeSortExecutionTime":30,"quickSortExecutionTime":11,"parallelMergeSortExecutionTime":10,"parallelQuickSortExecutionTime":8}
{"arraySize":1000,"runs":0.016,"arraytype":"Almost-Sorted-0.33","adaptiveSortExecutionTime":7,"insertionSortExecutionTime":82,"shellSortExecutionTime":27,"heapSortExecutionTime":67,"mergeSortExecutionTime":30,"quickSortExecutionTime":11,"parallelMergeSortExecutionTime":9,"parallelQuickSortExecutionTime":8}
{"arraySize":1000,"runs":0.012,"arraytype":"Almost-Sorted-0.33","adaptiveSortExecutionTime":7,"insertionSortExecutionTime":91,"shellSortExecutionTime":28,"heapSortExecutionTime":68,"mergeSortExecutionTime":67,"quickSortExecutionTime":12,"parallelMergeSortExecutionTime":10,"parallelQuickSortExecutionTime":8}
{"arraySize":1000,"runs":0.008,"arraytype":"Almost-Sorted-0.33","adaptiveSortExecutionTime":7,"insertionSortExecutionTime":86,"shellSortExecutionTime":64,"heapSortExecutionTime":66,"mergeSortExecutionTime":30,"quickSortExecutionTime":30,"parallelMergeSortExecutionTime":11,"parallelQuickSortExecutionTime":23}
{"arraySize":1000,"runs":0.009,"arraytype":"Almost-Sorted-0.33","adaptiveSortExecutionTime":7,"insertionSortExecutionTime":90,"shellSortExecutionTime":28,"heapSortExecutionTime":67,"mergeSortExecutionTime":30,"quickSortExecutionTime":11,"parallelMergeSortExecutionTime":10,"parallelQuickSortExecutionTime":9}
{"arraySize":1000,"runs":0.008,"arraytype":"Almost-Sorted-0.33","adaptiveSortExecutionTime":7,"insertionSortExecutionTime":84,"shellSortExecutionTime":27,"heapSortExecutionTime":67,"mergeSortExecutionTime":30,"quickSortExecutionTime":11,"parallelMergeSortExecutionTime":10,"parallelQuickSortExecutionTime":8}
{"arraySize":1000,"runs":0.009,"arraytype":"Almost-Sorted-0.33","adaptiveSortExecutionTime":8,"insertionSortExecutionTime":90,"shellSortExecutionTime":30,"heapSortExecutionTime":70,"mergeSortExecutionTime":32,"quickSortExecutionTime":12,"parallelMergeSortExecutionTime":11,"parallelQuickSortExecutionTime":9}
{"arraySize":1000,"runs":0.011,"arraytype":"Almost-Sorted-0.33","adaptiveSortExecutionTime":7,"insertionSortExecutionTime":82,"shellSortExecutionTime":28,"heapSortExecutionTime":68,"mergeSortExecutionTime":30,"quickSortExecutionTime":11,"parallelMergeSortExecutionTime":11,"parallelQuickSortExecutionTime":9}
{"arraySize":1000,"runs":0.007,"arraytype":"Almost-Sorted-0.33","adaptiveSortExecutionTime":7,"insertionSortExecutionTime":125,"shellSortExecutionTime":42,"heapSortExecutionTime":83,"mergeSortExecutionTime":30,"quickSortExecutionTime":11,"parallelMergeSortExecutionTime":9,"parallelQuickSortExecutionTime":8}
{"arraySize":1000,"runs":0.005,"arraytype":"Almost-Sorted-0.33","adaptiveSortExecutionTime":7,"insertionSortExecutionTime":87,"shellSortExecutionTime":28,"heapSortExecutionTime":105,"mergeSortExecutionTime":30,"quickSortExecutionTime":30,"parallelMergeSortExecutionTime":10,"parallelQuickSortExecutionTime":23}
{"arraySize":1000,"runs":0.008,"arraytype":"Almost-Sorted-0.33","adaptiveSortExecutionTime":8,"insertionSortExecutionTime":100,"shellSortExecutionTime":28,"heapSortExecutionTime":67,"mergeSortExecutionTime":30,"quickSortExecutionTime":11,"parallelMergeSortExecutionTime":10,"parallelQuickSortExecutionTime":8}
{"arraySize":1000,"runs":0.008,"arraytype":"Almost-Sorted-0.33","adaptiveSortExecutionTime":7,"insertionSortExecutionTime":90,"shellSortExecutionTime":29,"heapSortExecutionTime":66,"mergeSortExecutionTime":30,"quickSortExecutionTime":11,"parallelMergeSortExecutionTime":10,"parallelQuickSortExecutionTime":8}
{"arraySize":1000,"runs":0.009,"arraytype":"Almost-Sorted-0.33","adaptiveSortExecutionTime":7,"insertionSortExecutionTime":88,"shellSortExecutionTime":28,"heapSortExecutionTime":67,"mergeSortExecutionTime":30,"quickSortExecutionTime":30,"parallelMergeSortExecutionTime":11,"parallelQuickSortExecutionTime":25}
{"arraySize":1000,"runs":0.005,"arraytype":"Almost-Sorted-0.33","adaptiveSortExecutionTime":7,"insertionSortExecutionTime":85,"shellSortExecutionTime":26,"heapSortExecutionTime":105,"mergeSortExecutionTime":30,"quickSortExecutionTime":11,"parallelMergeSortExecutionTime":11,"parallelQuickSortExecutionTime":8}
